Workbook
Name Z_16822E29_7107_44E0_879B_999A9E1047E8_.wvu.PrintArea: 'Aluminium Foil'!$A$1:$I$97
Name Z_16822E29_7107_44E0_879B_999A9E1047E8_.wvu.PrintArea: Bagasse!$A$1:$H$97

Sheet Summary Sheet
A1: Neeyog Packaging
A2: OFF: 20, Gr Floor,Sidhpura Ind.Estate,S.V.Road,Gaiwadi Rd,Near Agilus Diagnostic Center,Goregaon(W),Mum- 062
A3: Phone : 022-28760709 Mobile 9867607003 Email:neeyog@gmail.com
A4: www.neeyog.com/www.neeeyog.net/www.indiamart.com/neeyogpackaging/www.facebook.com/neeyogpack
A7: PRODUCTS SUMMARY LIST | C7: Date 16.06.2026
A8: SR No | B8: Description of the Products
A9: 1 | B9: ALUMINIUM FOIL ROLL & CONTAINERS | C9: 1-2
A10: =A9+1 -> 2 | B10: BIODEGRADABLE BAGASSE PRODUCTS | C10: 3-6
A11: =A10+1 -> 3 | B11: PAPER PRODUCTS (PLATE, BOWL, GLASS, BOXES & CONTAINER) | C11: 7-8
A12: =A11+1 -> 4 | B12: OLIVE REFERENCE | C12: 9-10
A13: =A12+1 -> 5 | B13: OLIVE PAPER PRODUCTS | C13: 11-15
A14: =A13+1 -> 6 | B14: PACKNSERVE | C14: 16-17
A15: =A14+1 -> 7 | B15: JP PRODUCTS | C15: 18-19
A16: =A15+1 -> 8 | B16: PS | C16: 20-23
A17: =A16+1 -> 9 | B17: PAPER BAGS SOS, CUTSHEETS | C17: 24
A18: =A17+1 -> 10 | B18: PAPER CARRY BAGS WITH IMAGES | C18: 25
A19: =A18+1 -> 11 | B19: PAPER CARRY BAGS | C19: 26
A20: =A19+1 -> 12 | B20: ARECALEAF BIODEGRADABLE PRODUCTS | C20: 27
A21: =A20+1 -> 13 | B21: TISSUE PAPER | C21: 28-29
... A43: =A42+1 -> 35 | B43: LAMINATED POUCHES | C43: 67-68
A48: Terms & Conditions
A49: 1. The Prices in this list are Ex Mumbai Freight charges will be Extra for outstation deliveries
A50: 2. The Gst charges will be charged as per price list mentioned
A51: 3. The above prices are subject to change
A52: 4. Payment within 30days incase of delay interest @18% P.a will be applicable Extra
A54: For Placing Orders
A55: Pranali/Ranjeet | B55: Mob no:- 8879559946
B56: Email:- orders@neeyog.com/neeyog@gmail.com
A58: For Sales Enquiry
A59: Madhuri | B59: Mob no:- 7045402654
A60: Pranali | B60: Mob no:-9867607005
B62: Email:- enquiry@neeyog.com/neeyog@gmail.com
A107: =A42+1 -> 35 | B107: PS MOUSSE CUPS | C107: 34-36
A108: =A107+1 -> 36 | B108: BIOPAC PRODUCTS | C108: 38

Sheet Aluminium Foil
A1: Neeyog Packaging | J1: summary sheet
A2: OFF: 20, Gr Floor,Sidhpura Ind.Estate,S.V.Road,Gaiwadi Rd,Near Agilus Diagnostic Center,Goregaon(W),Mum- 062 | T2: Mamtora | U2: MM
A3: Phone : 022-28760709 Mobile 9867607003 Email:neeyog@gmail.com | T3: Bhiwandi | U3: BW
A4: www.neeyog.com/www.neeyog.net/www.indiamart.com/neeyogpackaging/www.facebook.com/neeyogpack | P4: FM | R4: 1-2 DAY | T4: Shop | U4: SH
P5: LS | Q5: Limited Stock | R5: 3-4 DAYS | T5: Vapi | U5: VP
A6: Wholesale Aluminium Foil Wrap & Containers Price List | G6: ='Summary Sheet'!C7 -> Date 16.06.2026 | P6: APO | Q6: As per Order | R6: 15-20 DAYS | T6: Bansi | U6: BN
A7: Sr. No. | B7: Code | C7: HSN CODE | D7: Description (HSN Code 76071991) | E7: Rate Excl Gst | F7: Rate Incl Gst | G7: Per Pcs | H7: Std Pack | I7: GST Rate | J7: Primary Godown | K7: Movement | L7: Box Size | M7: Tally Name
D8: Hindalco Superwrap Foil
A9: 1 | B9: FR01SW | C9: 76071991 | D9: 9MTR Foil Wrap (SW) | E9: 55.5 | F9: =E9+E9*I9 -> 65.49 | G9: Pcs | H9: 50 | I9: 0.18 | J9: VP | K9: FM
A10: =A9+1 -> 2 | B10: FR02SW | C10: 76071991 | D10: 18MTR Foil Wrap (SW) 290mm | E10: 105.41 | F10: =E10+E10*I10 -> 124.3838 | G10: Pcs | H10: 50 | I10: 0.18 | J10: VP | K10: FM
A11: =A10+1 -> 3 | B11: FR01SW | C11: 76071991 | D11: 72MTR Foil Wrap (SW) 290mm | E11: 352.84 | F11: =E11+E11*I11 -> 416.3512 | G11: Pcs | H11: 25 | I11: 0.18 | J11: VP | K11: FM
A12: =A11+1 -> 4 | B12: FR02SW | C12: 76071991 | D12: 1KG Foil Wrap Box (NW) (SW) | E12: 525.08 | F12: =E12+E12*I12 -> 619.5944 | G12: Pcs | H12: 25 | I12: 0.18 | J12: VP | K12: FM
A14: 1 | B14: FR01FW | D14: 9MTR Foil Wrap (FW) | E14: 57.7 | F14: =E14+E14*I14 -> 68.086 | G14: Pcs | H14: 50 | I14: 0.18
A15: 2 | B15: FR02FW | D15: 18MTR Foil Wrap STD (FW) | E15: 108.6 | F15: =E15+E15*I15 -> 128.148 | G15: Pcs | H15: 50 | I15: 0.18
A16: 3 | B16: FR03FW | D16: 72MTR Foil Wrap (FW) | E16: 357.6 | F16: =E16+E16*I16 -> 421.968 | G16: Pcs | H16: 25 | I16: 0.18
A17: 4 | B17: FR04FW | D17: 1KG Foil Wrap Box (FW) | E17: 528.6 | F17: =E17+E17*I17 -> 623.748 | G17: Pcs | H17: 25 | I17: 0.18
D18: Minda Foil (HSN Code 76071991)
A19: 1 | C19: 76071991 | D19: 18MTR Foil Wrap (MI) | E19: 95.2 | F19: =E19+E19*I19 -> 112.336 | G19: Pcs | H19: 100 | I19: 0.18 | J19: VP | K19: FM
A20: =A19+1 -> 2 | C20: 76071991 | D20: 72 No(35 Mtr) Foil wrap | E20: 198 | F20: =E20+E20*I20 -> 233.64 | G20: Pcs | H20: 25 | I20: 0.18 | J20: - | K20: APO
A21: =A20+1 -> 3 | C21: 76071991 | D21: 72mtr Foil wrap | E21: 330 | F21: =E21+E21*I21 -> 389.4 | G21: Pcs | H21: 25 | I21: 0.18 | J21: - | K21: APO
A22: =A21+1 -> 4 | C22: 76071991 | D22: 1KG Foil Wrap (GW) (MI) | E22: 390.5 | F22: =E22+E22*I22 -> 460.79 | G22: Pcs | H22: 25 | I22: 0.18 | J22: BW | K22: FM
A23: =A22+1 -> 5 | C23: 76071991 | D23: 1kg Net 18mic | E23: 528 | F23: =E23+E23*I23 -> 623.04 | G23: Pcs | H23: 25 | I23: 0.18 | J23: - | K23: APO
D24: PNS Foil Wrap (HSN Code 76071991)
A25: 1 | D25: 18Mtr PNS Wrapp Fresh Foil Wrap * 100pcs | E25: 78 | F25: =E25+E25*I25 -> 92.04 | G25: Pcs | H25: 100 | I25: 0.18 | J25: VP | K25: FM
A26: 2 | D26: 72Mtr PNS Wrapp Fresh Foil Wrap * 25pcs | E26: 280 | F26: =E26+E26*I26 -> 330.4 | G26: Pcs | H26: 25 | I26: 0.18 | J26: VP | K26: FM
D27: WrappFresh Foil Wrap (HSN Code 76071991)
A28: 1 | C28: 76071991 | D28: Heavy Duty 14Mic WrappFresh Foil Wrap | E28: 199.15 | F28: =E28+E28*I28 -> 234.997 | G28: Pcs | H28: 25 | I28: 0.18 | J28: VP | K28: FM
A29: 2 | C29: 76071991 | D29: 18MTR Wrapp Fresh Foil Wrap (18Special) | E29: 53.4 | F29: =E29+E29*I29 -> 63.012 | G29: Pcs | H29: 50 | I29: 0.18 | J29: VP | K29: FM
B30: L x W x D | D30: Minda Foil Container (HSN Code 76151030) | E30: Rate Excl Gst | F30: Rate Incl Gst | G30: Per Pcs | H30: Std Pack | I30: GST Rate
A31: 1 | B31: 79X79X37 | C31: 76151030 | D31: 120ML Foil Cont (MI) | E31: 1.1 | F31: =E31+E31*I31 -> 1.155 | G31: Pcs | H31: 5000 | I31: 0.05 | J31: BW | K31: FM
A32: =A31+1 -> 2 | B32: 79X79X38 | C32: 76151030 | D32: 210ml Moments /Alu Fresh Foil Cont (Light) | E32: 1.4 | F32: =E32+E32*I32 -> 1.47 | G32: Pcs | H32: 2000 | I32: 0.05 | J32: BW | K32: APO
A33: 3 | B33: 79X79X38 | D33: 210ml Moments /Alu Fresh Foil Cont (Heavy) | E33: 1.84 | F33: =E33+E33*I33 -> 1.932 | G33: Pcs | H33: 2000 | I33: 0.05 | J33: BW | K33: APO
A34: =A33+1 -> 4 | B34: 130X103X43 | C34: 76151030 | D34: 250ML Foil Cont (MI) | E34: 1.44 | F34: =E34+E34*I34 -> 1.512 | G34: Pcs | H34: 2000 | I34: 0.05 | J34: BW | K34: FM
A35: 5 | B35: 142X117X45 | C35: 76151030 | D35: 450ML Foil Cont (MI) | E35: 1.92 | F35: =E35+E35*I35 -> 2.016 | G35: Pcs | H35: 1500 | I35: 0.05 | J35: BW | K35: FM
A36: =A35+1 -> 6 | B36: 187X131X48 | C36: 76151030 | D36: 600ML Foil Cont (MI) (Oval) | E36: 2.2 | F36: =E36+E36*I36 -> 2.31 | G36: Pcs | H36: 1000 | I36: 0.05 | J36: BW | K36: FM
A37: 7 | B37: 203X138X43 | C37: 76151030 | D37: 750ML Foil Cont (MI) | E37: 2.94 | F37: =E37+E37*I37 -> 3.087 | G37: Pcs | H37: 1000 | I37: 0.05 | J37: BW | K37: FM
A38: 8 | B38: 197X105X49 | C38: 76151030 | D38: 660ml Moments Foil Cont | E38: 2.94 | F38: =E38+E38*I38 -> 3.087 | G38: Pcs | H38: 1000 | I38: 0.05 | J38: BW | K38: APO
A39: 9 | B39: 277X177X38 | C39: 76151030 | D39: 3cp Minda Foil Cont | E39: 6 | F39: =E39+E39*I39 -> 6.3 | G39: Pcs | H39: 1200 | I39: 0.05 | J39: BW | K39: SM
A40: 10 | C40: 76151030 | D40: 4cp Minda Foil Cont (Heavy) | E40: 7.2 | F40: =E40+E40*I40 -> 7.56 | G40: Pcs | H40: 1200 | I40: 0.05 | J40: BW | K40: APO
A41: 11 | C41: 76151030 | D41: 4cp Minda Foil Cont (Light) | E41: 6 | F41: =E41+E41*I41 -> 6.3 | G41: Pcs | H41: 1200 | I41: 0.05 | J41: BW | K41: APO
B42: L x W x D | D42: Minda Foil Container Premium (HSN Code 76151030)
A43: 1 | B43: 130X103X43 | C43: 76151030 | D43: 250ml Moments Foil Cont (10no) Prem | E43: 2.48 | F43: =E43+E43*I43 -> 2.604 | G43: Pcs | H43: 2000 | I43: 0.05 | J43: BW | K43: APO
A44: =A43+1 -> 2 | B44: 142X117X45 | C44: 76151030 | D44: 450ml Moments Foil Cont (4no) Prem | E44: 3.3 | F44: =E44+E44*I44 -> 3.465 | G44: Pcs | H44: 1500 | I44: 0.05 | J44: BW | K44: APO
A45: =A44+1 -> 3 | B45: 203X138X43 | C45: 76151030 | D45: 750ml Moments Foil Cont (24no) Prem | E45: 4.95 | F45: =E45+E45*I45 -> 5.1975 | G45: Pcs | H45: 1000 | I45: 0.05 | J45: BW | K45: APO
B46: L x W x D | D46: Alufresh Foil Container (HSN Code 76151030)
A47: 1 | C47: 76151030 | D47: 250ml Alu Fresh Color Foil Cont (10no) | E47: 1.02 | F47: =E47+E47*I47 -> 1.071 | G47: Pcs | H47: 2000 | I47: 0.05 | J47: VP | K47: APO
A48: =A47+1 -> 2 | C48: 76151030 | D48: 450ml Alu Fresh Color Foil Cont (10no) | E48: 1.37 | F48: =E48+E48*I48 -> 1.4385 | G48: Pcs | H48: 1500 | I48: 0.05 | J48: VP | K48: APO
D49: Pet Lid For Foil Cont (4823)
A50: 1 | C50: 4823 | D50: 250ml Pet Lid | E50: 0.94 | F50: =E50+E50*I50 -> 1.1092 | G50: Pcs | H50: 2000 | I50: 0.18 | J50: BN | K50: SM
A51: =A50+1 -> 2 | C51: 4823 | D51: 450ml Pet Lid | E51: 1.2 | F51: =E51+E51*I51 -> 1.416 | G51: Pcs | H51: 1500 | I51: 0.18 | J51: BN | K51: SM
D52: FOIL PAPER LIDS (HSN Code 48239090) | E52: SBS/450Gsm | F52: Duplex/ 320Gsm | G52: Per | H52: Pack
A53: 1 | C53: 48239090 | D53: 750ml Lid For Aluminium Containers | E53: 105 | F53: 67 | G53: 100Pcs | H53: 100Pcs | I53: 0.18 | J53: MM | K53: FM
A54: =A53+1 -> 2 | C54: 48239090 | D54: 600ml Lid For Aluminium Containers | E54: 95 | F54: 55 | G54: 100Pcs | H54: 100Pcs | I54: 0.18 | J54: MM | K54: FM
A55: =A54+1 -> 3 | C55: 48239090 | D55: 450ml Lid For Aluminium Containers | E55: 75 | F55: 45 | G55: 100Pcs | H55: 100Pcs | I55: 0.18 | J55: MM | K55: FM
A56: =A55+1 -> 4 | C56: 48239090 | D56: 250ml Lid For Aluminium Containers | E56: 50 | F56: 32 | G56: 100Pcs | H56: 100Pcs | I56: 0.18 | J56: MM | K56: FM
A57: =A56+1 -> 5 | C57: 48239090 | D57: 180ml Lid For Aluminium Containers | E57: - | F57: 28 | G57: 100Pcs | H57: 100Pcs | I57: 0.18 | J57: MM | K57: FM
A58: =A57+1 -> 6 | C58: 48239090 | D58: 120ml Lid For Aluminium Containers | E58: - | F58: 25 | G58: 100Pcs | H58: 100Pcs | I58: 0.18 | J58: MM | K58: FM
A59: =A58+1 -> 7 | C59: 48239090 | D59: 1500 ml 9 x 9 Shallow Aluminum Cont LID only | E59: 2.4 | F59: - | G59: Pcs | H59: 100Pcs | I59: 0.18 | J59: MM | K59: FM
A60: =A59+1 -> 8 | C60: 48239090 | D60: 3CP Foil Container Lid | E60: 2.1 | F60: 1.35 | G60: Pcs | H60: 100Pcs | I60: 0.18 | J60: MM | K60: FM
A61: PAGE 1
B62: L x W x D | D62: Foil Container (Exclusive Products) (HSN Code 76151030)
A63: 1 | C63: 76151030 | D63: 140ML Foil Cont (HI) Muffin | F63: =E63+E63*I63 -> 0 | G63: Pcs | H63: 5000 | I63: 0.05 | J63: BW | K63: FM
B64: L x W x D | D64: Foil Container (Exclusive Products) (HSN Code 76151030)
A65: =A64+1 -> 1 | C65: 76151030 | D65: 180ML Foil Cont (NG) | E65: 1.9 | F65: =E65+E65*I65 -> 1.995 | G65: Pcs | H65: 3000 | I65: 0.05 | K65: APO
A66: =A65+1 -> 2 | C66: 76151030 | D66: 520ML Foil Cont (NG) | E66: 5.25 | F66: =E66+E66*I66 -> 5.5125 | G66: Pcs | H66: 1000 | I66: 0.05 | K66: APO
A67: =A66+1 -> 3 | C67: 76151030 | D67: 250ml Glass | E67: 2.55 | F67: =E67+E67*I67 -> 2.6775 | G67: Pcs | H67: 2000 | I67: 0.05 | K67: APO
A68: =A67+1 -> 4 | B68: 93X61X23 | C68: 76151030 | D68: 100ML Foil Cont (MI) | E68: 0.9 | F68: =E68+E68*I68 -> 0.945 | G68: Pcs | H68: 5000 | I68: 0.05 | J68: BW | K68: FM
A69: 5 | C69: 76151030 | D69: 140ML Foil Cont (MI) Muffin | E69: 1.48 | F69: =E69+E69*I69 -> 1.554 | G69: Pcs | H69: 5000 | I69: 0.05
A70: 6 | C70: 76151030 | D70: 900ml Foil Cont Minda | E70: 5.25 | F70: =E70+E70*I70 -> 5.5125 | G70: Pcs | H70: 800 | I70: 0.05 | K70: APO
A71: =A70+1 -> 7 | B71: 244X244X43 | C71: 76151030 | D71: 1500ML Shallow Foil cont (MI) 9x9 | E71: 12.1 | F71: =E71+E71*I71 -> 12.705 | G71: Pcs | H71: 200 | I71: 0.05 | J71: BW | K71: FM
A72: =A71+1 -> 8 | B72: 244X244X58 | C72: 76151030 | D72: 9X9 Deep Foil cont 2100ML (MI) | E72: 13.8 | F72: =E72+E72*I72 -> 14.49 | G72: Pcs | H72: 200 | I72: 0.05 | K72: SM
A73: =A72+1 -> 9 | B73: 320X262X63 | C73: 76151030 | D73: 3200ML Half Deep Foil Cont (MI) | E73: 20.7 | F73: =E73+E73*I73 -> 21.735 | G73: Pcs | H73: 100 | I73: 0.05 | J73: BW | K73: FM
A74: =A73+1 -> 10 | B74: 330X272X15 | C74: 76151030 | D74: 3200ML Foil Cont Lid (MI) | E74: 12.65 | F74: =E74+E74*I74 -> 13.2825 | G74: Pcs | H74: 100 | I74: 0.05 | J74: BW | K74: FM
A75: =A74+1 -> 11 | B75: 525X325X79 | C75: 76151030 | D75: 9000ML Full Deep Foil Cont (MI) | E75: 65.5 | F75: =E75+E75*I75 -> 68.775 | G75: Pcs | H75: 50 | I75: 0.05 | J75: BW | K75: FM
A76: =A75+1 -> 12 | B76: 536X314X19 | C76: 76151030 | D76: 9000ML Full Deep Foil Cont Lid (MI) | E76: 36.8 | F76: =E76+E76*I76 -> 38.64 | G76: Pcs | H76: 50 | I76: 0.05 | J76: BW | K76: FM
A77: =A76+1 -> 13 | B77: 187X167X44 | C77: 76151030 | D77: 7 INCH ROUND ,700 ML | E77: 5.1 | F77: =E77+E77*I77 -> 5.355 | G77: Pcs | H77: 500 | I77: 0.05 | K77: APO
A78: =A77+1 -> 14 | B78: 233X210X48 | C78: 76151030 | D78: 9 INCH ROUND ,1300 ML | E78: 8.75 | F78: =E78+E78*I78 -> 9.1875 | G78: Pcs | H78: 500 | I78: 0.05 | K78: APO
A79: =A78+1 -> 15 | C79: 39239090 | D79: 7" Lid PVC (HSN Code 39239090) | E79: 3.5 | F79: =E79+E79*I79 -> 4.13 | G79: Pcs | H79: 1000 | I79: 0.18 | K79: APO
A80: =A79+1 -> 16 | C80: 39239090 | D80: 9" Lid PVC (HSN Code 39239090) | E80: 4.65 | F80: =E80+E80*I80 -> 5.487 | G80: Pcs | H80: 1000 | I80: 0.18 | K80: APO
A81: =A80+1 -> 17 | C81: 76151030 | D81: AFC 1120(1000ml) | E81: 6.9 | F81: =E81+E81*I81 -> 7.245 | G81: Pcs | H81: 400 | I81: 0.05 | K81: APO
A82: =A81+1 -> 18 | C82: 76151030 | D82: AFC 83120(1105ml) | E82: 8.05 | F82: =E82+E82*I82 -> 8.4525 | G82: Pcs | H82: 400 | I82: 0.05 | K82: APO
A83: =A82+1 -> 19 | C83: 76151030 | D83: AFC83185(1800ml) | E83: 10.65 | F83: =E83+E83*I83 -> 11.1825 | G83: Pcs | H83: 400 | I83: 0.05 | K83: APO
A84: =A83+1 -> 20 | C84: 76151030 | D84: AFC83190(2100ml) | E84: 15.7 | F84: =E84+E84*I84 -> 16.485 | G84: Pcs | H84: 300 | I84: 0.05 | K84: SM
A85: =A84+1 -> 21 | C85: 76151030 | D85: AFC73365(3285ml) | E85: 18.4 | F85: =E85+E85*I85 -> 19.32 | G85: Pcs | H85: 100 | I85: 0.05 | K85: APO
A86: =A85+1 -> 22 | B86: 220x114x53 | C86: 76151030 | D86: AFC6A(670ml) | E86: 5.06 | F86: =E86+E86*I86 -> 5.313 | G86: Pcs | H86: 500 | I86: 0.05 | K86: APO
A87: =A86+1 -> 23 | C87: 76151030 | D87: Oval Roaster (7000 ml) | E87: 51.75 | F87: =E87+E87*I87 -> 54.3375 | G87: Pcs | H87: 100 | I87: 0.05 | K87: APO
A88: =A87+1 -> 24 | C88: 76151030 | D88: Rectangular Roaster (6350 ml) | E88: 51.75 | F88: =E88+E88*I88 -> 54.3375 | G88: Pcs | H88: 100 | I88: 0.05 | K88: APO
A89: =A88+1 -> 25 | C89: 76151030 | D89: AFC 6A Large (905 ml) | E89: 3.35 | F89: =E89+E89*I89 -> 3.5175 | G89: Pcs | H89: 1000 | I89: 0.05 | K89: APO
A90: =A89+1 -> 26 | C90: 76151030 | D90: 6550 Baby Platter (10 inch) | E90: 7.65 | F90: =E90+E90*I90 -> 8.0325 | G90: Pcs | H90: 150 | I90: 0.05 | K90: APO
A91: =A90+1 -> 27 | C91: 76151030 | D91: 6586 Small Platter (14 inch) | E91: 15.5 | F91: =E91+E91*I91 -> 16.275 | G91: Pcs | H91: 100 | I91: 0.05 | K91: APO
A92: =A91+1 -> 28 | C92: 76151030 | D92: 65180 Medium Platter (17 inch) | E92: 33.35 | F92: =E92+E92*I92 -> 35.0175 | G92: Pcs | H92: 50 | I92: 0.05 | K92: APO
A93: =A92+1 -> 29 | C93: 76151030 | D93: 65220 Large Platter (22 inch) | E93: 57.5 | F93: =E93+E93*I93 -> 60.375 | G93: Pcs | H93: 50 | I93: 0.05 | K93: APO
A94: =A93+1 -> 30 | C94: 76151030 | D94: 6" Round Flan Dish (With Holes) | E94: 3.7 | F94: =E94+E94*I94 -> 3.885 | G94: Pcs | H94: 500 | I94: 0.05 | K94: APO
A95: =A94+1 -> 31 | C95: 76151030 | D95: 6" Round Flan Dish (Without Holes) | E95: 3.7 | F95: =E95+E95*I95 -> 3.885 | G95: Pcs | H95: 500 | I95: 0.05 | K95: APO
A97: PAGE 2

Sheet Bagasse
A1: Neeyog Packaging | I1: summary sheet
A2: OFF: 20, Gr Floor,Sidhpura Ind.Estate,S.V.Road,Gaiwadi Rd,Near Agilus Diagnostic Center,Goregaon(W),Mum- 062 | P2: Mamtora | Q2: MM
A3: Phone : 022-28760709 Mobile 9867607003 Email:neeyog@gmail.com | P3: Bhiwandi | Q3: BW
A4: www.neeyog.com/www.indiamart.com/neeyogpackaging/www.facebook.com/neeyogpack | L4: FM | N4: 1-2 DAY | P4: Shop | Q4: SH
L5: LS | M5: Limited Stock | N5: 3-4 DAYS | P5: Vapi | Q5: VP
A6: Wholesale Bagasse Products Price List | F6: ='Summary Sheet'!C7 -> Date 16.06.2026 | L6: APO | M6: As per Order | N6: 15-20 DAYS | P6: Bansi | Q6: BN
A7: SR No | B7: Product Photos | C7: Description | D7: Excl. Gst Rate | E7: Incl. Gst Rate | F7: Unit | G7: Std Pack | H7: GST | I7: Primary Godown | J7: Movement
C8: B W Bagasse Products (Biodegradable)( HSN Code 48237010)
A9: 1 | C9: BW 6" RD PLATE BAGASSE | D9: 1.3 | E9: =D9+D9*H9 -> 1.365 | F9: Pcs | G9: 3000 | H9: 0.05 | I9: VP | J9: FM
A10: =A9+1 -> 2 | C10: BW 6" DEEP RD PLATE BAGASSE | D10: 1.4 | E10: =D10+D10*H10 -> 1.47 | F10: Pcs | G10: 2000 | H10: 0.05 | I10: VP | J10: APO
A11: =A10+1 -> 3 | C11: BW 7" RD PLATE BAGASSE | D11: 1.85 | E11: =D11+D11*H11 -> 1.9425 | F11: Pcs | G11: 2000 | H11: 0.05 | I11: VP | J11: FM
A12: =A11+1 -> 4 | C12: BW 9" PLAIN RD PLATE BAGASSE | D12: 2.95 | E12: =D12+D12*H12 -> 3.0975 | F12: Pcs | G12: 1000 | H12: 0.05 | J12: APO
A13: =A12+1 -> 5 | C13: BW 9" DEEP RD PLATE BAGASSE | D13: 3.25 | E13: =D13+D13*H13 -> 3.4125 | F13: Pcs | G13: 2000 | H13: 0.05 | I13: VP | J13: LS
A14: =A13+1 -> 6 | B14: New Arrival | C14: BW 3CP Mini Smart Plate Bagasse*1500Pcs | D14: 2.6 | E14: =D14+D14*H14 -> 2.73 | F14: Pcs | G14: 1500 | H14: 0.05 | I14: VP | J14: LS
A15: =A14+1 -> 7 | C15: BW 9" 3CP RD PLATE BAGASSE | D15: 3.25 | E15: =D15+D15*H15 -> 3.4125 | F15: Pcs | G15: 500 | H15: 0.05 | J15: APO
A16: =A15+1 -> 8 | C16: BW 9" 3CP SQ Plate Bagasse | D16: 4.1 | E16: =D16+D16*H16 -> 4.305 | F16: Pcs | G16: 500 | H16: 0.05 | J16: APO
A17: =A16+1 -> 9 | C17: BW 10" RD PLATE BAGASSE | D17: 3.6 | E17: =D17+D17*H17 -> 3.78 | F17: Pcs | G17: 1000 | H17: 0.05 | I17: VP | J17: FM
A18: =A17+1 -> 10 | C18: BW 10" 3CP RD Plate Bagasse | D18: 4.5 | E18: =D18+D18*H18 -> 4.725 | F18: Pcs | G18: 500 | H18: 0.05 | I18: VP | J18: LS
A19: =A18+1 -> 11 | C19: BW 10" 3CP SQ Plate Bagasse | D19: 5 | E19: =D19+D19*H19 -> 5.25 | F19: Pcs | G19: 700 | H19: 0.05 | I19: VP | J19: FM
A20: =A19+1 -> 12 | C20: BW 11" SUPER RD PLATE BAGASSE | D20: 4.2 | E20: =D20+D20*H20 -> 4.41 | F20: Pcs | G20: 750 | H20: 0.05 | I20: VP | J20: APO
A21: =A20+1 -> 13 | C21: BW 11" 4CP RD PLATE BAGASSE | D21: 4.2 | E21: =D21+D21*H21 -> 4.41 | F21: Pcs | G21: 500 | H21: 0.05 | I21: VP | J21: APO
A22: =A21+1 -> 14 | C22: BW 12" SUPER RD PLATE BAGASSE | D22: 5.7 | E22: =D22+D22*H22 -> 5.985 | F22: Pcs | G22: 500 | H22: 0.05 | I22: VP | J22: FM
A23: =A22+1 -> 15 | C23: BW 12" Plain Smart Plate | D23: 5.05 | E23: =D23+D23*H23 -> 5.3025 | F23: Pcs | G23: 2000 | H23: 0.05 | I23: VP | J23: APO
A24: =A23+1 -> 16 | C24: BW 12" 4CP SUPER RD PLATE BAGASSE | D24: 5.7 | E24: =D24+D24*H24 -> 5.985 | F24: Pcs | G24: 500 | H24: 0.05 | I24: VP | J24: FM
A25: =A24+1 -> 17 | C25: BW 4X4 SQ DONA ENJOY BAGASSE | D25: 1.1 | E25: =D25+D25*H25 -> 1.155 | F25: Pcs | G25: 3000 | H25: 0.05 | I25: VP | J25: FM
A26: =A25+1 -> 18 | C26: BW 7" SQR PLATE BAGASSE | D26: 1.95 | E26: =D26+D26*H26 -> 2.0475 | F26: Pcs | G26: 1000 | H26: 0.05 | I26: VP | J26: FM
A27: =A26+1 -> 19 | C27: BW 1D TRAY LITE SQ. BAGASSE | D27: 1.5 | E27: =D27+D27*H27 -> 1.575 | F27: Pcs | G27: 2000 | H27: 0.05 | I27: VP | J27: LS
A28: =A27+1 -> 20 | C28: BW 2D TRAY RECT BAGASSE | D28: 2.4 | E28: =D28+D28*H28 -> 2.52 | F28: Pcs | G28: 1000 | H28: 0.05 | I28: VP | J28: LS
A29: =A28+1 -> 21 | B29: New Arrival | C29: BW 2 Oz Bowl | D29: 1.05 | E29: =D29+D29*H29 -> 1.1025 | F29: Pcs | G29: 5000 | H29: 0.05 | J29: APO
A30: =A29+1 -> 22 | B30: New Arrival | C30: BW 4 Oz Bowl | D30: 1.06 | E30: =D30+D30*H30 -> 1.113 | F30: Pcs | G30: 5000 | H30: 0.05 | J30: APO
A31: =A30+1 -> 23 | C31: BW 6OZ 180ML BOWL BAGASSE | D31: 1.15 | E31: =D31+D31*H31 -> 1.2075 | F31: Pcs | G31: 3000 | H31: 0.05 | I31: VP | J31: LS
A32: =A31+1 -> 24 | C32: BW 7 Oz Bowl | D32: 1.35 | E32: =D32+D32*H32 -> 1.4175 | F32: Pcs | G32: 2000 | H32: 0.05 | J32: APO
A33: =A32+1 -> 25 | C33: BW 8OZ 240ML BOWL BAGASSE | D33: 1.6 | E33: =D33+D33*H33 -> 1.68 | F33: Pcs | G33: 2000 | H33: 0.05 | I33: VP | J33: LS
A34: =A33+1 -> 26 | C34: BW 12OZ 350ML BOWL BAGASSE | D34: 1.95 | E34: =D34+D34*H34 -> 2.0475 | F34: Pcs | G34: 1500 | H34: 0.05 | I34: VP | J34: LS
A35: =A34+1 -> 27 | C35: BW 16OZ 480ML BOWL BAGASSE | D35: 2.7 | E35: =D35+D35*H35 -> 2.835 | F35: Pcs | G35: 1200 | H35: 0.05 | I35: VP | J35: LS
A36: =A35+1 -> 28 | C36: BW024 500ml OVAL BOWL Baggase | D36: 3.7 | E36: =D36+D36*H36 -> 3.885 | F36: Pcs | G36: 1000 | H36: 0.05 | J36: APO
A37: =A36+1 -> 29 | C37: BW025 500ml OVAL LID Bagasse | D37: 2.7 | E37: =D37+D37*H37 -> 2.835 | F37: Pcs | G37: 1000 | H37: 0.05 | J37: APO
A38: =A37+1 -> 30 | C38: BW 750ml Rectangle Bowl | D38: 4.25 | E38: =D38+D38*H38 -> 4.4625 | F38: Pcs | G38: 1000 | H38: 0.05 | J38: APO
A39: =A38+1 -> 31 | C39: BW 750ml Rectangle Bowl Lid | D39: 2.7 | E39: =D39+D39*H39 -> 2.835 | F39: Pcs | G39: 1000 | H39: 0.05 | J39: APO
A40: =A39+1 -> 32 | C40: BW 6X6 CLAMSHELL BURGER BOX BAGASSE | D40: 4.78 | E40: =D40+D40*H40 -> 5.019 | F40: Pcs | G40: 700 | H40: 0.05 | I40: VP | J40: FM
A41: =A40+1 -> 33 | C41: BW 8X8 CLAMSHELL BAGASSE | D41: 8.02 | E41: =D41+D41*H41 -> 8.421 | F41: Pcs | G41: 200 | H41: 0.05 | I41: VP | J41: FM
A42: =A41+1 -> 34 | C42: BW 8x8 3Cp Clam Shell | D42: 8.25 | E42: =D42+D42*H42 -> 8.6625 | F42: Pcs | G42: 200 | H42: 0.05 | J42: APO
A43: =A42+1 -> 35 | C43: BW 9X6 CLAMSHELL BAGASSE | D43: 6.85 | E43: =D43+D43*H43 -> 7.1925 | F43: Pcs | G43: 250 | H43: 0.05 | I43: VP | J43: LS
A44: =A43+1 -> 36 | C44: BW 9X9 CLAMSHELL BAGASSE | D44: 10.6 | E44: =D44+D44*H44 -> 11.13 | F44: Pcs | G44: 200 | H44: 0.05 | I44: VP | J44: LS
A45: =A44+1 -> 37 | C45: BW 9X9 3CP CLAMSHELL BAGASSE | D45: 10.6 | E45: =D45+D45*H45 -> 11.13 | F45: Pcs | G45: 200 | H45: 0.05 | J45: APO
A46: =A45+1 -> 38 | C46: BW 10X6 2CP CLAMSHELL BAGASSE | D46: 6.85 | E46: =D46+D46*H46 -> 7.1925 | F46: Pcs | G46: 250 | H46: 0.05 | I46: VP | J46: FM
A47: =A46+1 -> 39 | C47: BW 2CP TRAY | D47: 2.3 | E47: =D47+D47*H47 -> 2.415 | F47: Pcs | G47: 1000 | H47: 0.05 | J47: APO
A48: =A47+1 -> 40 | C48: BW 3CP MEAL TRAY (OB) BAGASSE | D48: 7.6 | E48: =D48+D48*H48 -> 7.98 | F48: Pcs | G48: 500 | H48: 0.05 | I48: VP | J48: FM
A49: =A48+1 -> 41 | C49: BW 3CP MEAL TRAY LID BAGASSE | D49: 5.5 | E49: =D49+D49*H49 -> 5.775 | F49: Pcs | G49: 500 | H49: 0.05 | I49: VP | J49: FM
A50: =A49+1 -> 42 | B50: New Arrival | C50: BW 4Cp Meal Tray (Anti Leak) | D50: 7.92 | E50: =D50+D50*H50 -> 8.316 | F50: Pcs | G50: 500 | H50: 0.05 | J50: APO
A51: =A50+1 -> 43 | B51: New Arrival | C51: BW 4Cp Meal Tray Lid | D51: 6.45 | E51: =D51+D51*H51 -> 6.7725 | F51: Pcs | G51: 500 | H51: 0.05 | J51: APO
A52: =A51+1 -> 44 | C52: BW 4Cp Meal Tray | D52: 7.55 | E52: =D52+D52*H52 -> 7.9275 | F52: Pcs | G52: 500 | H52: 0.05 | J52: APO
A53: =A52+1 -> 45 | C53: BW 4Cp Meal Tray Lid | D53: 6.15 | E53: =D53+D53*H53 -> 6.4575 | F53: Pcs | G53: 500 | H53: 0.05 | J53: APO
A54: =A53+1 -> 46 | C54: BW 5CP Meal Tray (OB) Anti Leak | D54: 8.4 | E54: =D54+D54*H54 -> 8.82 | F54: Pcs | G54: 500 | H54: 0.05 | I54: VP | J54: LS
A55: =A54+1 -> 47 | C55: BW 5 Cp Meal Tray Lid Anti Leak | D55: 6.2 | E55: =D55+D55*H55 -> 6.51 | F55: Pcs | G55: 500 | H55: 0.05 | J55: APO
A56: =A55+1 -> 48 | C56: BW 5 Cp B2B Meal Tray Only Anti Leak | D56: 9.15 | E56: =D56+D56*H56 -> 9.6075 | F56: Pcs | G56: 500 | H56: 0.05 | J56: APO
A57: =A56+1 -> 49 | C57: BW 5 Cp B2B Meal Tray Lid Anti Leak | D57: 6.95 | E57: =D57+D57*H57 -> 7.2975 | F57: Pcs | G57: 500 | H57: 0.05
A58: =A57+1 -> 50 | C58: BW 8Cp Meal Tray | D58: 9.85 | E58: =D58+D58*H58 -> 10.3425 | F58: Pcs | G58: 500 | H58: 0.05 | J58: APO
A59: =A58+1 -> 51 | C59: BW 8Cp Meal Tray Lid | D59: 6.95 | E59: =D59+D59*H59 -> 7.2975 | F59: Pcs | G59: 500 | H59: 0.05 | J59: APO
A60: =A59+1 -> 52 | C60: BW 80mm LID | D60: 1.65 | E60: =D60+D60*H60 -> 1.7325 | F60: Pcs | G60: 2000 | H60: 0.05 | J60: APO
A61: =A60+1 -> 53 | C61: BW 90mm LID | D61: 1.88 | E61: =D61+D61*H61 -> 1.974 | F61: Pcs | G61: 2000 | H61: 0.05 | J61: APO
A62: =A61+1 -> 54 | C62: BW 95MM PAPER ICE CREAM SPOON | D62: 0.85 | E62: =D62+D62*H62 -> 1.003 | F62: Pcs | G62: 5000 | H62: 0.18 | J62: APO
A63: =A62+1 -> 55 | C63: BW 158MM PAPER Spoon/Fork/Knife | D63: 1.55 | E63: =D63+D63*H63 -> 1.829 | F63: Pcs | G63: 2000 | H63: 0.18 | J63: APO
A64: =A63+1 -> 56 | B64: New Arrival | C64: BW 110ml Kiwi Bowl | D64: 1.25 | E64: =D64+D64*H64 -> 1.3125 | F64: Pcs | G64: 5000 | H64: 0.05 | J64: APO
A65: =A64+1 -> 57 | B65: New Arrival | C65: BW 250ml Glass | D65: 2.95 | E65: =D65+D65*H65 -> 3.0975 | F65: Pcs | G65: 1500 | H65: 0.05 | J65: APO
C66: Dinearth Bagasse Products (Biodegradable) ( HSN Code 48237010)
A67: 1 | C67: 35ML Dinearth Bagasse Round Cup | D67: 0.8 | E67: =D67+D67*H67 -> 0.84 | F67: Pcs | G67: 5000 | H67: 0.05 | I67: VP | J67: APO
A68: =A67+1 -> 2 | C68: DineEarth 35 ml Lid Only | D68: 0.85 | E68: =D68+D68*H68 -> 0.8925 | F68: Pcs | G68: 5000 | H68: 0.05 | J68: APO
A69: =A68+1 -> 3 | C69: 100ML Dinearth Bagasse Bowl | D69: 1.05 | E69: =D69+D69*H69 -> 1.1025 | F69: Pcs | G69: 3600 | H69: 0.05 | I69: VP | J69: LS
A70: =A69+1 -> 4 | C70: 100ml Bowl -PET LID | D70: 0.52 | E70: =D70+D70*H70 -> 0.546 | F70: Pcs | G70: 3600 | H70: 0.05 | J70: APO
A71: =A70+1 -> 5 | C71: 180ML Dinearth Bagasse Bowl | D71: 1.2 | E71: =D71+D71*H71 -> 1.26 | F71: Pcs | G71: 2250 | H71: 0.05 | J71: APO
A72: =A71+1 -> 6 | C72: 240ML Dinearth Bagasse Bowl | D72: 1.55 | E72: =D72+D72*H72 -> 1.6275 | F72: Pcs | G72: 1500 | H72: 0.05 | I72: VP | J72: FM
A73: =A72+1 -> 7 | C73: 150ML Dinearth SQ Bagasse Bowl | D73: 1.2 | E73: =D73+D73*H73 -> 1.26 | F73: Pcs | G73: 2250 | H73: 0.05 | I73: VP | J73: FM
A74: =A73+1 -> 8 | C74: 350ML Dinearth Bagasse Large Bowl | D74: 2.05 | E74: =D74+D74*H74 -> 2.1525 | F74: Pcs | G74: 2400 | H74: 0.05 | J74: APO
A75: =A74+1 -> 9 | C75: Dinearth 12oz Bowl - Export | D75: 2.05 | E75: =D75+D75*H75 -> 2.1525 | F75: Pcs | G75: 2400 | H75: 0.05 | J75: APO
A76: =A75+1 -> 10 | C76: Dinearth 16oz Bowl -480ml | D76: 3.15 | E76: =D76+D76*H76 -> 3.3075 | F76: Pcs | G76: 900 | H76: 0.05 | J76: APO
A77: =A76+1 -> 11 | C77: 340ML Dinearth Bagasse Round Bowl | D77: 3.15 | E77: =D77+D77*H77 -> 3.3075 | F77: Pcs | G77: 1000 | H77: 0.05 | I77: VP | J77: FM
A78: =A77+1 -> 12 | C78: Dinearth 500 ml Bowl (20Pac x 50Pcs) | D78: 4.35 | E78: =D78+D78*H78 -> 4.5675 | F78: Pcs | G78: 1000 | H78: 0.05 | J78: APO
A79: =A78+1 -> 13 | C79: DineEarth 340/500ml Lid Only | D79: 2 | E79: =D79+D79*H79 -> 2.1 | F79: Pcs | G79: 1000 | H79: 0.05 | J79: APO
A80: =A79+1 -> 14 | C80: Dinearth 4 Inch Sqaure Plate | D80: 1.15 | E80: =D80+D80*H80 -> 1.2075 | F80: Pcs | G80: 7200 | H80: 0.05 | J80: APO
A81: =A80+1 -> 15 | C81: 6" Dinearth Bagasse Round Plate | D81: 1.5 | E81: =D81+D81*H81 -> 1.575 | F81: Pcs | G81: 2200 | H81: 0.05 | I81: VP | J81: FM
A82: =A81+1 -> 16 | C82: 7" Dinearth Bagasse Round Plate | D82: 1.85 | E82: =D82+D82*H82 -> 1.9425 | F82: Pcs | G82: 2200 | H82: 0.05 | I82: VP | J82: FM
A83: =A82+1 -> 17 | C83: 7" Dinearth Bagasse SQ Plate | D83: 1.95 | E83: =D83+D83*H83 -> 2.0475 | F83: Pcs | G83: 2400 | H83: 0.05 | J83: APO
A84: =A83+1 -> 18 | C84: 9" Dinearth Bagasse Round Plate | D84: 3.05 | E84: =D84+D84*H84 -> 3.2025 | F84: Pcs | G84: 1000 | H84: 0.05 | I84: VP | J84: FM
A85: =A84+1 -> 19 | C85: 9" Dinearth Bagasse Deep Round Plate | D85: 3.1 | E85: =D85+D85*H85 -> 3.255 | F85: Pcs | G85: 1200 | H85: 0.05 | J85: APO
A86: =A85+1 -> 20 | C86: 9" Dinearth Bagasse Mini SQ Plate | D86: 3.55 | E86: =D86+D86*H86 -> 3.7275 | F86: Pcs | G86: 900 | H86: 0.05 | I86: VP | J86: LS
A87: =A86+1 -> 21 | C87: 9" 3CP Dinearth Bagasse Round Plate | D87: 3.15 | E87: =D87+D87*H87 -> 3.3075 | F87: Pcs | G87: 900 | H87: 0.05 | I87: VP | J87: FM
A88: =A87+1 -> 22 | C88: 10" Dinearth Bagasse Round Plate | D88: 4.2 | E88: =D88+D88*H88 -> 4.41 | F88: Pcs | G88: 1000 | H88: 0.05 | I88: VP | J88: LS
A89: =A88+1 -> 23 | C89: Dinearth 10 " Round plate -Deep | D89: 4.25 | E89: =D89+D89*H89 -> 4.4625 | F89: Pcs | G89: 1000 | H89: 0.05 | J89: APO
A90: =A89+1 -> 24 | C90: 10" 3CP Dinearth Bagasse Round Plate | D90: 4.25 | E90: =D90+D90*H90 -> 4.4625 | F90: Pcs | G90: 800 | H90: 0.05 | I90: VP | J90: FM
A91: =A90+1 -> 25 | C91: 10" 3CP Dinearth Bagasse SQ Plate | D91: 4.3 | E91: =D91+D91*H91 -> 4.515 | F91: Pcs | G91: 600 | H91: 0.05 | J91: APO
A92: =A91+1 -> 26 | C92: 11" Dinearth Bagasse Round Plate | D92: 4.4 | E92: =D92+D92*H92 -> 4.62 | F92: Pcs | G92: 900 | H92: 0.05 | J92: APO
A93: =A92+1 -> 27 | C93: 11" 4CP Dinearth Bagasse Round Plate | D93: 4.4 | E93: =D93+D93*H93 -> 4.62 | F93: Pcs | G93: 500 | H93: 0.05 | I93: VP | J93: FM
A94: =A93+1 -> 28 | C94: 12" Dinearth Bagasse Round Plate | D94: 5.35 | E94: =D94+D94*H94 -> 5.6175 | F94: Pcs | G94: 900 | H94: 0.05 | I94: VP | J94: FM
A95: =A94+1 -> 29 | C95: 12" 4CP Dinearth Bagasse Round Plate | D95: 5.35 | E95: =D95+D95*H95 -> 5.6175 | F95: Pcs | G95: 500 | H95: 0.05 | I95: VP | J95: FM
A96: =A95+1 -> 30 | C96: 4CP Dinearth Bagasse Rect Meal Tray-XL | D96: 7.5 | E96: =D96+D96*H96 -> 7.875 | F96: Pcs | G96: 500 | H96: 0.05 | I96: VP | J96: FM
A97: =A96+1 -> 31 | C97: 5CP Dinearth Bagasse Rect Meal Cont-XL | D97: 8 | E97: =D97+D97*H97 -> 8.4 | F97: Pcs | G97: 500 | H97: 0.05 | I97: VP | J97: LS
A98: =A97+1 -> 32 | C98: Dinearth 5CP Rect Tray (8Pac x 50Pcs) (11*9*2) | D98: 8.22 | E98: =D98+D98*H98 -> 8.631 | F98: Pcs | G98: 400 | H98: 0.05 | J98: APO
A99: =A98+1 -> 33 | C99: 5 Compartment Meal Tray Lid | D99: 6.55 | E99: =D99+D99*H99 -> 6.8775 | F99: Pcs | G99: 400 | H99: 0.05 | J99: APO
A100: =A99+1 -> 34 | C100: 6 Compartment Meal Tray | D100: 8.05 | E100: =D100+D100*H100 -> 8.4525 | F100: Pcs | G100: 300 | H100: 0.05 | J100: APO
...

Sheet Paper Products
A1: Neeyog Packaging | L1: summary sheet | V1: Vendor | W1: Brand | X1: Status | Y1: Key Products/Remarks
A2: OFF: 20, Gr Floor,Sidhpura Ind.Estate,S.V.Road,Gaiwadi Rd,Near Agilus Diagnostic Center,Goregaon(W), Mumbai-400062 | S2: Mamtora | T2: MM | V2: Shant Industries | W2: Eco Paper | X2: Primary | Y2: Economic Glass
A3: Phone : 022-28760709 Mobile 9867607003 Email:neeyog@gmail.com | S3: Bhiwandi | T3: BW | V3: Sahara Industry | W3: Clarro | X3: Primary | Y3: Leakproof, Plain Paper Cups
A4: www.neeyog.com/www.neeyog.net/www.indiamart.com/neeyogpackaging/www.facebook.com/neeyogpack | O4: FM | Q4: 1-2 DAY | S4: Shop | T4: SH | V4: Sai Swaram | W4: SI | X4: Primary | Y4: Ripple Cups / Double Wall (DW)
O5: LS | P5: Limited Stock | Q5: 3-4 DAYS | S5: Vapi | T5: VP
A6: Wholesale Paper Products Price List | I6: ='Summary Sheet'!C7 -> Date 16.06.2026 | O6: APO | P6: As per Order | Q6: 15-20 DAYS | S6: Bansi | T6: BN
A7: SR No | B7: Description | C7: GSM | D7: Diameter | G7: Basic | H7: Rate | I7: Per | J7: Carton | K7: GST | L7: Primary Godown | M7: Movement | N7: Old Description Name | V7: For customise print for more details at Printed Sheet
B8: ECO PAPER CUPS (TNPL) (HSN CODE 48236900) | C8: GSM | D8: Top | E8: BT | F8: H | G8: Rate | H8: Incl Gst | I8: Per | J8: Pack | K8: GST
A9: 1 | B9: 100ML Eco SI Paper Cup (67D) * 5000pcs | C9: 177 | D9: 67 | E9: 52 | F9: 52 | G9: 46 | H9: =G9+G9*18% -> 54.28 | I9: 100 | J9: 5000 | K9: 0.18 | L9: MM | M9: FM | N9: 100ML Eco SI Paper Cup | O9: =H9/1.09 -> 49.798165
A10: 2 | B10: 150ML Eco SI Paper Cup (69D) *5000pcs | C10: 177 | D10: 69 | E10: 52 | F10: 62 | G10: 50.5 | H10: =G10+G10*18% -> 59.59 | I10: 100 | J10: 5000 | K10: 0.18 | L10: MM | M10: FM | N10: 150ML Eco SI Paper Cup
A11: CLARRO PAPER CUPS TALL (Leak Proof) (HSN CODE 48236900) | C11: GSM | D11: Top | E11: BT | F11: H | G11: Rate | H11: Incl Gst | I11: Per | J11: Pack | K11: GST
A12: 1 | B12: 90ML SI Tall Paper Cup (Cllaro) (55D) | C12: 185 | D12: 55 | E12: 40 | F12: 60 | H12: =G12+G12*K12 -> 0 | I12: 100 | J12: 6000 | K12: 0.18 | L12: MM | M12: LS | N12: 90ML SI Tall Paper Cup (Cllaro) (55D)
A13: 2 | B13: 110ML SI Paper Cup Tall (Cllaro) (58D) * 6000pcs | C13: 185 | D13: 59 | E13: 39 | F13: 72 | G13: 54 | H13: =G13+G13*K13 -> 63.72 | I13: 100 | J13: 6000 | K13: 0.18 | L13: MM | M13: FM | N13: 110ML SI Tall Paper Cup (Cllaro) (58D)
B14: CLARRO PAPER CUPS (Leak Proof) (HSN CODE 48236900)
A15: 1 | B15: 100ML SI Paper Cup (Cllaro) (67D) * 5000pcs | C15: 185 | D15: 67 | E15: 52 | F15: 52 | G15: 52 | H15: =G15+G15*K15 -> 61.36 | I15: 100 | J15: 5000 | K15: 0.18 | L15: MM | M15: FM | N15: 100ML SI Paper Cup (Cllaro)
A16: =A15+1 -> 2 | B16: 100ML Paper Cups (Cllaro) | C16: 225 | D16: 67 | E16: 52 | F16: 52 | G16: 66.5 | H16: =G16+G16*K16 -> 78.47 | I16: 100 | J16: 5000 | K16: 0.18 | L16: MM | M16: FM | N16: 100ML Paper Cups (Cllaro)
A17: =A16+1 -> 3 | B17: 130ML SI Paper Cup (Cllaro) (68D) * 5000pcs | C17: 185 | D17: 68 | E17: 52 | F17: 58 | G17: 55 | H17: =G17+G17*K17 -> 64.9 | I17: 100 | J17: 5000 | K17: 0.18 | L17: MM | M17: FM | N17: 130ML SI Paper Cup (Cllaro)
A18: =A17+1 -> 4 | B18: 150ML SI Paper Cup (Cllaro) (69D) * 5000pcs | C18: 185 | D18: 69 | E18: 52 | F18: 62 | G18: 57 | H18: =G18+G18*K18 -> 67.26 | I18: 100 | J18: 5000 | K18: 0.18 | L18: MM | M18: FM | N18: 150ML SI Paper Cup (Cllaro)
A19: =A18+1 -> 5 | B19: 175ML SI Paper Cup (Cllaro) (71D) * 5000pcs | C19: 185 | D19: 71 | E19: 52 | F19: 71 | G19: 64.5 | H19: =G19+G19*K19 -> 76.11 | I19: 100 | J19: 5000 | K19: 0.18 | L19: MM | M19: FM | N19: 175ML SI Paper Cup (Cllaro)
A20: =A19+1 -> 6 | B20: 200ML SI Paper Cup (Cllaro) (72D) * 5000pcs | C20: 185 | D20: 72 | E20: 52 | F20: 75 | G20: 72 | H20: =G20+G20*K20 -> 84.96 | I20: 100 | J20: 5000 | K20: 0.18 | L20: MM | M20: FM | N20: 200ML SI Paper Cup (Cllaro)
A21: =A20+1 -> 7 | B21: 200ML SI Paper Cup (Cllaro) (72D) (225G) * 5000pcs | C21: 225 | D21: 72 | E21: 52 | F21: 75 | G21: 90 | H21: =G21+G21*K21 -> 106.2 | I21: 100 | J21: 5000 | K21: 0.18 | L21: MM | M21: FM | N21: 200ML SI Paper Cup (Cllaro)
A22: =A21+1 -> 8 | B22: 250ML SI Paper Cup (Cllaro) (77D) * 4000pcs | C22: 225 | D22: 77 | E22: 52 | F22: 97 | G22: 112 | H22: =G22+G22*K22 -> 132.16 | I22: 100 | J22: 4000 | K22: 0.18 | L22: MM | M22: FM | N22: 250ML SI Paper Cup (Cllaro)
A23: =A22+1 -> 9 | B23: 300ML SI Paper Cup (Cllaro) * 4000pcs | C23: 225 | D23: 80 | E23: 52 | F23: 109 | G23: 125 | H23: =G23+G23*K23 -> 147.5 | I23: 100 | J23: 4000 | K23: 0.18 | L23: MM | M23: FM | N23: 300ML SI Paper Cup (Cllaro)
A24: =A23+1 -> 10 | B24: 110ML Paper Cups Tall Printed | C24: 185 | D24: 67 | E24: 52 | F24: 52 | G24: 71 | H24: =G24+G24*K24 -> 83.78 | I24: 100 | J24: 6000 | K24: 0.18 | M24: APO | N24: 110ML Paper Cups Tall Printed
A25: =A24+1 -> 11 | B25: 150ML Paper Cups Printed | C25: 185 | D25: 69 | E25: 52 | F25: 62 | G25: 72 | H25: =G25+G25*K25 -> 84.96 | I25: 100 | J25: 5000 | K25: 0.18 | M25: APO | N25: 150ML Paper Cups Printed
A26: =A25+1 -> 12 | B26: 200MLPaper Cups PRINTED ( Cllaro) | C26: 195 | D26: 72 | E26: 52 | F26: 75 | G26: 90 | H26: =G26+G26*K26 -> 106.2 | I26: 100 | J26: 5000 | K26: 0.18 | M26: APO | N26: 200MLPaper Cups PRINTED ( Cllaro)
A27: 13 | B27: 240ML SI 8OZ Paper Cup (Cllaro) (280GSM) * 1000pcs | C27: 280 | D27: 80 | G27: 126 | H27: =G27+G27*K27 -> 148.68 | I27: 100 | J27: 1000 | K27: 0.18 | L27: MM | M27: FM | N27: 240ML SI 8OZ Paper Cup (Cllaro)
A28: Customisation Min Moq 50000 @20 Paise Extra Development Charges @ 4500/- Extra
B29: CLARRO PAPER WATI (HSN CODE 48236100) | C29: GSM | D29: Top | E29: BT | F29: H | G29: Rate | H29: Incl Gst | I29: Per | J29: Pack | K29: GST
A30: 1 | B30: 50ML SI Icecream Paper Wati (62D) | C30: 177 | D30: 63.75 | E30: 51.56 | F30: 36 | G30: 57 | H30: =G30+G30*K30 -> 67.26 | I30: 100Pcs | J30: 5000 | K30: 0.18 | L30: MM | M30: FM | N30: 50ML SI Icecream Paper Wati (62D)
A31: 2 | B31: 100ML SI Icecream Paper Wati (73D) | C31: 185 | D31: 74 | E31: 60.83 | F31: 41 | G31: 68.5 | H31: =G31+G31*K31 -> 80.83 | I31: 100Pcs | J31: 2500 | K31: 0.18 | L31: MM | M31: FM
A32: 3 | B32: 150ML SI Icecream Paper Wati | C32: 185 | D32: 76 | E32: 60.83 | F32: 52 | G32: 84.5 | H32: =G32+G32*K32 -> 99.71 | I32: 100Pcs | J32: 2500 | K32: 0.18 | L32: MM | M32: FM
B33: PAPER CUPS - Dolphin (HSN CODE 48236900) | D33: Top | E33: BT | F33: H | G33: Rate | H33: Incl Gst | I33: Unit | J33: Pack
A34: 1 | B34: 60ML DL Prnt Paper Cups | D34: 49 | E34: 36 | F34: 45 | G34: 28 | H34: =G34+G34*18% -> 33.04 | I34: 50 | J34: 9600 | K34: 0.18 | M34: APO | N34: New box pack is 10350
A35: 2 | B35: 80ML DL Tall Printed Paper Cups | D35: 52 | E35: 37 | F35: 50 | G35: 33 | H35: =G35+G35*18% -> 38.94 | I35: 50 | J35: 8800 | K35: 0.18
A36: 3 | B36: 90ML DL Paper Cups Plain | D36: 57 | E36: 42 | F36: 55 | G36: 39 | H36: =G36+G36*18% -> 46.02 | I36: 50 | J36: 6800 | K36: 0.18 | L36: MM | M36: FM
A37: 4 | B37: 150ML DL Paper Cups (68D) * 5000Pcs | D37: 68 | G37: 48.5 | H37: =G37+G37*18% -> 57.23 | I37: 50 | J37: 5500 | K37: 0.18
A38: 5 | B38: 200ML DL Paper Cups (72D) * 5000pc | D38: 72 | G38: 57.5 | H38: =G38+G38*18% -> 67.85 | I38: 50 | J38: 5000 | K38: 0.18
A39: PAGE 6
B40: Export Products (HSN - 4823) | C40: GSM | D40: Top l | E40: Top W | F40: H | G40: Rate | H40: Incl Gst | I40: Per | J40: Pack | K40: GST
A41: 1 | B41: 65ml PNS Prem Prnt Paper Cups (ST) | G41: 0.34 | H41: =G41+G41*K41 -> 0.4012 | I41: Pcs | J41: 9600 | K41: 0.18 | L41: BW | M41: FM
A42: 2 | B42: 130ml PNS Prem Print Paper Cups (ST) | C42: 205 | G42: 0.48 | H42: =G42+G42*K42 -> 0.5664 | I42: Pcs | J42: 6400 | K42: 0.18 | L42: VP | M42: FM
A43: 3 | B43: 150ml PNS Prem Prnt Paper Cups (ST) | C43: 205 | G43: 0.6 | H43: =G43+G43*K43 -> 0.708 | I43: Pcs | J43: 5000 | K43: 0.18 | L43: MM | M43: LS
A44: 4 | B44: 200ml PNS Prem Print Paper Cups (ST) | C44: 205 | D44: 80 | E44: 56 | F44: 92 | G44: 0.68 | H44: =G44+G44*K44 -> 0.8024 | I44: Pcs | J44: 6050 | K44: 0.18 | L44: MM | M44: LS
A45: 5 | B45: 250ml Premium Paper Cup Printed PNS (A&M) | C45: 225 | G45: 0.9 | H45: =G45+G45*K45 -> 1.062 | I45: Pcs | J45: 3500 | K45: 0.18 | L45: MM | M45: FM
A46: 6 | B46: 8oz Premium | C46: 225 | G46: 1.25 | H46: =G46+G46*K46 -> 1.475 | I46: Pcs | J46: 3500 | K46: 0.18 | M46: APO
A47: 7 | B47: 12oz 330ml Printed Paper Cup 2PE | C47: 245 | D47: 80 | E47: 51 | F47: 112 | G47: 1.6 | H47: =G47+G47*K47 -> 1.888 | I47: Pcs | J47: 500 | K47: 0.18 | M47: APO
A48: 8 | B48: 650ml Paper cup WS | C48: 245 | D48: 90 | G48: 2.4 | H48: =G48+G48*K48 -> 2.832 | I48: Pcs | J48: 500 | K48: 0.18 | L48: BW | M48: FM
B49: SI RIPPLE CUPS (HSN CODE 48236900) | C49: GSM | D49: Top | E49: BT | F49: H | G49: Basic /Pcs | H49: Incl GST | I49: Per | J49: Box Pack | K49: GST %
B50: Ripple Cup Brown
A51: 1 | B51: 150ml SI Ripple Paper Cups Brown | C51: 195+220 | D51: 62 | E51: 51 | F51: 60 | G51: 1.2 | H51: =G51+G51*K51 -> 1.416 | I51: Pcs | J51: 1000 | K51: 0.18 | L51: BW | M51: FM
A52: 2 | B52: 200ml SI Ripple Paper Cups Brown | C52: 195+220 | D52: 67 | E52: 51 | F52: 73 | G52: 1.35 | H52: =G52+G52*K52 -> 1.593 | I52: Pcs | J52: 1000 | K52: 0.18 | L52: BW | M52: FM
A53: 3 | B53: 8OZ SI Ripple Paper Cup Brown | C53: 250+240 | D53: 80 | E53: 56 | F53: 92 | G53: 2 | H53: =G53+G53*K53 -> 2.36 | I53: Pcs | J53: 1000 | K53: 0.18 | L53: BW | M53: FM
A54: 4 | B54: 12OZ SI Ripple Paper Cup Brown | C54: 300+240 | D54: 90 | E54: 60 | F54: 112.5 | G54: 3.05 | H54: =G54+G54*K54 -> 3.599 | I54: Pcs | J54: 500 | K54: 0.18 | L54: BW | M54: FM
A55: 5 | B55: 16OZ SI Ripple Paper Cup Brown | C55: 300+240 | D55: 90 | E55: 60 | F55: 135.5 | G55: 2.95 | H55: =G55+G55*K55 -> 3.481 | I55: Pcs | J55: 500 | K55: 0.18
B56: Ripple Cup Black
A57: 1 | B57: 8OZ SI Ripple Paper Cup (Black) | G57: 1.75 | H57: =G57+G57*K57 -> 2.065 | I57: Pcs | J57: 1000 | K57: 0.18 | L57: BW | M57: FM
B58: CP Double Wall Cups (HSN CODE 48236900) | D58: Top | E58: BT | F58: H | G58: Basic /Pcs | H58: Incl GST | I58: Per | J58: Box Pack | K58: GST %
A59: 1 | B59: 7OZ 210ML CP D/W Paper Cups (White/Brown) | D59: 73 | E59: 50 | F59: 83 | G59: 1.8 | H59: =G59+G59*K59 -> 2.124 | I59: Pcs | J59: 1000 | K59: 0.18
B60: SI Double Wall Cups (HSN CODE 48236900) | D60: Top | E60: BT | F60: H | G60: Basic /Pcs | H60: Incl GST | I60: Per | J60: Box Pack | K60: GST %
A61: 1 | B61: 8OZ 250ML SI D/W Paper Cups White/Brown | C61: 250+240 | D61: 80 | E61: 56 | F61: 92 | G61: 2.1 | H61: =G61+G61*K61 -> 2.478 | I61: Pcs | J61: 500 | K61: 0.18 | L61: BW | M61: FM
A62: 2 | B62: 12OZ 350ML SI D/W Paper Cups White/Brown | C62: 300+240 | D62: 90 | E62: 60 | F62: 112.5 | G62: 3.15 | H62: =G62+G62*K62 -> 3.717 | I62: Pcs | J62: 500 | K62: 0.18 | L62: BW | M62: FM
B64: HIPS LIDS FOR PAPER CUP (HSN CODE 39239090) | C64: Dia | G64: Rate | H64: Incl Gst | I64: Per | J64: Pack | K64: GST
A65: 1 | B65: 70DIA FLAT LIDS FOR 200ML TALL | C65: 70 | G65: 0.55 | H65: =G65+G65*K65 -> 0.649 | I65: Pcs | J65: 9000 | K65: 0.18 | M65: APO
A66: =A65+1 -> 2 | B66: 72D HIPS Infi Flat Lid * 10000pcs | C66: 72 | G66: 0.65 | H66: =G66+G66*K66 -> 0.767 | I66: Pcs | J66: 10000 | K66: 0.18 | L66: MM | M66: LS
A67: =A66+1 -> 3 | B67: 76DIA HIPS LID FOR 150ML WATI | C67: 76 | G67: 0.6 | H67: =G67+G67*K67 -> 0.708 | I67: Pcs | J67: 7500 | K67: 0.18 | M67: APO
A68: =A67+1 -> 4 | B68: 80DIA FLAT LID FOR 300ML CLLARO | C68: 80 | G68: 0.7 | H68: =G68+G68*K68 -> 0.826 | I68: Pcs | J68: 6000 | K68: 0.18 | L68: MM | M68: LS
A69: =A68+1 -> 5 | B69: 80DIA Flat lid for 8oz & 12oz SP | C69: 80 | G69: 0.6 | H69: =G69+G69*K69 -> 0.708 | I69: Pcs | J69: 5000 | K69: 0.18 | M69: APO
A70: =A69+1 -> 6 | B70: 82DIA HIPS LID FOR 330ML CLLARO | C70: 82 | G70: 0.7 | H70: =G70+G70*K70 -> 0.826 | I70: Pcs | J70: 6500 | K70: 0.18 | M70: APO
A71: =A70+1 -> 7 | B71: 87Dia Flat Lid Plain/Scut | C71: 87 | G71: 1 | H71: =G71+G71*K71 -> 1.18 | I71: Pcs | J71: 1000 | K71: 0.18 | M71: APO
A72: =A71+1 -> 8 | B72: 90DIA HIPS Flat Lid | C72: 90 | G72: 0.9 | H72: =G72+G72*K72 -> 1.062 | I72: Pcs | J72: 6000 | K72: 0.18 | L72: MM | M72: LS
A73: =A72+1 -> 9 | B73: 70MM Sipper Lid (200ML TALL) | C73: 70 | G73: 0.9 | H73: =G73+G73*K73 -> 1.062 | I73: Pcs | J73: 8000 | K73: 0.18 | L73: MM | M73: LS
A74: =A73+1 -> 10 | B74: 80/82DIA Sipper Lid (8oz Cup) | C74: 80/82 | G74: 0.95 | H74: =G74+G74*K74 -> 1.121 | I74: Pcs | J74: 6000 | K74: 0.18 | L74: BW | M74: FM
A75: =A74+1 -> 11 | B75: 80D/82D HIPS PUSHBACK LID Black * 5000pc | C75: 80 | G75: 1 | H75: =G75+G75*K75 -> 1.18 | I75: Pcs | J75: 5000 | K75: 0.18 | L75: MM | M75: FM
A76: =A75+1 -> 12 | B76: 87Dia Sipper Lid (12Oz Tall) | C76: 87 | G76: 1.35 | H76: =G76+G76*K76 -> 1.593 | I76: Pcs | J76: 2000 | K76: 0.18 | L76: BW | M76: FM
A77: =A76+1 -> 13 | B77: 90 Dia Sipper Lid (12Oz Cup) | C77: 90 | G77: 1.12 | H77: =G77+G77*K77 -> 1.3216 | I77: Pcs | J77: 4000 | K77: 0.18 | L77: MM | M77: FM
A78: =A77+1 -> 14 | B78: 90D HIPS PUSHBACK LID [Black] * 4000pcs | C78: 90 | G78: 1.15 | H78: =G78+G78*K78 -> 1.357 | I78: Pcs | J78: 4000 | K78: 0.18 | L78: MM | M78: FM
B79: Paper Lids (HSN - 4823) | G79: Rate | H79: Incl Gst | I79: Per | J79: Pack | K79: GST
A80: 1 | B80: Paper Lids 73Dia (100ml) | G80: 1.38 | H80: =G80+G80*K80 -> 1.6284 | I80: Pcs | J80: 3500 | K80: 0.18 | M80: APO
A81: 2 | B81: Paper Lid 80Dia White | G81: 1.35 | H81: =G81+G81*K81 -> 1.593 | I81: Pcs | J81: 1450 | K81: 0.18 | M81: APO
A82: 3 | B82: Paper Lid 90Dia White | G82: 1.65 | H82: =G82+G82*K82 -> 1.947 | I82: Pcs | J82: 1000 | K82: 0.18 | M82: LS
A83: 4 | B83: Paper Lid 116 Dia White (250/500/1000) | G83: 3.3 | H83: =G83+G83*K83 -> 3.894 | I83: Pcs | J83: 1000 | K83: 0.18 | M83: APO
A84: 5 | B84: Paper Lid 116Dia 2Layer | G84: 3.65 | H84: =G84+G84*K84 -> 4.307 | I84: Pcs | J84: 1000 | K84: 0.18 | M84: APO
B85: Baggase Lids for Cups (HSN CODE 48236900)
A86: 1 | B86: 80dia Baggase Lids-Sipper | G86: 1.5 | H86: =G86+G86*K86 -> 1.575 | I86: Pcs | J86: 2000 | K86: 0.05 | L86: MM | M86: FM
A87: 2 | B87: 90Dia Baggase Lids- Sipper | G87: 1.65 | H87: =G87+G87*K87 -> 1.7325 | I87: Pcs | J87: 2000 | K87: 0.05 | L87: BW | M87: FM
B88: Paper Container(Kraft)PW (HSN CODE 48236900) | C88: GSM | D88: Top | E88: BT | F88: H | G88: Cont | H88: Lid | I88: With Lid | J88: Pack | K88: GST
A89: 1 | B89: 300ML PW Paper Cont Kraft (OB) (110D) * 1000pcs | C89: 260 | D89: 110 | G89: 2.65 | H89: 2.55 | I89: =H89+G89 -> 5.2 | J89: 1000 | K89: 0.18 | L89: MM | M89: LS | N89: 300ML PW Paper Cont Kraft (WL)
A90: 2 | B90: 400ML PW Paper Cont Kraft (OB) | C90: 305 | D90: 110 | G90: 3.15 | H90: 2.55 | I90: =H90+G90 -> 5.7 | J90: 500 | K90: 0.18 | L90: MM | M90: LS | N90: 400ML PW Paper Cont Kraft (WL)
A91: 3 | B91: 500ML PW Paper Cont Kraft (OB) (110D) * 500pcs | C91: 305 | D91: 110 | G91: 3.6 | H91: 2.55 | I91: =H91+G91 -> 6.15 | J91: 500 | K91: 0.18 | L91: MM | M91: LS | N91: 500ML PW Paper Cont Kraft (WL)
A92: 4 | B92: 750ML PW Paper Cont Kraft (OB) (110D) * 500pcs | C92: 305 | D92: 110 | G92: 4.3 | H92: 2.55 | I92: =H92+G92 -> 6.85 | J92: 500 | K92: 0.18 | L92: MM | M92: LS | N92: 750ML N PW Paper Cont Kraft (WL)
A93: 5 | B93: 1000ML PW Paper Cont Kraft (OB) (127D) * 500pcs | C93: 305 | D93: 110 | G93: 5.3 | H93: 2.95 | I93: =H93+G93 -> 8.25 | J93: 500 | K93: 0.18 | L93: MM | M93: LS
B94: PW SALAD Kraft Bowl 148D (HSN CODE 48236900) | G94: Rate | H94: Incl Gst
A95: 1 | B95: 500ML PW FLAT KRAFT PAPER BOWL (148D) * 500pc | C95: 305 | D95: 148 | G95: 3.9 | H95: =G95+G95*K95 -> 4.602 | I95: Pcs | J95: 500 | K95: 0.18 | L95: MM | M95: FM | N95: 500ML PW FLAT KRAFT PAPER BOWL (148D)
A96: 2 | B96: 750ML PW FLAT KRAFT PAPER BOWL (148D) * 500pc | C96: 305 | D96: 148 | G96: 4.25 | H96: =G96+G96*K96 -> 5.015 | I96: Pcs | J96: 500 | K96: 0.18 | L96: MM | M96: FM | N96: 750ML PW FLAT KRAFT PAPER BOWL (148D)
A97: 3 | B97: 1000ML PW FLAT KRAFT PAPER BOWL (148D) | C97: 320 | D97: 148 | G97: 4.95 | H97: =G97+G97*K97 -> 5.841 | I97: Pcs | J97: 500 | K97: 0.18 | L97: MM | M97: FM | N97: 1000ML PW FLAT KRAFT PAPER BOWL (148D)
B98: PW SALAD White Bowl 148D (HSN CODE 48236900) | G98: Rate | H98: Incl Gst
A99: 1 | B99: 500ML PW FLAT PAPER BOWL [White] (OB) (148D) * 500pc | C99: 305 | D99: 148 | G99: 3.8 | H99: =G99+G99*K99 -> 4.484 | I99: Pcs | J99: 500 | K99: 0.18 | L99: MM | M99: APO
A100: 1 | B100: 750ML PW FLAT PAPER BOWL [White] (OB) (148D) * 500pc | C100: 305 | D100: 148 | G100: 4.15 | H100: =G100+G100*K100 -> 4.897 | I100: Pcs | J100: 500 | K100: 0.18 | L100: MM | M100: APO
A101: 3 | B101: 1000ML PW FLAT PAPER BOWL [White] (OB) (148D) * 500pc | C101: 320 | D101: 148 | G101: 4.75 | H101: =G101+G101*K101 -> 5.605 | I101: Pcs | J101: 500 | K101: 0.18 | L101: MM | M101: APO
...

Sheet Olive Reference 
A1: Neeyog Packaging | J1: Summary Sheet | P1: Mamtora | Q1: MM
A2: OFF:G20, Gr Floor,Sidhpura Ind.Estate,S.V.Road,Gaiwadi Rd,Near Agilus Diagnostic Center,Goregaon(W),Mum- 062 | P2: Bhiwandi | Q2: BW
A3: Phone : 022-28760709 Mobile 9867607003 Email:neeyog@gmail.com | L3: FM | N3: 1-2 DAY | P3: Shop | Q3: SH
A4: www.neeyog.com/www.neeyog.net/www.indiamart.com/neeyogpackaging/www.facebook.com/neeyogpack | L4: LS | M4: Limited Stock | N4: 3-4 DAYS | P4: Vapi | Q4: VP
L5: APO | M5: As per Order | N5: 15-20 DAYS | P5: Bansi | Q5: BN
A6: Wholesale Olive Paper Products Price List | G6: ='Summary Sheet'!C7 -> Date 16.06.2026
A8: SR No | B8: Code | C8: Description | E8: Top Dia | F8: Box Packing | G8: Basic Price / 100Pcs | H8: Incl GST /Pcs | I8: GST %
A9: Single Wall Plain Cups (HSN CODE 48236900)
A10: 1 | B10: 4001PL | C10: 100 ML PAPER CUP- Plain | E10: 62 | F10: 6000 | G10: 47.2 | H10: =G10+G10*I10 -> 55.696 | I10: 0.18
A11: 2 | B11: 4003PL | C11: 100 ML PAPER CUP- Plain | E11: 62 | F11: 6000 | G11: 48.5 | H11: =G11+G11*I11 -> 57.23 | I11: 0.18
A12: 3 | B12: 4006PL | C12: 4006PL 130ml S/W Paper Cup *6000pcs | E12: 65 | F12: 6000 | G12: 54.3 | H12: =G12+G12*I12 -> 64.074 | I12: 0.18
A13: =A12+1 -> 4 | B13: 4009PL | C13: 150 ML PAPER CUP - PLAIN | E13: 70 | F13: 5000 | G13: 53.1 | H13: =G13+G13*I13 -> 62.658 | I13: 0.18
A14: =A13+1 -> 5 | B14: 4013APL | C14: 4013APL 200ml S/W Paper Cup DLX Plain *4000pcs | E14: 73 | F14: 4000 | G14: 80 | H14: =G14+G14*I14 -> 94.4 | I14: 0.18
A15: =A14+1 -> 6 | B15: 4013PL | C15: 4013PL 200ml OE Paper Cup (73D) * 4000pc | E15: 73 | F15: 4000 | G15: 75.5 | H15: =G15+G15*I15 -> 89.09 | I15: 0.18
A16: =A15+1 -> 7 | B16: 4018PL | C16: 4018PL 250ml OE Paper Cup (80D) 205Gsm*2500Pcs | E16: 80 | F16: 2500 | G16: 86.15 | H16: =G16+G16*I16 -> 101.657 | I16: 0.18
A17: =A16+1 -> 8 | B17: 4022PL | C17: 300 ML PAPER CUP | E17: 80 | F17: 2500 | G17: 110 | H17: =G17+G17*I17 -> 129.8 | I17: 0.18
A18: 10 | B18: 4032 | C18: 4032 480ml OE S/W Paper Cup SB [Plain] * 1000pcs | F18: 1000
A19: Tall Paper Cups (HSN CODE 48236900)
A20: 1 | B20: 4008PL | C20: 4008PL 150ml S/W Tall Paper Cup Plain *5000pcs | E20: 66 | F20: 5000 | G20: 57.8 | H20: =G20+G20*I20 -> 68.204 | I20: 0.18
A21: 2 | B21: 4012PL | C21: 4012PL 200ML OE TALL PAPER CUP 2PE (69D) *4000Pcs | E21: 69 | F21: 4000 | G21: 70.8 | H21: =G21+G21*I21 -> 83.544 | I21: 0.18
A22: SINGLE WALL CUPS (2PE) (HSN CODE 48236900)
A23: 1 | B23: 4012 | C23: 200 ML TALL PAPER CUP | D23: 182 | E23: 69 | F23: 4000 | G23: 73.2 | H23: =G23+G23*I23 -> 86.376 | I23: 0.18
A24: =A23+1 -> 2 | B24: 4017A | C24: 250 ML PAPER CUP - DELUXE | E24: 73 | F24: 4000 | G24: 86.7 | H24: =G24+G24*I24 -> 102.306 | I24: 0.18
A25: =A24+1 -> 3 | B25: 4022 | C25: 300 ML PAPER CUP | D25: 202 | E25: 80 | F25: 2500 | G25: 1.15 | H25: =G25+G25*I25 -> 1.357 | I25: 0.18
A26: =A25+1 -> 4 | B26: 4026 | C26: 330 ML PAPER CUP | D26: 202 | E26: 80 | F26: 2500 | G26: 118 | H26: =G26+G26*I26 -> 139.24 | I26: 0.18
A27: =A26+1 -> 5 | B27: 4028A | C27: 360 ML PAPER CUP - DELUXE | E27: 90 | F27: 2000 | G27: 165 | H27: =G27+G27*I27 -> 194.7 | I27: 0.18
A28: =A27+1 -> 6 | B28: 4032 | C28: 4032 480ml OE S/W Paper Cup SB [Plain] * 1000pcs | E28: 90 | F28: 1000 | G28: 177 | H28: =G28+G28*I28 -> 208.86 | I28: 0.18
A29: =A28+1 -> 7 | B29: 4037 | C29: 650 ML PAPER CUP SB | E29: 90 | F29: 500 | G29: 215 | H29: =G29+G29*I29 -> 253.7 | I29: 0.18
A30: =A29+1 -> 8 | B30: 4039 | C30: 720 ML PAPER CUP | E30: 90 | F30: 500 | G30: 295 | H30: =G30+G30*I30 -> 348.1 | I30: 0.18
A31: Common Printed Cups (HSN CODE 48236900)
A32: 1 | B32: 4003 | C32: 100 ML PAPER CUP | D32: 182 | E32: 62 | F32: 6000 | G32: 0.44 | H32: =G32+G32*I32 -> 0.5192 | I32: 0.18
A33: =A32+1 -> 2 | B33: 4006 | C33: 130 ML PAPER CUP | D33: 182 | E33: 65 | F33: 6000 | G33: 0.49 | H33: =G33+G33*I33 -> 0.5782 | I33: 0.18
A34: =A33+1 -> 3 | B34: 4009 | C34: 150 ML PAPER CUP | D34: 182 | E34: 70 | F34: 5000 | G34: 0.59 | H34: =G34+G34*I34 -> 0.6962 | I34: 0.18
A35: =A34+1 -> 4 | B35: 4013 | C35: 200 ML PAPER CUP | D35: 182 | E35: 73 | F35: 4000 | G35: 0.69 | H35: =G35+G35*I35 -> 0.8142 | I35: 0.18
A36: =A35+1 -> 5 | B36: 4017 | C36: 250 ML PAPER CUP | D36: 182 | E36: 73 | F36: 4000 | G36: 0.9 | H36: =G36+G36*I36 -> 1.062 | I36: 0.18
A37: =A36+1 -> 6 | B37: 4018 | C37: 250 ML PAPER CUP | D37: 182 | E37: 80 | F37: 2500 | G37: 0.98 | H37: =G37+G37*I37 -> 1.1564 | I37: 0.18
A38: =A37+1 -> 7 | B38: 4022 | C38: 300 ML PAPER CUP | D38: 202 | E38: 80 | F38: 2500 | G38: 1 | H38: =G38+G38*I38 -> 1.18 | I38: 0.18
A39: =A38+1 -> 8 | B39: 4023 | C39: 300 ML PAPER CUP SB | D39: 202 | E39: 90 | F39: 2500 | G39: 1.4 | H39: =G39+G39*I39 -> 1.652 | I39: 0.18
A40: =A39+1 -> 9 | B40: 4026 | C40: 330 ML PAPER CUP | D40: 202 | E40: 80 | F40: 2500 | G40: 1.18 | H40: =G40+G40*I40 -> 1.3924 | I40: 0.18
A41: =A40+1 -> 10 | B41: 4029 | C41: 360 ML PAPER CUP SB | D41: 222 | E41: 90 | F41: 2000 | G41: 1.65 | H41: =G41+G41*I41 -> 1.947 | I41: 0.18
A42: =A41+1 -> 11 | B42: 4032 | C42: 480 ML PAPER CUP SB - 2PE | E42: 90 | F42: 1000 | G42: 1.72 | H42: =G42+G42*I42 -> 2.0296 | I42: 0.18
A43: =A42+1 -> 12 | B43: 4037 | C43: 650 ML PAPER CUP SB - 2PE | E43: 90 | F43: 1000 | G43: 2.15 | H43: =G43+G43*I43 -> 2.537 | I43: 0.18
A44: =A43+1 -> 13 | B44: 4039 | C44: 720 ML PAPER CUP - 2PE | E44: 90 | F44: 1000 | G44: 2.95 | H44: =G44+G44*I44 -> 3.481 | I44: 0.18
A45: Heavy Printed Cups (HSN CODE 48236900)
A46: 1 | B46: 4006 A | C46: 130 ML PAPER CUP - DELUXE | E46: 65 | F46: 6000 | G46: 0.59 | H46: =G46+G46*I46 -> 0.6962 | I46: 0.18
A47: =A46+1 -> 2 | B47: 4009 A | C47: 150 ML PAPER CUP - DELUXE | E47: 70 | F47: 5000 | G47: 0.59 | H47: =G47+G47*I47 -> 0.6962 | I47: 0.18
A48: =A47+1 -> 3 | B48: 4013 A | C48: 200 ML PAPER CUP - DELUXE | E48: 73 | F48: 4000 | G48: 0.8 | H48: =G48+G48*I48 -> 0.944 | I48: 0.18
A49: =A48+1 -> 4 | B49: 4017 A | C49: 250 ML PAPER CUP - DELUXE - 2PE | E49: 73 | F49: 4000 | G49: 0.92 | H49: =G49+G49*I49 -> 1.0856 | I49: 0.18
A50: =A49+1 -> 5 | B50: 4018 A | C50: 250 ML PAPER CUP - DELUXE | E50: 80 | F50: 2500 | G50: 1.18 | H50: =G50+G50*I50 -> 1.3924 | I50: 0.18
A51: =A50+1 -> 6 | B51: 4022 A | C51: 300 ML PAPER CUP - DELUXE | E51: 80 | F51: 2500 | G51: 1.25 | H51: =G51+G51*I51 -> 1.475 | I51: 0.18
A52: =A51+1 -> 7 | B52: 4026 A | C52: 330 ML PAPER CUP - DELUXE | E52: 80 | F52: 2500 | G52: 1.68 | H52: =G52+G52*I52 -> 1.9824 | I52: 0.18
A53: =A52+1 -> 8 | B53: 4037 | C53: 650 ML PAPER CUP SB - 2PE | E53: 90 | F53: 1000 | G53: 2.15 | H53: =G53+G53*I53 -> 2.537 | I53: 0.18
A54: =A53+1 -> 9 | B54: 4039 | C54: 720 ML PAPER CUP - 2PE | E54: 90 | F54: 1000 | G54: 2.95 | H54: =G54+G54*I54 -> 3.481 | I54: 0.18
A55: PRINTED WHITE RIPPLE CUPS (HSN CODE 48236900)
A56: Sr No | B56: Code | C56: Description | E56: Top Dia | F56: Box Packing | G56: Basic Price / 100 Pcs | H56: Incl GST /Pcs | I56: GST %
A57: 1 | B57: 4003RHP | C57: 4003RHP 100ml OE Ripple Glass White [Printed] * 3000Pcs | D57: 392 | E57: 62 | F57: 3000 | G57: 105 | H57: =G57+G57*I57 -> 123.9 | I57: 0.18
A58: =A57+1 -> 2 | B58: 4006RHP | C58: 130 ML RIPPLE PAPER CUP | D58: 392 | E58: 65 | F58: 2000 | G58: 115 | H58: =G58+G58*I58 -> 135.7 | I58: 0.18
A59: =A58+1 -> 3 | B59: 4009RHP | C59: 4009RHP 150ml OE Printed Ripple Glass (70D) * 2000pcs | D59: 392 | E59: 70 | F59: 2000 | G59: 118 | H59: =G59+G59*I59 -> 139.24 | I59: 0.18
A60: =A59+1 -> 4 | B60: 4013RHP | C60: 4013RHP 200ml OE Ripple Glass White [Printed] * 1500 | D60: 392 | E60: 73 | F60: 1500 | G60: 140 | H60: =G60+G60*I60 -> 165.2 | I60: 0.18
A61: =A60+1 -> 5 | B61: 4018RHP | C61: 4018RHP 250ml OE Ripple Com Print Glass (80D) * 2000pcs | D61: 392 | E61: 80 | F61: 1500 | G61: 185 | H61: =G61+G61*I61 -> 218.3 | I61: 0.18
A62: =A61+1 -> 6 | B62: 4020RHP | C62: 250 ML RIPPLE PAPER CUP SB | D62: 412 | E62: 80 | F62: 1500 | G62: 180 | H62: =G62+G62*I62 -> 212.4 | I62: 0.18
A63: =A62+1 -> 7 | B63: 4022RHP | C63: 4022RV 300ml OE Ripple Paper Cup (80D) Printed * 1400Pcs | D63: 432 | E63: 80 | F63: 1400 | G63: 225 | H63: =G63+G63*I63 -> 265.5 | I63: 0.18
A64: =A63+1 -> 8 | B64: 4023RHP | C64: 300 ML RIPPLE PAPER CUP | D64: 432 | E64: 90 | F64: 1000 | G64: 224 | H64: =G64+G64*I64 -> 264.32 | I64: 0.18
A65: =A64+1 -> 9 | B65: 4026RHP | C65: 330 ML RIPPLE PAPER CUP | D65: 432 | E65: 80 | F65: 1000 | G65: 236 | H65: =G65+G65*I65 -> 278.48 | I65: 0.18
A66: =A65+1 -> 10 | B66: 4029RHP | C66: 360 ML RIPPLE PAPER CUP SB | D66: 452 | E66: 90 | F66: 1000 | G66: 290 | H66: =G66+G66*I66 -> 342.2 | I66: 0.18
A67: =A66+1 -> 11 | B67: 4032RHP | C67: 450 ML RIPPLE PAPER CUP | D67: 452 | E67: 90 | F67: 1000 | G67: 345 | H67: =G67+G67*I67 -> 407.1 | I67: 0.18
A69: PRINTED WHITE RIPPLE TALL CUPS (HSN CODE 48236900)
A70: 1 | B70: 4008RHP | C70: 150 ML TALL RIPPLE PAPER CUP | D70: 392 | E70: 65 | F70: 2000 | G70: 118 | H70: =G70+G70*I70 -> 139.24 | I70: 0.18
A71: KRAFT RIPPLE CUPS (HSN CODE 48236900)
A72: 1 | B72: 4003RK | C72: 4003RHK 100ML OE Ripple Glass Brown * 3000Pcs | E72: 62 | F72: 3000 | G72: 94.4 | H72: =G72+G72*I72 -> 111.392 | I72: 0.18
A73: 2 | B73: 4006RHK | C73: 4006RHK 130ml OE Ripple Glass Brown (62D) * 2000pc | E73: 62 | F73: 2000 | G73: 103 | H73: =G73+G73*I73 -> 121.54 | I73: 0.18
A74: 3 | B74: 4009RHK | C74: 4009RHK 150ml OE Ripple Glass (70D) Kraft Plain * 3000pc | D74: 382 | E74: 70 | F74: 3000 | G74: 106 | H74: =G74+G74*I74 -> 125.08 | I74: 0.18
A75: 4 | B75: 4013RHK | C75: 4013R(H)K 200ML OE Ripple Glass Brown * 1500 | D75: 382 | E75: 73 | F75: 1500 | G75: 125 | H75: =G75+G75*I75 -> 147.5 | I75: 0.18
A76: 5 | B76: 4018RHK | C76: 4018RHK 250ML OE Ripple BROWN Glass * 1500pcs | D76: 382 | E76: 80 | F76: 1500 | G76: 155 | H76: =G76+G76*I76 -> 182.9 | I76: 0.18
B77: 4018RHKC | C77: 4018RHKC 250ml OE Ripple BROWN Glass (80D) * 2000pcs | E77: 80 | F77: 2000 | G77: 155 | H77: =G77+G77*I77 -> 182.9 | I77: 0.18
A78: 6 | B78: 4018RHK | C78: 4018RHK 250ml OE Ripple Black Glass (80D) * 1500pcs | E78: 80 | F78: 1500 | G78: 170 | H78: =G78+G78*I78 -> 200.6 | I78: 0.18
A79: 7 | B79: 4022RHK | C79: 300 ML RIPPLE PAPER CUP | D79: 422 | E79: 80 | F79: 1000 | G79: 220 | H79: =G79+G79*I79 -> 259.6 | I79: 0.18
A80: 8 | B80: 4023RHK | C80: 300 ML RIPPLE PAPER CUP | D80: 422 | E80: 90 | F80: 1000 | G80: 220 | H80: =G80+G80*I80 -> 259.6 | I80: 0.18
A81: 9 | B81: 4026RK | C81: 330 ML RIPPLE PAPER CUP | E81: 80 | F81: 1000 | G81: 232.5 | H81: =G81+G81*I81 -> 274.35 | I81: 0.18
A82: 10 | B82: 4029RK | C82: 360 ML RIPPLE PAPER CUP SB | E82: 90 | F82: 1000 | G82: 2.6 | H82: =G82+G82*I82 -> 3.068 | I82: 0.18
A83: 11 | B83: 4029RHK | C83: 4029RHK 350ml OE Ripple Cup Brown (90 Dia) *1000pcs | E83: 90 | F83: 1000 | G83: 290 | H83: =G83+G83*I83 -> 342.2 | I83: 0.18
A84: 12 | B84: 4032RHK | C84: 480 ML RIPPLE PAPER CUP | D84: 442 | E84: 90 | F84: 1000 | G84: 340 | H84: =G84+G84*I84 -> 401.2 | I84: 0.18
A85: KRAFT RIPPLE TALL CUPS (HSN CODE 48236900)
A86: 1 | B86: 4008RHK | C86: 4008RHK 150ml Tall Ripple Paper Cup (65D) * 3000pc | E86: 65 | F86: 3000 | G86: 1.1 | H86: =G86+G86*I86 -> 1.298 | I86: 0.18
A87: PRICE LIST - AQUEOUS COATED
A88: SINGLE WALL CUPS (HSN CODE 48236900)
A89: SR No | B89: Code | C89: Description | E89: Top Dia | F89: Box Packing | G89: Basic Price / Pcs | H89: Incl GST /Pcs | I89: GST %
A90: 1 | B90: 8003 | C90: 100 ML PAPER CUP | D90: 176 | E90: 62 | F90: 6000 | G90: 0.58 | H90: =G90+G90*I90 -> 0.6844 | I90: 0.18
A91: =A90+1 -> 2 | B91: 8006 | C91: 130 ML PAPER CUP | D91: 176 | E91: 65 | F91: 6000 | G91: 0.68 | H91: =G91+G91*I91 -> 0.8024 | I91: 0.18
A92: =A91+1 -> 3 | B92: 8008 | C92: 150 ML TALL PAPER CUP | D92: 176 | E92: 65 | F92: 5000 | G92: 0.7 | H92: =G92+G92*I92 -> 0.826 | I92: 0.18
A93: =A92+1 -> 4 | B93: 8013 | C93: 200 ML PAPER CUP | D93: 176 | E93: 73 | F93: 4000 | G93: 0.85 | H93: =G93+G93*I93 -> 1.003 | I93: 0.18
A94: =A93+1 -> 5 | B94: 8018 | C94: 250 ML PAPER CUP | D94: 176 | E94: 80 | F94: 2500 | G94: 1.05 | H94: =G94+G94*I94 -> 1.239 | I94: 0.18
A95: =A94+1 -> 6 | B95: 8020 | C95: 250 ML PAPER CUP SB PREMUM | D95: 196 | E95: 80 | F95: 2500 | G95: 1.3 | H95: =G95+G95*I95 -> 1.534 | I95: 0.18
A96: =A95+1 -> 7 | B96: 8023 | C96: 300 ML PAPER CUP SB PREMIUM | D96: 196 | E96: 90 | F96: 2500 | G96: 1.65 | H96: =G96+G96*I96 -> 1.947 | I96: 0.18
A97: =A96+1 -> 8 | B97: 8026 | C97: 330 ML PAPER CUP | D97: 196 | E97: 80 | F97: 2500 | G97: 1.65 | H97: =G97+G97*I97 -> 1.947 | I97: 0.18
A98: =A97+1 -> 9 | B98: 8029 | C98: 360 ML PAPER CUP SB | D98: 216 | E98: 90 | F98: 2000 | G98: 1.88 | H98: =G98+G98*I98 -> 2.2184 | I98: 0.18
A99: =A98+1 -> 10 | B99: 8032 | C99: 480 ML PAPER CUP SB | D99: 216 | E99: 90 | F99: 1000 | G99: 2.12 | H99: =G99+G99*I99 -> 2.5016 | I99: 0.18
A100: RIPPLE CUPS (HSN CODE 48236900)
A101: SR No | B101: Code | C101: Description | E101: Top Dia | F101: Box Packing | G101: Basic Price / Pcs | H101: Incl GST /Pcs | I101: GST %
A102: 1 | B102: 8008R | C102: 150 ML TALL RIPPLE CUP | E102: 65 | F102: 2000 | G102: 1.18 | H102: =G102+G102*I102 -> 1.3924 | I102: 0.18
...

Sheet Olive Products
A1: Neeyog Packaging | K1: Summary Sheet | Q1: Mamtora | R1: MM
A2: OFF:G20, Gr Floor,Sidhpura Ind.Estate,S.V.Road,Gaiwadi Rd,Near Agilus Diagnostic Center,Goregaon(W),Mum- 062 | M2: NL | N2: New Launch | Q2: Bhiwandi | R2: BW
A3: Phone : 022-28760709 Mobile 9867607003 Email:neeyog@gmail.com | M3: FM | O3: 1-2 DAY | Q3: Shop | R3: SH
A4: www.neeyog.com/www.neeyog.net/www.indiamart.com/neeyogpackaging/www.facebook.com/neeyogpack | M4: LS | N4: Limited Stock | O4: 3-4 DAYS | Q4: Vapi | R4: VP
M5: APO | N5: As per Order | O5: 15-20 DAYS | Q5: Bansi | R5: BN
A6: Wholesale Olive Classic Paper Products Price List | H6: ='Summary Sheet'!C7 -> Date 16.06.2026
A7: SINGLE WALL CUPS
A8: PRICE LIST - CLASSIC SERIES
A9: CLASSIC SINGLE WALL CUPS (HSN CODE 48236900) | K9: Primary Godown | L9: Movement
A10: SR No | C10: Code | D10: Description | E10: GSM | F10: Top Dia | G10: Box Packing | H10: Basic Price / Pcs | I10: Incl GST /Pcs | J10: GST %
D11: Single Wall Plain Cups | K11: APO | L11: FM
A12: 1 | B12: 4003C | C12: 4003C | D12: 100 ML PAPER CUP | F12: 62 | G12: 6300 | H12: 0.45 | I12: =H12+H12*J12 -> 0.531 | J12: 0.18
A13: =A12+1 -> 2 | B13: 4006C | C13: 4006C | D13: 130 ML PAPER CUP | F13: 65 | G13: 6300 | H13: 0.51 | I13: =H13+H13*J13 -> 0.6018 | J13: 0.18
A14: =A13+1 -> 3 | B14: 4008C | C14: 4008C | D14: 150 ML TALL PAPER CUP | F14: 65 | G14: 5400 | H14: 0.53 | I14: =H14+H14*J14 -> 0.6254 | J14: 0.18
A15: =A14+1 -> 4 | B15: 4009C | C15: 4009C | D15: 150 ML PAPER CUP | F15: 70 | G15: 4800 | H15: 0.53 | I15: =H15+H15*J15 -> 0.6254 | J15: 0.18
A16: =A15+1 -> 5 | B16: 4013C | C16: 4013C | D16: 200 ML PAPER CUP | F16: 73 | G16: 4800 | H16: 0.66 | I16: =H16+H16*J16 -> 0.7788 | J16: 0.18
A17: =A16+1 -> 6 | B17: 4018C | C17: 4018C | D17: 250 ML PAPER CUP | F17: 80 | G17: 4800 | H17: 0.83 | I17: =H17+H17*J17 -> 0.9794 | J17: 0.18
A18: =A17+1 -> 7 | B18: 4022C | C18: 4022C | D18: 300 ML PAPER CUP | F18: 80 | G18: 4000 | H18: 0.93 | I18: =H18+H18*J18 -> 1.0974 | J18: 0.18
A19: =A18+1 -> 8 | B19: 4026C | C19: 4026C | D19: 330 ML PAPER CUP | F19: 80 | G19: 3000 | H19: 0.98 | I19: =H19+H19*J19 -> 1.1564 | J19: 0.18
A20: =A19+1 -> 9 | B20: 4029C | C20: 4029C | D20: 360 ML PAPER CUP SB | F20: 90 | G20: 2000 | H20: 1.35 | I20: =H20+H20*J20 -> 1.593 | J20: 0.18
A21: =A20+1 -> 10 | B21: 4032C | C21: 4032C | D21: 480 ML PAPER CUP SB | F21: 90 | G21: 1000 | H21: 1.6 | I21: =H21+H21*J21 -> 1.888 | J21: 0.18
A22: CLASSIC ICE CREAM CUP (HSN CODE 48236900)
A23: 1 | C23: 4051CPL | D23: 50 ML SAUCE CUP - PLAIN | F23: 62 | G23: 5000 | H23: 0.44 | I23: =H23+H23*J23 -> 0.5192 | J23: 0.18
A24: 2 | C24: 4055CPL | D24: 90 ML ICE CREAM CUP - PLAIN | F24: 64 | G24: 4000 | H24: 0.51 | I24: =H24+H24*J24 -> 0.6018 | J24: 0.18
A25: SR No | C25: Code | D25: Description | F25: Top Dia | G25: Box Packing | H25: Basic Price / Pcs | I25: Incl GST /Pcs | J25: GST %
A26: CLASSIC RIPPLE CUPS (HSN CODE 48236900)
A27: 1 | C27: 4003RHKC | D27: 100 ML RIPPLE PAPER CUP | E27: 362 | F27: 62 | G27: 3000 | H27: 0.91 | I27: =H27+H27*J27 -> 1.0738 | J27: 0.18
A28: =A27+1 -> 2 | C28: 4006RHKC | D28: 130 ML RIPPLE PAPER CUP | E28: 362 | F28: 62 | G28: 3000 | H28: 0.93 | I28: =H28+H28*J28 -> 1.0974 | J28: 0.18
A29: =A28+1 -> 3 | C29: 4008RHKC | D29: 150 ML TALL RIPPLE CUP | F29: 65 | G29: 3000 | H29: 0.99 | I29: =H29+H29*J29 -> 1.1682 | J29: 0.18
A30: =A29+1 -> 4 | C30: 4009RHKC | D30: 150 ML PAPER CUP | E30: 362 | F30: 70 | G30: 3000 | H30: 0.99 | I30: =H30+H30*J30 -> 1.1682 | J30: 0.18
A31: =A30+1 -> 5 | C31: 4013RHKC | D31: 4013R(H)KC 200ML OE Ripple Glass Brown ( 73D) * 2000 | E31: 362 | F31: 73 | G31: 2000 | H31: 1.23 | I31: =H31+H31*J31 -> 1.4514 | J31: 0.18
A32: =A31+1 -> 6 | C32: 4018RHKC | D32: 250 ML RIPPLE PAPER CUP | F32: 80 | G32: 2000 | H32: 1.63 | I32: =H32+H32*J32 -> 1.9234 | J32: 0.18
A33: CLASSIC PLATS & BOWL -GST 18 % EXTRA
A34: 1 | B34: 4501CPL | C34: 4501CPL | D34: 4"X4" PAPER DONA - PLAIN | G34: 6000 | H34: 0.57 | I34: =H34+H34*J34 -> 0.6726 | J34: 0.18
A35: 2 | B35: 4502CPL | C35: 4502CPL | D35: 5"X5" PAPER PLATE - PLAIN | G35: 4000 | H35: 0.89 | I35: =H35+H35*J35 -> 1.0502 | J35: 0.18
A36: 3 | B36: 4506CPL | C36: 4506CPL | D36: 150 ML PAPER BOWL - PLAIN | G36: 6000 | H36: 0.57 | I36: =H36+H36*J36 -> 0.6726 | J36: 0.18
A37: 4 | B37: 4507CPL | C37: 4507CPL | D37: 200 ML PAPER BOWL - PLAIN | G37: 4000 | H37: 0.77 | I37: =H37+H37*J37 -> 0.9086 | J37: 0.18
A38: 5 | B38: 4515CPL | C38: 4515CPL | D38: 6" PAPER PLATE - PLAIN | G38: 4000 | H38: 0.89 | I38: =H38+H38*J38 -> 1.0502 | J38: 0.18
A39: 6 | B39: 4518CPL | C39: 4518CPL | D39: 7" PAPER PLATE - PLAIN | G39: 3000 | H39: 1.25 | I39: =H39+H39*J39 -> 1.475 | J39: 0.18
A40: CLASSIC PAPER STRAW | F40: Sleeves | G40: Box Packing | H40: Basic Price / Pcs | I40: Incl GST /Pcs | J40: GST %
A41: 1 | C41: 4651CPL | D41: 6 MM - PAPER STRAW PLAIN | F41: 100 | G41: 10000 | H41: 0.2 | I41: =H41+H41*J41 -> 0.236 | J41: 0.18
A42: 2 | C42: 4651C | D42: 6 MM - PAPER STRAW | F42: 100 | G42: 10000 | H42: 0.22 | I42: =H42+H42*J42 -> 0.2596 | J42: 0.18
A43: 3 | C43: 4654CPL | D43: 8 MM - PAPER STRAW PLAIN | F43: 100 | G43: 10000 | H43: 0.28 | I43: =H43+H43*J43 -> 0.3304 | J43: 0.18
A44: 4 | C44: 4654C | D44: 8 MM - PAPER STRAW | F44: 100 | G44: 10000 | H44: 0.3 | I44: =H44+H44*J44 -> 0.354 | J44: 0.18
A45: Double WALL CUPS (HSN CODE 48236900)
A46: Sr No | C46: Code | D46: Description | F46: Top Dia | G46: Box Packing | H46: Basic Price / Pcs | I46: Incl GST /Pcs | J46: GST %
A47: 1 | C47: 4018DWPL | D47: 4018DWPL 250ml OE D/W White Glass Plain (80D) * 1500pcs | E47: 452 | F47: 80 | G47: 1500 | H47: 195 | I47: =H47+H47*J47 -> 230.1 | J47: 0.18
A48: 2 | C48: 4020 | D48: 4020 250ml OE DW Paper Cup (80D) Printed [Black on white] * 1500pcs | F48: 80 | G48: 1500 | H48: 198 | I48: =H48+H48*J48 -> 233.64 | J48: 0.18
A49: 3 | C49: 4023DW | D49: 300 ML DW PAPER CUP | E49: 452 | F49: 90 | G49: 1000 | H49: 230 | I49: =H49+H49*J49 -> 271.4 | J49: 0.18
A50: 4 | C50: 4026DW | D50: 330 ML DW PAPER CUP | E50: 452 | F50: 80 | G50: 1000 | H50: 255 | I50: =H50+H50*J50 -> 300.9 | J50: 0.18
A51: 5 | C51: 4029DWA | D51: 4029DWA 360ML OE D/W Paper Cup SB Deluxe (90 Dia) *1000pcs | E51: 502 | F51: 90 | G51: 1000 | H51: 275 | I51: =H51+H51*J51 -> 324.5 | J51: 0.18
A52: 6 | C52: 4029DWK | D52: 4029DWK 360ml OE D/W Paper Cup Brown (90D) *1000pcs | F52: 90 | G52: 1000 | H52: 275 | I52: =H52+H52*J52 -> 324.5 | J52: 0.18
A53: 7 | C53: 4032DW | D53: 450 ML DW PAPER CUP | E53: 482 | F53: 90 | G53: 1000 | H53: 315 | I53: =H53+H53*J53 -> 371.7 | J53: 0.18
A54: ICE CREAM CUP (HSN CODE 48236900)
A55: Sr No | C55: Code | D55: Description | E55: GSM | F55: Top Dia | G55: Box Packing | H55: Basic Price /100 Pcs | I55: Incl GST /Pcs | J55: GST %
A56: 1 | B56: OE50MLSC | C56: 4051PL | D56: 4051 50ml OE SAUCE Paper Cup | E56: 190 | F56: 62 | G56: 5000 | H56: 50 | I56: =H56+H56*J56 -> 59 | J56: 0.18
A57: =A56+1 -> 2 | C57: 4053 | D57: 75 ML ICE CREAM CUP - 2PE | E57: 190 | F57: 64 | G57: 5000 | H57: 54.5 | I57: =H57+H57*J57 -> 64.31 | J57: 0.18
A58: =A57+1 -> 3 | C58: 4055 | D58: 90 ML ICE CREAM CUP - 2PE | E58: 190 | F58: 65 | G58: 4000 | H58: 59 | I58: =H58+H58*J58 -> 69.62 | J58: 0.18
A59: =A58+1 -> 4 | B59: 4058- 120ml Ice Cream Cup 3000 | C59: 4058 | D59: 4058 120ML OE Ice Cream Vati (Printed) | E59: 190 | F59: 73 | G59: 3000 | H59: 69 | I59: =H59+H59*J59 -> 81.42 | J59: 0.18
A60: =A59+1 -> 5 | C60: 4058PL | D60: 120 ML ICE CREAM CUP - 2PE | E60: 190 | F60: 73 | G60: 3000 | H60: 69 | I60: =H60+H60*J60 -> 81.42 | J60: 0.18
A61: =A60+1 -> 6 | C61: 4060 | D61: 150 ML ICE CREAM CUP - 2PE | E61: 190 | F61: 75 | G61: 3000 | H61: 87.5 | I61: =H61+H61*J61 -> 103.25 | J61: 0.18
A62: =A61+1 -> 7 | C62: 4062 | D62: 180 ML ICE CREAM CUP - 2PE | E62: 190 | F62: 85 | G62: 2500 | H62: 95.6 | I62: =H62+H62*J62 -> 112.808 | J62: 0.18
A63: =A62+1 -> 8 | C63: 4062 A | D63: 180 ML ICE CREAM CUP - 2PE | F63: 85 | G63: 2500 | H63: 115 | I63: =H63+H63*J63 -> 135.7 | J63: 0.18
A64: =A63+1 -> 9 | C64: 4065 | D64: 250 ML ICE CREAM CUP - 2PE | E64: 210 | F64: 88 | G64: 2500 | H64: 155 | I64: =H64+H64*J64 -> 182.9 | J64: 0.18
A65: =A64+1 -> 10 | C65: 4068 | D65: 300 ML ICE CREAM CUP - 2PE | E65: 210 | F65: 90 | G65: 2000 | H65: 172 | I65: =H65+H65*J65 -> 202.96 | J65: 0.18
A66: PAPER LIDS (HSN CODE 48236900)
A67: Sr No | C67: Code | D67: Description | G67: Box Packing | H67: Basic Price / 100Pcs | I67: Incl GST /Pcs | J67: GST %
A68: 1 | C68: 4701PL | D68: 4701PL 62 Dia OE Flat Paper Lid *5000pcs | E68: 270 | F68: 62 | G68: 5000 | H68: 65 | I68: =H68+H68*J68 -> 76.7 | J68: 0.18
A69: =A68+1 -> 2 | C69: 1701 | D69: 62 DIA DOME PET LID | E69: NA | F69: 62 | G69: 5000 | H69: 47 | I69: =H69+H69*J69 -> 55.46 | J69: 0.18
A70: =A69+1 -> 3 | C70: 4703PL | D70: 73 DIA SIPPER PAPER LID | E70: 272 | F70: 73 | G70: 4000 | H70: 90 | I70: =H70+H70*J70 -> 106.2 | J70: 0.18
A71: =A70+1 -> 4 | C71: 4707PL | D71: 4707PL 80D OE Flat Paper Lid * 5000Pcs | E71: 272 | F71: 80 | G71: 5000 | H71: 79 | I71: =H71+H71*J71 -> 93.22 | J71: 0.18
A72: =A71+1 -> 5 | C72: 4708PL | D72: 80 DIA SIPPER PAPER LID | E72: 272 | F72: 80 | G72: 3000 | H72: 110 | I72: =H72+H72*J72 -> 129.8 | J72: 0.18
A73: =A72+1 -> 6 | C73: 4711PL | D73: 4711PL 90D OE Flat Paper Lid * 4000Pcs | E73: 272 | F73: 90 | G73: 4000 | H73: 97 | I73: =H73+H73*J73 -> 114.46 | J73: 0.18
A74: =A73+1 -> 7 | C74: 4712PL | D74: 90 DIA SIPPER PAPER LID | E74: 272 | F74: 90 | G74: 2000 | H74: 115 | I74: =H74+H74*J74 -> 135.7 | J74: 0.18
A75: PLA & PLASTIC LIDS (HSN CODE 39235090)
A76: Sr No | C76: Code | D76: Description | G76: Box Packing | H76: Basic Price / 100Pcs | I76: Incl GST /Pcs | J76: GST %
A77: 1 | B77: 5703 - 73 Dia Sipper PP Lid Only 6000 | C77: 5703 | D77: 5703 - 73 Dia Sipper PP Lid * 6000pcs | E77: NA | F77: 73 | G77: 7200 | H77: 83 | I77: =H77+H77*J77 -> 97.94 | J77: 0.18
A78: 2 | C78: 5708 | D78: 80 DIA SIPPER PP LID | E78: NA | F78: 80 | G78: 5000 | H78: 98 | I78: =H78+H78*J78 -> 115.64 | J78: 0.18
A79: 3 | C79: 5709 | D79: 80 DIA LOCKABLE SIPPER PP LID | F79: 80 | G79: 5000 | H79: 95 | I79: =H79+H79*J79 -> 112.1 | J79: 0.18
A80: 4 | C80: 5711 | D80: 90 DIA FLAT PP LID | E80: NA | F80: 90 | G80: 7500 | H80: 95 | I80: =H80+H80*J80 -> 112.1 | J80: 0.18
A81: 5 | C81: 5712 | D81: 90 DIA SIPPER PP LID | E81: NA | F81: 90 | G81: 5000 | H81: 120 | I81: =H81+H81*J81 -> 141.6 | J81: 0.18
A82: 6 | C82: 5713 | D82: 90 DIA LOCKABLE SIPPER PP LID | F82: 90 | G82: 5000 | H82: 125 | I82: =H82+H82*J82 -> 147.5 | J82: 0.18
A83: 7 | C83: 1704 | D83: 1704 73 & 75 Dia OE Dome Pet Lid (For 120ml and 150ml) *2800pcs | E83: NA | F83: 73&75 | G83: 2800 | H83: 110 | I83: =H83+H83*J83 -> 129.8 | J83: 0.18
A84: 8 | C84: 1705 | D84: 75 DIA FLAT PET LID | E84: NA | F84: 75 | G84: 5000 | H84: 50 | I84: =H84+H84*J84 -> 59 | J84: 0.18
A85: 9 | C85: 1709 | D85: 85 & 87 DIA DOME PET LID (TWIN) | E85: NA | F85: 85&87 | G85: 4000 | H85: 1.35 | I85: =H85+H85*J85 -> 1.593 | J85: 0.18
A86: 10 | C86: 7708 | D86: 80 DIA SIPPER CPLA LID | E86: NA | F86: 80 | G86: 5000 | H86: 159 | I86: =H86+H86*J86 -> 187.62 | J86: 0.18
A87: 11 | C87: 7712 | D87: 90 DIA SIPPER CPLA LID | E87: NA | F87: 90 | G87: 5000 | H87: 212 | I87: =H87+H87*J87 -> 250.16 | J87: 0.18
A88: 12 | C88: 7713 | D88: 90 DIA DOME CLEAR PLA LID | E88: NA | F88: 90 | G88: 5000 | H88: 194.7 | I88: =H88+H88*J88 -> 229.746 | J88: 0.18
A89: PET LIDS – GST 18% EXTRA (HSN CODE 39235090)
A90: 1 | C90: 1706 | D90: 80 DIA DOME PET LID | E90: NA | F90: 80 | G90: 5000 | H90: 60 | I90: =H90+H90*J90 -> 70.8 | J90: 0.18
A91: 2 | C91: 1707 | D91: 80 DIA FLAT PET LID | E91: NA | F91: 80 | G91: 5000 | H91: 52 | I91: =H91+H91*J91 -> 61.36 | J91: 0.18
A92: 3 | C92: 1711 | D92: 90 DIA FLAT PET LID | E92: NA | F92: 90 | G92: 5000 | H92: 68 | I92: =H92+H92*J92 -> 80.24 | J92: 0.18
A93: 4 | C93: 1713 | D93: 1713 90Dia OE Dome Pet Lid *5000pcs | E93: NA | F93: 90 | G93: 5000 | H93: 88.5 | I93: =H93+H93*J93 -> 104.43 | J93: 0.18
A94: PLATES AND BOWLS (HSN CODE 48236900)
A95: Sr No | C95: Code | D95: Description | G95: Box Packing | H95: Basic Price / 100 Pcs | I95: Incl GST /Pcs | J95: GST %
A96: 1 | B96: 4501 4x4 Paper Dona 4000pcs | C96: 4501 | D96: 4501 OE 4x4 SQ Paper Dona [Common Print] * 4000pcs | E96: 227 | G96: 4000 | H96: 68 | I96: =H96+H96*J96 -> 80.24 | J96: 0.18
A97: 2 | C97: 4502 | D97: 4502 5x5 OE Paper Plate * 3000Pcs | E97: 227 | G97: 3000 | H97: 100 | I97: =H97+H97*J97 -> 118 | J97: 0.18
A98: 3 | B98: 4506 150ml Paper Bowl 5000pcs | C98: 4506 | D98: 4506 OE 150ml Paper Bowl (205GSM) [Common Print] * 5000pcs | E98: 227 | G98: 5000 | H98: 67 | I98: =H98+H98*J98 -> 79.06 | J98: 0.18
A99: 4 | B99: 4506 150ml Paper Bowl 5000pcs | C99: 4506 | D99: 4506 OE 150ml Paper Bowl 255GSM [Common Print] * 5000pcs | E99: 227 | G99: 5000 | H99: 75 | I99: =H99+H99*J99 -> 88.5 | J99: 0.18
A100: 5 | C100: 4507 | D100: 4507 200ml OE Paper Bowl * 4000pcs | E100: 227 | G100: 4000 | H100: 85 | I100: =H100+H100*J100 -> 100.3 | J100: 0.18
...

Sheet PNS
A1: Neeyog Packaging | K1: Summary Sheet' | P1: Mamtora | Q1: MM
A2: OFF: 20, Gr Floor,Sidhpura Ind.Estate,S.V.Road,Gaiwadi Rd,Near Agilus Diagnostic Center,Goregaon(W),Mum- 062 | L2: NL | M2: New Launch | P2: Bhiwandi | Q2: BW
A3: Phone : 28760709 Mobile 9867607003 Email:neeyog@gmail.com | L3: FM | N3: 1-2 DAY | P3: Shop | Q3: SH
A4: www.neeyog.com/www.indiamart.com/neeyogpackaging/www.facebook.com/neeyogpack | L4: LS | M4: Limited Stock | N4: 3-4 DAYS | P4: Vapi | Q4: VP
L5: APO | M5: As per Order | N5: 15-20 DAYS | P5: Bansi | Q5: BN
A6: Paknserve Paper Product Price List | G6: ='Summary Sheet'!C7 -> Date 16.06.2026
A8: Sr. No. | B8: Code | C8: HSN Code | D8: Photos | E8: Paper PRODUCTS | F8: Rate Excl GST | G8: Rate Incl GST | H8: Per | I8: Packing | J8: Gst | K8: Primary Godown | L8: Movement
E9: PNS Economy
A10: 1 | B10: PNS01 | C10: 48191010 | E10: Popcorn Pocket Small | F10: 1.35 | G10: =F10+F10*J10 -> 1.4175 | H10: Pcs | J10: 0.05
A11: =A10+1 -> 2 | B11: PNS02 | C11: 48191010 | E11: PNS 20 OZ Popcorn Box * 2000 Pcs | F11: 2.5 | G11: =F11+F11*J11 -> 2.625 | H11: Pcs | I11: 2000 | J11: 0.05
A12: =A11+1 -> 3 | B12: PNS03 | C12: 48191010 | E12: PNS 32 OZ SQ Popcorn Box * 400Pcs | F12: 3.6 | G12: =F12+F12*J12 -> 3.78 | H12: Pcs | I12: 400 | J12: 0.05
A13: =A12+1 -> 4 | B13: PNS04 | C13: 48191010 | E13: PNS 64 OZ SQ Popcorn Box * 400Pcs | F13: 4.8 | G13: =F13+F13*J13 -> 5.04 | H13: Pcs | I13: 400 | J13: 0.05
A14: =A13+1 -> 5 | B14: PNS05 | C14: 48191010 | E14: PNS Waffle Cone | F14: 1.6 | G14: =F14+F14*J14 -> 1.68 | H14: Pcs | I14: 5000 | J14: 0.05
A15: =A14+1 -> 6 | B15: PNS06 | C15: 48236900 | E15: PNS ITC WAFFLE TRAY ENJOY 9.5X2.50X1.50 (COM PRNT) | F15: 3.2 | G15: =F15+F15*J15 -> 3.776 | H15: Pcs | I15: 2000 | J15: 0.18
A16: =A15+1 -> 7 | B16: PNS07 | C16: 48191010 | E16: PNS ITC WAFFLE BOX 9.5X2.50X1.50 (200Gsm) | F16: 3.55 | G16: =F16+F16*J16 -> 3.7275 | H16: Pcs | I16: 2000 | J16: 0.05
A17: =A16+1 -> 8 | B17: PNS08 | C17: 48191010 | E17: 1Cup Duplex Kraft Holder (PNS) * 1600pcs | F17: 2.25 | G17: =F17+F17*J17 -> 2.3625 | H17: Pcs | I17: 3000 | J17: 0.05
A18: =A17+1 -> 9 | B18: PNS09 | C18: 48191010 | E18: JP-30-1401 2Cup Kraft Duplex Holder | F18: 2.75 | G18: =F18+F18*J18 -> 2.8875 | H18: Pcs | I18: 2000 | J18: 0.05
A19: =A18+1 -> 10 | B19: PNS10 | C19: 48191010 | E19: PNS ITC WRAP ROLL BOX ENJOY RED/GREEN*3200PCS (COM PRNT) | F19: 2.2 | G19: =F19+F19*J19 -> 2.31 | H19: Pcs | I19: 3200 | J19: 0.05 | L19: 2000
A20: =A19+1 -> 11 | B20: PNS11 | C20: 48236900 | E20: PNS KRAFT WRAP ROLL BOX *1500PCS | F20: 3.62 | G20: =(F20*J20)+F20 -> 3.801 | H20: Pcs | I20: 1500 | J20: 0.05
A21: =A20+1 -> 12 | B21: PNS12 | C21: 48191010 | E21: PNS ITC PEDA BOX 45x45x30MM *6000PCS (COM PRNT) | F21: 1.8 | G21: =F21+F21*J21 -> 1.89 | H21: Pcs | I21: 3000 | J21: 0.05
A22: =A21+1 -> 13 | B22: PNS13 | C22: 48191010 | E22: Kraft Wrapp Box Small Enjoy 8"X2"X2" (With Inside Lamination) KRAFT WRAP BOX SMALL ENJOY 280G | F22: 2.7 | G22: =(F22*J22)+F22 -> 2.835 | H22: Pcs | I22: 100 | J22: 0.05 | K22: SHOP | L22: FM
A23: =A22+1 -> 14 | B23: PNS14 | C23: 48191010 | E23: Kraft Wrapp Box Large Enjoy 8"X2.5"X2.5" (With Inside Lamination) KRAFT WRAP BOX LARGE ENJOY 280G | F23: 3.25 | G23: =(F23*J23)+F23 -> 3.4125 | H23: Pcs | I23: 100 | J23: 0.05 | K23: SHOP | L23: FM
A24: =A23+1 -> 15 | B24: PNS15 | E24: Kraft Dosa box Enjoy 12"X3"X1.75" (With Inside Lamination) KRAFT DOSA BOX ENJOY 280G | F24: 3.8 | G24: =(F24*J24)+F24 -> 3.99 | H24: Pcs | I24: 100 | J24: 0.05 | K24: SHOP | L24: FM
C25: 48191010 | E25: Kraft 4*4*3 ENjoy Box (SNACK BOX) | F25: 3.4 | G25: =(F25*J25)+F25 -> 3.57 | H25: Pcs | I25: 100 | J25: 0.05
C26: 48191010 | E26: Kraft 5*5*3 ENjoy Box (BURGER BOX) | F26: 4.75 | G26: =(F26*J26)+F26 -> 4.9875 | H26: Pcs | I26: 100 | J26: 0.05
C27: 48191010 | E27: Kraft 7*5*3 ENjoy Box (SNACK BOX) | F27: 5.4 | G27: =(F27*J27)+F27 -> 5.67 | H27: Pcs | I27: 100 | J27: 0.05
C28: 48191010 | E28: Kraft 9*6*3 ENjoy Box | F28: 8 | G28: =(F28*J28)+F28 -> 8.4 | H28: Pcs | I28: 100 | J28: 0.05
A29: =A24+1 -> 16 | B29: PNS16 | C29: 48236900 | E29: PNS French Fries Plain Brown (A&M) * 3200Pcs | F29: 1.9 | G29: =(F29*J29)+F29 -> 2.242 | H29: Pcs | I29: 3200 | J29: 0.18
A30: =A29+1 -> 17 | B30: PNS17 | C30: 48191010 | E30: KRAFT 3X3X2 WINDOW 280G | F30: 2.5 | G30: =F30+F30*J30 -> 2.625 | H30: Pcs | I30: 500 | J30: 0.05 | K30: SHOP | L30: FM
A31: =A30+1 -> 18 | B31: PNS18 | C31: 48192020 | E31: PNS Window Sandwich Box [VP] *600Pcs | F31: 3.9 | G31: =(F31*J31)+F31 -> 4.095 | H31: Pcs | I31: 3200 | J31: 0.05 | K31: SHOP | L31: FM
A32: =A31+1 -> 19 | B32: PNS19 | C32: 48192020 | E32: PNS Small Burger Box (100x100x80mm) [VP]*300Pcs | F32: 4.15 | G32: =(F32*J32)+F32 -> 4.3575 | H32: Pcs | I32: 300 | J32: 0.05
A33: 20 | B33: PNS20 | C33: 48192020 | E33: PNS Big Burger Box (110x110x90mm) [VP]*200Pcs | F33: 4.7 | G33: =(F33*J33)+F33 -> 4.935 | H33: Pcs | I33: 200 | J33: 0.05
A34: 21 | B34: PNS21 | C34: 48236900 | E34: PNS 300ml Paper Tray [VP] ( 135x80x30mm) *PCS | F34: 2.45 | G34: =(F34*J34)+F34 -> 2.891 | H34: Pcs | I34: 900 | J34: 0.18
A35: =A34+1 -> 22 | B35: PNS22 | C35: 48236900 | E35: PNS 500ml Paper Tray [VP] (135x85x40mm) * PCS | F35: 2.8 | G35: =(F35*J35)+F35 -> 3.304 | H35: Pcs | I35: 900 | J35: 0.18
A36: =A35+1 -> 23 | B36: PNS23 | C36: 48236900 | E36: PNS 750ml Paper Trays (150x100x)[VP]* PCS | F36: 3.25 | G36: =(F36*J36)+F36 -> 3.835 | H36: Pcs | I36: 600 | J36: 0.18
A37: =A36+1 -> 24 | B37: PNS24 | C37: 48236900 | E37: PNS 1000ml Paper Trays (165x120x) [VP] * PCS | F37: 3.55 | G37: =(F37*J37)+F37 -> 4.189 | H37: Pcs | I37: 300 | J37: 0.18
A38: =A37+1 -> 25 | B38: PNS25 | C38: 48236900 | E38: PNS Single Waffle Box | F38: 5.35 | G38: =(F38*J38)+F38 -> 5.6175 | H38: Pcs | I38: 1200 | J38: 0.05
A39: =A38+1 -> 26 | B39: PNS26 | C39: 48236900 | E39: PNS Double Waffle Box | F39: 6.45 | G39: =(F39*J39)+F39 -> 6.7725 | H39: Pcs | I39: 900 | J39: 0.05
A40: =A39+1 -> 27 | B40: PNS27 | C40: 48236900 | E40: Quick Pack Snack Box | F40: 5.15 | G40: =(F40*J40)+F40 -> 5.4075 | H40: Pcs | I40: 900 | J40: 0.05
A41: =A40+1 -> 28 | B41: PNS28 | C41: 48236900 | E41: 4.5 " PNS Paper Boat Tray | F41: 1.15 | G41: =(F41*J41)+F41 -> 1.357 | H41: Pcs | I41: 8000 | J41: 0.18
A42: =A41+1 -> 29 | B42: PNS29 | C42: 48236900 | E42: 5.5" PNS Paper Boat Tray | F42: 1.35 | G42: =(F42*J42)+F42 -> 1.593 | H42: Pcs | I42: 6000 | J42: 0.18
A43: =A42+1 -> 30 | B43: PNS30 | C43: 48236900 | E43: 6 " PNS Paper Boat Tray | F43: 1.68 | G43: =(F43*J43)+F43 -> 1.9824 | H43: Pcs | I43: 5000 | J43: 0.18
A44: =A43+1 -> 31 | B44: PNS31 | C44: 48236900 | E44: 8-Cavity Meal Tray Box Kraft/White (300gsm) * 100pcs | F44: 16 | G44: =(F44*J44)+F44 -> 16.8 | H44: Pcs | I44: 100 | J44: 0.05
A45: =A44+1 -> 32 | B45: PNS32 | C45: 48236900 | E45: PNS 12x3.75x3.5 Dosa Box with Insert (White/Kraft) | F45: 12.4 | G45: =(F45*J45)+F45 -> 13.02 | H45: Pcs | I45: 100 | J45: 0.05
A46: =A45+1 -> 33 | B46: PNS33 | C46: 48236900 | E46: PNS 12x7x2 Dosa Box with Insert (White/Kraft) | F46: 14.3 | G46: =(F46*J46)+F46 -> 15.015 | H46: Pcs | I46: 100 | J46: 0.05
A47: =A46+1 -> 34 | B47: PNS34 | C47: 48236900 | E47: PNS Sleeves 16 x 3.25 | F47: 2.15 | G47: =(F47*J47)+F47 -> 2.537 | H47: Pcs | I47: 5000 | J47: 0.18
A48: 35 | E48: 6.5x6.5 Ecowrap Printed Checks cut sheet [Purple] * Pcs | F48: 0.5 | G48: =(F48*J48)+F48 -> 0.59 | H48: Pcs | I48: 500 = 1Pac | J48: 0.18
B49: PNS30 | E49: PNS 606030 Prnt Brownie Tray
B50: PNS31 | E50: PNS 906030 RE Prnt Pastry Tray
E51: CAKE PASTRY BOARD RD BLACK 3.50X3.50 | F51: 0.9 | G51: =F51+F51*J51 -> 1.062 | H51: Pcs | I51: 5000 | J51: 0.18
E52: CAKE PASTRY BOARD RT BLACK 3.50X2 | F52: 0.9 | G52: =F52+F52*J52 -> 1.062 | H52: Pcs | I52: 5000 | J52: 0.18
E53: CAKE PASTRY BOARD TR BLACK 4.50X3 | F53: 0.9 | G53: =F53+F53*J53 -> 1.062 | H53: Pcs | I53: 5000 | J53: 0.18
E54: CAKE PASTRY BOARD SQ BLACK 3.50X3.50 | F54: 1.4 | G54: =F54+F54*J54 -> 1.652 | H54: Pcs | I54: 5000 | J54: 0.18
E55: CAKE PASTRY BOARD SQ GOLD 3.50 x 3.50 | F55: 1.4 | G55: =F55+F55*J55 -> 1.652 | H55: Pcs | I55: 5000 | J55: 0.18
E56: CAKE PASTRY BOARD RT GOLD 3.50 x 2 | F56: 1 | G56: =F56+F56*J56 -> 1.18 | H56: Pcs | I56: 5000 | J56: 0.18
A57: =A56+1 -> 1 | E57: CAKE PASTRY BOARD TR GOLD 4.50x3 | F57: 1 | G57: =F57+F57*J57 -> 1.18 | H57: Pcs | I57: 5000 | J57: 0.18
A58: =A57+1 -> 2 | E58: CAKE PASTRY BOARD RD GOLD 3.50x3.50 | F58: 1 | G58: =F58+F58*J58 -> 1.18 | H58: Pcs | I58: 5000 | J58: 0.18
E59: A&M Paper Products
E60: PNS French Fries Medium Pocket Printed (A&M) * 5000Pcs | F60: 1.6 | G60: =F60+F60*J60 -> 1.888 | H60: Pcs | I60: 5000 | J60: 0.18
E61: 6X6 BOAT TRAY BOAT TRAY BROWN(A&M) * 3200PC
A63: 1 | E63: 250ml Spout Pouch[Com Prnt]*1000pcs 12(P)+12(MP)+100(LD) | F63: 4.8 | G63: =(F63*J63)+F63 -> 5.664 | H63: Pcs | I63: 900 | J63: 0.18
A64: 2 | E64: 400ml Spout Pouch[Com Prnt]*1000pcs 12(P)+9(AL)+105(LD) | F64: 6 | G64: =(F64*J64)+F64 -> 7.08 | H64: Pcs | I64: 800 | J64: 0.18

Sheet JP Product
A1: Neeyog Packaging
A2: OFF:20, Gr Floor,Sidhpura Ind.Estate,S.V.Road,Gaiwadi Rd,Near Agilus Diagnostic Center,Goregaon(W),Mum- 062
A3: Phone : 022-28760709 Mobile 9867607003 Email:neeyog@gmail.com
A4: www.neeyog.com/www.indiamart.com/neeyogpackaging/www.facebook.com/neeyogpack
K5: ='Summary Sheet'!C7 -> Date 16.06.2026
A6: JP Product Price List
A8: Sr No | B8: Photos | C8: Item Name | D8: Item Code No | E8: Size in (mm) | F8: Board | G8: Basic | H8: Rate Incl Gst | I8: Box Pack | J8: MOQ Pack | K8: HSN code | L8: GST%
A9: FLAT BOXES
A10: 1 | C10: Wrap box | D10: JP-0A-8002 | E10: 203 x 50 x 45 | F10: FBB | G10: 3.4 | H10: =G10+G10*L10 -> 3.57 | I10: 1000 | J10: 3000 | K10: 48192020 | L10: 0.05
A11: 2 | C11: Wrap box Big | D11: JP-0A-8006 | E11: 203 x 65 x 65 | F11: FBB | G11: 4.85 | H11: =G11+G11*L11 -> 5.0925 | I11: 400 | J11: 2400 | K11: 48192020 | L11: 0.05
A12: 3 | C12: Unprinted Dosa Box | D12: JP-0H-8007 | E12: 305 x 76 x 45 | F12: Duplex with FGC | G12: 4.2 | H12: =G12+G12*L12 -> 4.41 | I12: 500 | J12: 1500 | K12: 48192020 | L12: 0.05
A13: 4 | C13: Unprinted Frankie | D13: JP-0A-8008 | E13: 227 x 70 x 90 | F13: FBB | G13: 2.25 | H13: =G13+G13*L13 -> 2.3625 | I13: 1200 | J13: 2400 | K13: 48192020 | L13: 0.05
A14: 5 | C14: Kraft Frankie | D14: JP-0M-8008 | E14: 227 x 70 x 90 | F14: Kraft | G14: 2.25 | H14: =G14+G14*L14 -> 2.3625 | I14: 1200 | J14: 2400 | K14: 48192020 | L14: 0.05
A15: 6 | C15: Frankie Generic Printed | D15: JP-0A-8008 | E15: 227 x 70 x 90 | F15: FBB | G15: 2.65 | H15: =G15+G15*L15 -> 2.7825 | I15: 1200 | J15: 2400 | K15: 48192020 | L15: 0.05
A16: 7 | C16: Waffle Pouch | D16: JP-25A-5008 | E16: 5x5x1 inches | F16: FBB | G16: 2.7 | H16: =G16+G16*L16 -> 2.835 | I16: 1500 | J16: 3000 | K16: 48192020 | L16: 0.05
A17: 8 | C17: Single Waffle Box | D17: JP-25A-5009 | E17: 11.5 x 5.5 x 11.2 | F17: FBB | G17: 5.6 | H17: =G17+G17*L17 -> 5.88 | I17: 500 | J17: 1500 | K17: 48192020 | L17: 0.05
A18: BURGER BOXES
A19: 9 | C19: Burger Box | D19: JP-1A-1001 | E19: 110 x 110 x 55 | F19: FBB | G19: 5.25 | H19: =G19+G19*L19 -> 5.5125 | I19: 300 | J19: 600 | K19: 48192020 | L19: 0.05
A20: 10 | C20: Unprinted Burger Box | D20: JP-1A-1001 | E20: 110 x 110 x 55 | F20: FBB | G20: 4.8 | H20: =G20+G20*L20 -> 5.04 | I20: 300 | J20: 600 | K20: 48192020 | L20: 0.05
A21: SANDWICH BOXES
A22: 11 | C22: Sandwich Box | D22: JP-10A-6001 | E22: 123(l)x123(B)x74(W) | F22: FBB | G22: 5 | H22: =G22+G22*L22 -> 5.25 | I22: 400 | J22: 1600 | K22: 48192020 | L22: 0.05
A23: 12 | C23: Unprinted Sandwich Box | D23: JP-10A-6001 | E23: 123(l)x123(B)x74(W) | F23: FBB | G23: 4.65 | H23: =G23+G23*L23 -> 4.8825 | I23: 400 | J23: 1600 | K23: 48192020 | L23: 0.05
A24: 13 | C24: Single Sandwich Box | D24: JP-10A-6004 | E24: 167 x 85 x 55 | F24: FBB | G24: 4.8 | H24: =G24+G24*L24 -> 5.04 | I24: 500 | J24: 2000 | K24: 48192020 | L24: 0.05
A25: 14 | C25: Indian Grill Sandwich | D25: JP-11A-6002 | E25: 130 x 110 x 50 | F25: FBB | G25: 5.8 | H25: =G25+G25*L25 -> 6.09 | I25: 600 | J25: 1200 | K25: 48192020 | L25: 0.05
A26: POPCORN BOXES
A27: 15 | C27: Popcorn 32 oz | D27: JP-8A-7005 | E27: 100 x 100 x 117 | F27: FBB | G27: 5.35 | H27: =G27+G27*L27 -> 6.313 | I27: 400 | J27: 800 | K27: 48236900 | L27: 0.18
A28: 16 | C28: Popcorn 64 oz | D28: JP-8A-7004 | E28: 120 x 120 x 190 | F28: FBB | G28: 7.2 | H28: =G28+G28*L28 -> 8.496 | I28: 500 | J28: 1000 | K28: 48236900 | L28: 0.18
A29: CUP HOLDERS
A30: 17 | C30: 2 Cup Holder | D30: JP-30-1401 | E30: 180 x 90 x 50 | F30: Duplex | G30: 2.65 | H30: =G30+G30*L30 -> 2.7825 | I30: 700 | J30: 1400 | K30: 48192020 | L30: 0.05
A31: 18 | C31: Single cup Holder | D31: JP-30-1415 | E31: 90 x 90 x 50 | F31: Duplex | G31: 2.35 | H31: =G31+G31*L31 -> 2.4675 | I31: 1000 | J31: 2000 | K31: 48192020 | L31: 0.05
A32: 19 | C32: 4 cup Holder | D32: JP-30-1402 | E32: 180 x 180 x 50 | F32: Duplex | G32: 6 | H32: =G32+G32*L32 -> 6.3 | I32: 500 | J32: 1000 | K32: 48192020 | L32: 0.05
A33: MEAL BOXES
A34: 20 | C34: 500 ml Meal box | D34: JP-7A-4003 | E34: 95 x 85 x 90 | F34: FBB | G34: 5.9 | H34: =G34+G34*L34 -> 6.195 | I34: 300 | J34: 600 | K34: 48192020 | L34: 0.05
A35: 21 | C35: 700 ml Meal box | D35: JP-7A-4004 | E35: 130 x 105 x 60 | F35: FBB | G35: 6.15 | H35: =G35+G35*L35 -> 6.4575 | I35: 300 | J35: 600 | K35: 48192020 | L35: 0.05
A36: 22 | C36: Single Serving Mealbox | D36: JP-29-1305 | E36: 170(l)x180(b)x125(w) | F36: Whiteback | G36: 13.1 | H36: =G36+G36*L36 -> 13.755 | I36: 250 | J36: 250 | K36: 48192020 | L36: 0.05
A37: FRIES SCOOP
A38: 23 | C38: Fries Scoop (small) | D38: JP-9A-1201 | E38: 80 x 90 | F38: FBB | G38: 2.35 | H38: =G38+G38*L38 -> 2.4675 | I38: 600 | J38: 2400 | K38: 48192020 | L38: 0.05
A39: 24 | C39: Fries Cone with sauce pocket | D39: JP-9A-1207 | E39: 280x200x165 | F39: FBB | G39: 3.6 | H39: =G39+G39*L39 -> 3.78 | I39: 1000 | J39: 2000 | K39: 48192020 | L39: 0.05
A40: SNACK BOXES
A41: Sr No | B41: Photos | C41: Item Name | D41: Item Code No | E41: Size in (mm) | F41: Board | G41: Basic | H41: Rate Incl Gst | I41: Box Pack | J41: MOQ Pack | K41: HSN code | L41: GST%
A42: 25 | C42: Snack Box L.P | D42: JP-2A-2001 | E42: 165 x 110 x 60 | F42: FBB | G42: 5.85 | H42: =G42+G42*L42 -> 6.1425 | I42: 300 | J42: 600 | K42: 48192020 | L42: 0.05
A43: 26 | C43: Snack Wok Box | D43: JP-2A-2013 | E43: 153 x102 x 43 | F43: FBB | G43: 4.95 | H43: =G43+G43*L43 -> 5.1975 | I43: 300 | J43: 600 | K43: 48192020 | L43: 0.05
A44: 27 | C44: 250ml White Snack Box | D44: JP-2-2023EW | E44: Top 110x90x40 Bottom90x70x40 | F44: FBB + PE | G44: 3.6 | H44: =G44+G44*L44 -> 3.78 | I44: 850 | J44: 850 | K44: 48192090 | L44: 0.05
A45: 28 | C45: 500ml White Snack Box | D45: JP-2-2024EW | E45: Top 150x100x40 Bottom 135x85x40 | F45: FBB + PE | G45: 4.3 | H45: =G45+G45*L45 -> 4.515 | I45: 500 | J45: 1000 | K45: 48192090 | L45: 0.05
A46: 29 | C46: 750ml White Snack Box | D46: JP-2-2025EW | E46: Top170x120x45 Bottom150x100x45 | F46: FBB + PE | G46: 5.55 | H46: =G46+G46*L46 -> 5.8275 | I46: 400 | J46: 800 | K46: 48192090 | L46: 0.05
A47: 30 | C47: 1000ml White Snack Box | D47: JP-2-2026EW | E47: Top180x135x40 Bottom165x120x40 | F47: FBB + PE | G47: 6.8 | H47: =G47+G47*L47 -> 7.14 | I47: 400 | J47: 800 | K47: 48192090 | L47: 0.05
A48: 31 | C48: 1250ml White Snack Box | D48: JP-2-2027EW | E48: Top 200x140x50 Bottom180x120x50 | F48: FBB + PE | G48: 7.5 | H48: =G48+G48*L48 -> 7.875 | I48: 400 | J48: 800 | K48: 48192090 | L48: 0.05
A49: SNACK BOXES KRAFT
A50: Sr No | B50: Photos | C50: Item Name | D50: Item Code No | E50: Size in (mm) | F50: Board | I50: Box Pack | J50: MOQ Pack | K50: HSN code | L50: GST%
A51: 32 | C51: Snack Box Kraft | D51: JP-2M-2013 | E51: 153 x102 x 43 | F51: Kraft + FGC | G51: 4.6 | H51: =G51+G51*L51 -> 4.83 | I51: 300 | J51: 600 | K51: 48192020 | L51: 0.05
A52: 33 | C52: 250ml Kraft Snack Box | D52: JP-2-2023EK | E52: Top 110x90x40 Bottom90x70x40 | F52: Kraft +P.E | G52: 3.75 | H52: =G52+G52*L52 -> 3.9375 | I52: 850 | J52: 850 | K52: 48192090 | L52: 0.05
A53: 34 | C53: 500ml Kraft Snack Box | D53: JP-2-2024EK | E53: Top 150x100x40 Bottom 135x85x40 | F53: Kraft +P.E | G53: 4.2 | H53: =G53+G53*L53 -> 4.41 | I53: 500 | J53: 1000 | K53: 48192090 | L53: 0.05
A54: 35 | C54: 750ml Kraft Snack Box | D54: JP-2-2025EK | E54: Top170x120x45 Bottom150x100x45 | F54: Kraft +P.E | G54: 5.65 | H54: =G54+G54*L54 -> 5.9325 | I54: 400 | J54: 800 | K54: 48192090 | L54: 0.05
A55: 36 | C55: 1000ml Kraft Snack Box | D55: JP-2-2026EK | E55: Top180x135x40 Bottom165x120x40 | F55: Kraft +P.E | G55: 7.15 | H55: =G55+G55*L55 -> 7.5075 | I55: 400 | J55: 800 | K55: 48192090 | L55: 0.05
A56: 37 | C56: 1250ml Kraft Snack Box | D56: JP-2-2027EK | E56: Top 200x140x50 Bottom180x120x50 | F56: Kraft +P.E | G56: 7.6 | H56: =G56+G56*L56 -> 7.98 | I56: 400 | J56: 800 | K56: 48192090 | L56: 0.05
A57: TRAYS IN KRAFT
A58: 38 | C58: Dip with dip tray medium | D58: JP-5-3025NK | E58: 190 x 95 x 40 | F58: Kraft +P.E | G58: 3.55 | H58: =G58+G58*L58 -> 4.189 | I58: 500 | J58: 1000 | K58: 48236900 | L58: 0.18
A59: 39 | C59: 250 ml Kraft Tray | D59: JP-5-3032EK | E59: Top-110 x 90 x 40 Bottom -90 x 70 x 40 | F59: Kraft +P.E | G59: 2.3 | H59: =G59+G59*L59 -> 2.714 | I59: 1000 | J59: 1000 | K59: 48236900 | L59: 0.18
A60: 40 | C60: 500 ml Kraft Tray | D60: JP-5-3033EK | E60: Top-150 x 100 x 40 Bottom-135x85x40 | F60: Kraft +P.E | G60: 3 | H60: =G60+G60*L60 -> 3.54 | I60: 500 | J60: 1000 | K60: 48236900 | L60: 0.18
A61: 41 | C61: 750 ml Kraft Tray | D61: JP-5-3034EK | E61: Top-170x120x45 Bottom-150x100x45 | F61: Kraft +P.E | G61: 3.75 | H61: =G61+G61*L61 -> 4.425 | I61: 500 | J61: 1000 | K61: 48236900 | L61: 0.18
A62: 42 | C62: 1000 ml Kraft Tray | D62: JP-5-3035EK | E62: Top-180 x 135x 45 Bottom-165x120x45 | F62: Kraft +P.E | G62: 4.35 | H62: =G62+G62*L62 -> 5.133 | I62: 450 | J62: 900 | K62: 48236900 | L62: 0.18
A63: 43 | C63: 1250 ml Kraft Tray | D63: JP-5-3036EK | E63: Top-200x140x50 Bottom-180x120x50 | F63: Kraft +P.E | G63: 4.7 | H63: =G63+G63*L63 -> 5.546 | I63: 450 | J63: 900 | K63: 48236900 | L63: 0.18
A64: TRAYS
A65: Sr No | B65: Photos | C65: Item Name | D65: Item Code No | E65: Size in (mm) | F65: Board | I65: Box Pack | J65: MOQ Pack | K65: HSN code | L65: GST%
A66: 44 | C66: Small Wok tray | D66: JP-5A-3005 | E66: 100 x100 x 40 | F66: FBB | G66: 2.7 | H66: =G66+G66*L66 -> 3.186 | I66: 800 | J66: 1600 | K66: 48236900 | L66: 0.18
A67: 45 | C67: Medium Wok tray | D67: JP-5A-3006 | E67: 144 x 80 x 45 | F67: FBB | G67: 3.05 | H67: =G67+G67*L67 -> 3.599 | I67: 600 | J67: 1200 | K67: 48236900 | L67: 0.18
A68: 46 | C68: 250 ml White Tray | D68: JP-5-3032EW | E68: Top-110 x 90 x 40 Bottom-90x70x40 | F68: FBB + PE | G68: 2.2 | H68: =G68+G68*L68 -> 2.596 | I68: 1000 | J68: 1000 | K68: 48236900 | L68: 0.18
A69: 47 | C69: 500 ml White Tray | D69: JP-5A-3033EW | E69: Top-150 x 100 x 40 Bottom-135x85x40 | F69: FBB + PE | G69: 2.85 | H69: =G69+G69*L69 -> 3.363 | I69: 500 | J69: 1000 | K69: 48236900 | L69: 0.18
A70: 48 | C70: 750 ml White Tray | D70: JP-5-3034EW | E70: Top-170x120x45 Bottom-150x100x45 | F70: FBB + PE | G70: 3.6 | H70: =G70+G70*L70 -> 4.248 | I70: 500 | J70: 1000 | K70: 48236900 | L70: 0.18
A71: 49 | C71: 1000 ml White Tray | D71: JP-5-3035EW | E71: Top-180 x 135x 45 Bottom-165x120x45 | F71: FBB + PE | G71: 4.15 | H71: =G71+G71*L71 -> 4.897 | I71: 450 | J71: 900 | K71: 48236900 | L71: 0.18
A72: 50 | C72: 1250 ml White Tray | D72: JP-5-3036EW | E72: Top-200x140x50 Bottom-180x120x50 | F72: FBB + PE | G72: 4.5 | H72: =G72+G72*L72 -> 5.31 | I72: 450 | J72: 900 | K72: 48236900 | L72: 0.18
A73: 51 | C73: Stick Tray (Potato Swirls) | D73: JP-5I-3039 | E73: Top-11.25x4.5x2" Bottom-10x3x2" | F73: Duplex with FGC | G73: 4.9 | H73: =G73+G73*L73 -> 5.782 | I73: 300 | J73: 1200 | K73: 48236900 | L73: 0.18
A74: 52 | C74: Dip-In Tray | D74: JP -5A-3042 | E74: 157 x 95 x 44 | F74: FBB | G74: 4.25 | H74: =G74+G74*L74 -> 5.015 | I74: 1000 | J74: 2000 | K74: 48236900 | L74: 0.18
A75: DONER BOXES
A76: 53 | C76: Doner Box 26 OZ | D76: JP-31E-1502 | E76: 750ml | F76: FBB + PE | G76: 6.2 | H76: =G76+G76*L76 -> 7.316 | I76: 600 | J76: 2400 | K76: 48236900 | L76: 0.18
A77: 54 | C77: Doner Box 32 OZ | D77: JP-31E-1503 | E77: 1000ml | F77: FBB + PE | G77: 7.3 | H77: =G77+G77*L77 -> 8.614 | I77: 600 | J77: 2400 | K77: 48236900 | L77: 0.18

Sheet PS
A1: Neeyog Packaging | I1: Summary Sheet' | P1: Mamtora | Q1: MM
A2: OFF: 20, Gr Floor,Sidhpura Ind.Estate,S.V.Road,Gaiwadi Rd,Near Agilus Diagnostic Center,Goregaon(W),Mum- 062 | L2: NL | M2: New Launch | P2: Bhiwandi | Q2: BW
A3: Phone : 28760709 Mobile 9867607003 Email:neeyog@gmail.com | L3: FM | N3: 1-2 DAY | P3: Shop | Q3: SH
A4: www.neeyog.com/www.indiamart.com/neeyogpackaging/www.facebook.com/neeyogpack | L4: LS | M4: Limited Stock | N4: 3-4 DAYS | P4: Vapi | Q4: VP
L5: APO | M5: As per Order | N5: 15-20 DAYS | P5: Bansi | Q5: BN
A6: Wholesale PS items Products Price List | E6: ='Summary Sheet'!C7 -> Date 16.06.2026
A8: Sr. No. | B8: HSN CODE | C8: PS PRODUCTS (HSN Code - 39249090) | D8: Rate Excl GST | E8: Rate Incl GST | F8: Per | G8: Packing | H8: GST | I8: Primary Godown | J8: Movement
C9: NP Products
A10: 1 | B10: 39249090 | C10: NP PS 1 SQ Biq 250ml Cup (N25) | D10: 5.15 | E10: =D10*1.18 -> 6.077 | F10: Pcs | G10: 1200 | H10: 0.18 | I10: BN | J10: FM
A11: =A10+1 -> 2 | B11: 39249090 | C11: NP PS 2 Big Triangle Cont 175ml | D11: 4.5 | E11: =D11*1.18 -> 5.31 | F11: Pcs | G11: 1200 | H11: 0.18 | I11: BN | J11: FM
A12: =A11+1 -> 3 | B12: 39249090 | C12: NP PS 3 Triangle Small Cup 60ml | D12: 1.85 | E12: =D12*1.18 -> 2.183 | F12: Pcs | G12: 3900 | H12: 0.18 | I12: BN | J12: FM
A13: =A12+1 -> 4 | B13: 39249090 | C13: NP PS 4 SQ Small Cup 60ml | D13: 1.85 | E13: =D13*1.18 -> 2.183 | F13: Pcs | G13: 3000 | H13: 0.18 | I13: BN | J13: FM
A14: =A13+1 -> 5 | B14: 39249090 | C14: NP PS 5 Hexa Shot Glass 60ml | D14: 1.85 | E14: =D14*1.18 -> 2.183 | F14: Pcs | G14: 3000 | H14: 0.18 | I14: BN | J14: FM
A15: =A14+1 -> 6 | B15: 39249090 | C15: NP PS 6 Solo Shot Glass | D15: 1.85 | E15: =D15*1.18 -> 2.183 | F15: Pcs | G15: 2000 | H15: 0.18 | I15: BN | J15: FM
A16: =A15+1 -> 7 | B16: 39249090 | C16: NP PS 7 SQ Cup 80 ml | D16: 2.65 | E16: =D16*1.18 -> 3.127 | F16: Pcs | G16: 2000 | H16: 0.18 | I16: BN | J16: LS
A17: =A16+1 -> 8 | B17: 39249090 | C17: NP PS 8 SQ 120ml Cup | D17: 4.25 | E17: =D17*1.18 -> 5.015 | F17: Pcs | G17: 1200 | H17: 0.18 | I17: BW | J17: FM
A18: =A17+1 -> 9 | B18: 39249090 | C18: NP PS 9 - 4 inch Boat Tray (Black/Clear) | D18: 2.15 | E18: =D18*1.18 -> 2.537 | F18: Pcs | G18: 3000 | H18: 0.18 | I18: BW | J18: FM
A19: =A18+1 -> 10 | B19: 39249090 | C19: NP PS 10 Flower Wati 60ml | D19: 2.1 | E19: =D19*1.18 -> 2.478 | F19: Pcs | G19: 3000 | H19: 0.18 | I19: BW | J19: FM
A20: =A19+1 -> 11 | B20: 39249090 | C20: NP PS 11 - 6" Flower Plate (Black / Trans) | D20: 4.3 | E20: =D20*1.18 -> 5.074 | F20: Pcs | G20: 1000 | H20: 0.18 | I20: BW | J20: LS
A21: =A20+1 -> 12 | B21: 39249090 | C21: NP PS 12 Chamcham Wati (Old NP PS 22) | D21: 1.9 | E21: =D21*1.18 -> 2.242 | F21: Pcs | G21: 6000 | H21: 0.18 | J21: APO
A22: =A21+1 -> 13 | B22: 39249090 | C22: NP PS 13 125ml Matka Cont [Trans] | D22: 3.1 | E22: =D22*1.18 -> 3.658 | F22: Pcs | G22: 1200 | H22: 0.18 | I22: BW | J22: FM
A23: =A22+1 -> 14 | B23: 39249090 | C23: NP PS 14 Square Cont 100ml [Trans] | D23: 3.35 | E23: =D23*1.18 -> 3.953 | F23: Pcs | G23: 1200 | H23: 0.18 | J23: APO
A24: =A23+1 -> 15 | B24: 39249090 | C24: NP PS 15 Rect Mousse Cont 120ml | D24: 3.65 | E24: =D24*1.18 -> 4.307 | F24: Pcs | G24: 1200 | H24: 0.18 | I24: BW | J24: FM
A25: =A24+1 -> 16 | B25: 39249090 | C25: NP PS 16 Tequila Shot Cont 30ml | D25: 1.3 | E25: =D25*1.18 -> 1.534 | F25: Pcs | G25: 1600 | H25: 0.18 | J25: APO
A26: =A25+1 -> 17 | B26: 39249090 | C26: NP PS 17 Ice Cream Bowl [Blk/Trans] | D26: 3.1 | E26: =D26*1.18 -> 3.658 | F26: Pcs | G26: 3000 | H26: 0.18 | J26: APO
A27: =A26+1 -> 18 | B27: 39249090 | C27: NP PS 18 SQ Jelly Cont 60ml | D27: 1.25 | E27: =D27*1.18 -> 1.475 | F27: Pcs | G27: 5000 | H27: 0.18 | J27: APO
A28: =A27+1 -> 19 | B28: 39249090 | C28: NP PS 19 3" RD Starter Plate (Black/Trans) * 6000pcs | D28: 1.25 | E28: =D28*1.18 -> 1.475 | F28: Pcs | G28: 6000 | H28: 0.18 | J28: APO
A29: =A28+1 -> 20 | B29: 39249090 | C29: NP-PS-20 100ml Cup (Clear) | D29: 2.5 | E29: =D29*1.18 -> 2.95 | F29: Pcs | G29: 1500 | H29: 0.18 | I29: BW | J29: FM
A30: =A29+1 -> 21 | B30: 39249090 | C30: NP PS 21 Rect Pastry Tray (Blk) | D30: 2.45 | E30: =D30*1.18 -> 2.891 | F30: Pcs | G30: 2500 | H30: 0.18 | I30: BW | J30: LS
A31: =A30+1 -> 22 | B31: 39249090 | C31: NP PP 22 SQ 3x3 Tray (Blk) | D31: 2.7 | E31: =D31*1.18 -> 3.186 | F31: Pcs | G31: 2000 | H31: 0.18 | I31: BW | J31: LS
A32: =A31+1 -> 23 | B32: 39249090 | C32: NP PS 23 Pan Dish (Trans) | D32: 1.5 | E32: =D32*1.18 -> 1.77 | F32: Pcs | G32: 5000 | H32: 0.18 | J32: APO
A33: =A32+1 -> 24 | B33: 39249090 | C33: NP PS 24 Oval Dish | D33: 1.5 | E33: =D33*1.18 -> 1.77 | F33: Pcs | G33: 5000 | H33: 0.18 | J33: APO
A34: =A33+1 -> 25 | B34: 39249090 | C34: NP PS 25 4Cavity Mithai Box 125X125MM X 40MM | D34: 31.5 | E34: =D34*1.18 -> 37.17 | F34: Pcs | G34: 150 | H34: 0.18 | J34: APO
A35: =A34+1 -> 26 | B35: 39249090 | C35: NP PS 26 RD Jelly Cont 60ml [Trans] | D35: 1.25 | E35: =D35*1.18 -> 1.475 | F35: Pcs | G35: 1400 | H35: 0.18 | J35: APO
A36: =A35+1 -> 27 | B36: 39249090 | C36: NP PS 27 Cham Cham Tray RT Cont [Trans] (VE) | D36: 2 | E36: =D36*1.18 -> 2.36 | F36: Pcs | G36: 2600 | H36: 0.18 | J36: APO
A37: =A36+1 -> 28 | B37: 39249090 | C37: NP PS 28 150ml RD Glass Cont [Trans] | D37: 4.2 | E37: =D37*1.18 -> 4.956 | F37: Pcs | G37: 1400 | H37: 0.18 | J37: APO
A38: =A37+1 -> 29 | B38: 39249090 | C38: NP PS 29 200ml SQ Glass Cont [Trans] | D38: 4.8 | E38: =D38*1.18 -> 5.664 | F38: Pcs | G38: 1200 | H38: 0.18 | J38: APO
A39: =A38+1 -> 30 | C39: NP PS 30 Wine Glass 130ml | D39: 3.2 | E39: Upcoming | H39: 0.18
A40: =A39+1 -> 31 | C40: NP PS 31 (GT) Ice Cream Bowl (120ml) | D40: 3.35 | E40: =D40*1.18 -> 3.953 | F40: Pcs | G40: 1200 | H40: 0.18
A41: =A40+1 -> 32 | C41: NP PS 32 4 Cavity Sweet Box 125x125x30MM (WL) * 280Pcs | D41: 25 | E41: =D41*1.18 -> 29.5 | F41: Pcs | G41: 280 | H41: 0.18
A42: 33 | C42: NP PS 33 SQ Wati | D42: 2.1 | E42: =D42*1.18 -> 2.478 | F42: Pcs | H42: 0.18
A43: =A42+1 -> 34 | B43: 39249090 | C43: NP PS 45 SQ Dessert Box ( 350ml) (85x85x65mm) | D43: 17 | E43: =D43+D43*H43 -> 20.06 | F43: Pcs | G43: 300 | H43: 0.18
A44: 35 | B44: 39249090 | C44: NP PS 51 SQ Dessert Box (250ml) (85x85x50mm) | D44: 13.5 | E44: =D44+D44*H44 -> 15.93 | F44: Pcs | H44: 0.18
C45: Black Pastry Tray With Lid
A46: 1 | B46: 39249090 | C46: PNS 8080 Pastry SQ HIPS Tray With Pet Dome Lid | D46: 4.75 | E46: =D46*1.18 -> 5.605 | F46: Pcs | G46: 1200 | H46: 0.18 | I46: BN | J46: LS
A47: 2 | B47: 39249090 | C47: PNS 1160 Pastry Rect HIPS Tray With Pet Dome Lid | D47: 4.2 | E47: =D47*1.18 -> 4.956 | F47: Pcs | G47: 1200 | H47: 0.18 | I47: BN | J47: LS
A48: =A47+1 -> 3 | B48: 39249090 | C48: PNS TP01 Pastry Triangle HIPS Tray With Pet Dome Lid | D48: 6.75 | E48: =D48*1.18 -> 7.965 | F48: Pcs | G48: 600 | H48: 0.18 | J48: APO
A49: 4 | B49: 39249090 | C49: LGP TP02 Pastry Triangle Small HIPS Tray With Pet Dome Lid(110x75x60mm) | D49: 3.2 | E49: =D49*1.18 -> 3.776 | F49: Pcs | G49: 750 | H49: 0.18
A50: 5 | C50: LGP TP03 Pastry [Rect] Small HIPS Tray With Pet Dome Lid * 750Pcs | D50: 3.2 | E50: =D50*1.18 -> 3.776 | F50: Pcs | G50: 750 | H50: 0.18
C51: Golden Pastry Tray With Lid
A52: 1 | B52: 39249090 | C52: PNS 8080 Pastry SQ PET Golden Tray With Pet Dome Lid | D52: 5.9 | E52: =D52*1.18 -> 6.962 | F52: Pcs | G52: 1200 | H52: 0.18
A53: 2 | B53: 39249090 | C53: PNS 1160 Pastry Rect PET Golden Tray With Pet Dome Lid | D53: 5.3 | E53: =D53*1.18 -> 6.254 | F53: Pcs | G53: 1200 | H53: 0.18
A54: 3 | B54: 39249090 | C54: PNS TP01 Pastry Triangle PET Golden Tray With Pet Dome Lid | D54: 8.4 | E54: =D54*1.18 -> 9.912 | F54: Pcs | G54: 600 | H54: 0.18
C55: Navin Products (HSN Code - 39249090) | D55: Basic Rate | E55: Incl. Gst Rate | F55: Unit | G55: Std. Pack. | H55: Gst
A56: 1 | B56: 39249090 | C56: N-1 LEAF SHAPE PLATE (K-12) | D56: 2.55 | E56: =D56*1.18 -> 3.009 | F56: Pcs | G56: 2400 | H56: 0.18 | J56: APO
A57: =A56+1 -> 2 | B57: 39249090 | C57: N-2 TRIANGLE GLASS (65 ML) PS 6 | D57: 3.6 | E57: =D57*1.18 -> 4.248 | F57: Pcs | G57: 1800 | H57: 0.18
A58: =A57+1 -> 3 | B58: 39249090 | C58: N-3 TRIANGLE GLASS (60ML) PS3 | D58: 2.3 | E58: =D58*1.18 -> 2.714 | F58: Pcs | G58: 2400 | H58: 0.18 | I58: Bansi | J58: APO
A59: =A58+1 -> 4 | B59: 39249090 | C59: N-4 SQUARE GLASS (50 ML)PS4 | D59: 2.3 | E59: =D59*1.18 -> 2.714 | F59: Pcs | G59: 2400 | H59: 0.18 | J59: APO
A60: =A59+1 -> 5 | B60: 39249090 | C60: N-5 LACE RD Cont 80ML | D60: 2.65 | E60: =D60*1.18 -> 3.127 | F60: Pcs | G60: 1500 | H60: 0.18 | J60: APO
A61: =A60+1 -> 6 | B61: 39249090 | C61: N-6 SHORT GLASS (65ML) | D61: 2.7 | E61: =D61*1.18 -> 3.186 | F61: Pcs | G61: 1800 | H61: 0.18 | I61: BN | J61: LS
A62: =A61+1 -> 7 | B62: 39249090 | C62: N-7 BIG FRUIT BOWL (160ML)PS2 | D62: 5.9 | E62: =D62*1.18 -> 6.962 | F62: Pcs | G62: 1000 | H62: 0.18 | J62: APO
A63: =A62+1 -> 8 | B63: 39249090 | C63: N-7 LID FOR N-7 | D63: 1.6 | E63: =D63*1.18 -> 1.888 | F63: Pcs | G63: 4800 | H63: 0.18 | J63: APO
A64: =A63+1 -> 9 | B64: 39249090 | C64: N-8 6 INCHES PLATE | D64: 4.2 | E64: =D64*1.18 -> 4.956 | F64: Pcs | G64: 720 | H64: 0.18 | J64: APO
A65: =A64+1 -> 10 | B65: 39249090 | C65: N-9 HEXAGON Cont 70ML | D65: 3.9 | E65: =D65*1.18 -> 4.602 | F65: Pcs | G65: 2400 | H65: 0.18 | J65: APO
A66: =A65+1 -> 11 | B66: 39249090 | C66: N-10 FLOWER VATI 65ML | D66: 2.55 | E66: =D66*1.18 -> 3.009 | F66: Pcs | G66: 2400 | H66: 0.18 | I66: BN | J66: FM
A67: =A66+1 -> 12 | B67: 39249090 | C67: N-11 SMALL SWEET HANDI 40ML (PS19) | D67: 2.45 | E67: =D67*1.18 -> 2.891 | F67: Pcs | G67: 2400 | H67: 0.18 | J67: APO
A68: =A67+1 -> 13 | B68: 39249090 | C68: N-12 PEPSI CUP (PS 23) 60ML | D68: 2.45 | E68: =D68*1.18 -> 2.891 | F68: Pcs | G68: 2400 | H68: 0.18 | J68: APO
A69: =A68+1 -> 14 | B69: 39249090 | C69: N-13 BIG DESIGNER BOWL 130ML | D69: 3.7 | E69: =D69*1.18 -> 4.366 | F69: Pcs | G69: 1500 | H69: 0.18 | I69: BN | J69: LS
A70: =A69+1 -> 15 | B70: 39249090 | C70: N-14 CYLINDERICAL SHOT GLASS (70ML) | D70: 3.25 | E70: =D70*1.18 -> 3.835 | F70: Pcs | G70: 1600 | H70: 0.18 | J70: APO
A71: =A70+1 -> 16 | B71: 39249090 | C71: N-15 DINNER SPOON (BLACK) | D71: 1 | E71: =D71*1.18 -> 1.18 | F71: Pcs | G71: 4000 | H71: 0.18 | J71: APO
A72: =A71+1 -> 17 | B72: 39249090 | C72: N-16 30 ML TEQUILA SHOT GLASS | D72: 1.5 | E72: =D72*1.18 -> 1.77 | F72: Pcs | G72: 2400 | H72: 0.18 | I72: BN | J72: LS
A73: =A72+1 -> 18 | B73: 39249090 | C73: N-17 150 ML WINE STAND CONT. | D73: 3.55 | E73: =D73*1.18 -> 4.189 | F73: Pcs | G73: 900 | H73: 0.18 | I73: BN | J73: FM
A74: =A73+1 -> 19 | B74: 39249090 | C74: N-18 200 ML FROSTED AIRLINE CONT. | D74: 3.6 | E74: =D74*1.18 -> 4.248 | F74: Pcs | G74: 1000 | H74: 0.18 | I74: BN | J74: FM
A75: =A74+1 -> 20 | B75: 39249090 | C75: N-19 250 ML PLAIN CONT. | D75: 4.1 | E75: =D75*1.18 -> 4.838 | F75: Pcs | G75: 1000 | H75: 0.18 | I75: BN | J75: FM
A76: =A75+1 -> 21 | B76: 39249090 | C76: N-20 100 ML CONT. | D76: 2.65 | E76: =D76*1.18 -> 3.127 | F76: Pcs | G76: 1500 | H76: 0.18 | I76: BN | J76: LS
A77: =A76+1 -> 22 | B77: 39249090 | C77: N-20 LID FOR N- 20 | D77: 0.9 | E77: =D77*1.18 -> 1.062 | F77: Pcs | G77: 4000 | H77: 0.18 | I77: BN | J77: LS
A78: =A77+1 -> 23 | B78: 39249090 | C78: N-21 SMALL SQ. BOWL 70ML | D78: 2.2 | E78: =D78*1.18 -> 2.596 | F78: Pcs | G78: 2400 | H78: 0.18 | I78: BN | J78: LS
A79: =A78+1 -> 24 | B79: 39249090 | C79: N-22 TART BOWL (K-10) 40ML | D79: 2.2 | E79: =D79*1.18 -> 2.596 | F79: Pcs | G79: 2400 | H79: 0.18 | I79: BN | J79: FM
A80: =A79+1 -> 25 | B80: 39249090 | C80: N-23 FORKS | D80: 1 | E80: =D80*1.18 -> 1.18 | F80: Pcs | G80: 4000 | H80: 0.18 | I80: BN | J80: FM
A81: =A80+1 -> 26 | B81: 39249090 | C81: N-24 Sporks | D81: 0.85 | E81: =D81*1.18 -> 1.003 | F81: Pcs | G81: 6000 | H81: 0.18 | J81: APO
A82: =A81+1 -> 27 | B82: 39249090 | C82: N-25 Big SQ Bowl 160ML | D82: 6.2 | E82: =D82*1.18 -> 7.316 | F82: Pcs | G82: 1000 | H82: 0.18 | J82: APO
A83: =A82+1 -> 28 | B83: 39249090 | C83: N-26 Oval Bowl 80ML | D83: 2.95 | E83: =D83*1.18 -> 3.481 | F83: Pcs | G83: 2400 | H83: 0.18 | I83: BN | J83: LS
A84: =A83+1 -> 29 | B84: 39249090 | C84: N-27 Short Glass 40 ML | D84: 2.1 | E84: =D84*1.18 -> 2.478 | F84: Pcs | G84: 4000 | H84: 0.18 | I84: BN | J84: LS
A85: =A84+1 -> 30 | B85: 39249090 | C85: N-28 Tall Mouse Glass 70 ML | D85: 2.85 | E85: =D85*1.18 -> 3.363 | F85: Pcs | G85: 2400 | H85: 0.18 | J85: APO
A86: =A85+1 -> 31 | B86: 39249090 | C86: N-29 Twisted Square Cup 65 ML | D86: 2.95 | E86: =D86*1.18 -> 3.481 | F86: Pcs | G86: 2400 | H86: 0.18 | J86: APO
A87: =A86+1 -> 32 | B87: 39249090 | C87: N-30 2 Piece Wine Glass 150ML | D87: 5.6 | E87: =D87*1.18 -> 6.608 | F87: Pcs | G87: 500 | H87: 0.18 | I87: BN | J87: LS
A88: =A87+1 -> 33 | B88: 39249090 | C88: N-31 Lotus Bowl 70ML | D88: 2.95 | E88: =D88*1.18 -> 3.481 | F88: Pcs | G88: 2400 | H88: 0.18 | I88: BN | J88: LS
A89: =A88+1 -> 34 | B89: 39249090 | C89: N-32 Boat Vati (PS 37) 30ML | D89: 2.1 | E89: =D89*1.18 -> 2.478 | F89: Pcs | G89: 3200 | H89: 0.18 | I89: BN | J89: LS
A90: =A89+1 -> 35 | B90: 39249090 | C90: N-33 90ML Glass | D90: 3.4 | E90: =D90*1.18 -> 4.012 | F90: Pcs | G90: 1440 | H90: 0.18 | J90: APO
A91: =A90+1 -> 36 | B91: 39249090 | C91: N-34 Round Bowl 110ML | D91: 3.5 | E91: =D91*1.18 -> 4.13 | F91: Pcs | G91: 1600 | H91: 0.18 | J91: APO
A92: =A91+1 -> 37 | B92: 39249090 | C92: N-35 Light Weight Dinner Spoon | D92: 0.85 | E92: =D92*1.18 -> 1.003 | F92: Pcs | G92: 6000 | H92: 0.18 | J92: APO
A93: =A92+1 -> 38 | B93: 39249090 | C93: N-36 Butter Knife | D93: 0.85 | E93: =D93*1.18 -> 1.003 | F93: Pcs | G93: 6000 | H93: 0.18 | J93: APO
A94: =A93+1 -> 39 | B94: 39249090 | C94: N-37 Lining Bowl Cont. 60ML | E94: =D94*1.18 -> 0 | F94: Pcs | G94: 2400 | H94: 0.18 | J94: APO
A95: =A94+1 -> 40 | B95: 39249090 | C95: N-38 SMALL DESSERT SPOON | D95: 0.45 | E95: =D95*1.18 -> 0.531 | F95: Pcs | G95: 8000 | H95: 0.18 | I95: BN | J95: LS
A96: =A95+1 -> 41 | B96: 39249090 | C96: N-39 3" SQ Plate | D96: 2.95 | E96: =D96*1.18 -> 3.481 | F96: Pcs | G96: 2000 | H96: 0.18 | J96: APO
A97: =A96+1 -> 42 | B97: 39249090 | C97: N-40 Shell Plate | D97: 2.55 | E97: =D97*1.18 -> 3.009 | F97: Pcs | G97: 2400 | H97: 0.18 | J97: APO
A98: =A97+1 -> 43 | B98: 39249090 | C98: N-41 SQUARE SALAD BOX | D98: 6.4 | E98: =D98*1.18 -> 7.552 | F98: Pcs | G98: 1000 | H98: 0.18 | J98: APO
A99: =A98+1 -> 44 | B99: 39249090 | C99: N-42 400ML SQUARE MITHAI BOX | D99: 11.55 | E99: =D99*1.18 -> 13.629 | F99: Pcs | G99: 500 | H99: 0.18 | J99: APO
A100: =A99+1 -> 45 | B100: 39249090 | C100: N-43 50ML SQURE LINING | D100: 2.55 | E100: =D100*1.18 -> 3.009 | F100: Pcs | G100: 2800 | H100: 0.18 | J100: APO
A101: =A100+1 -> 46 | B101: 39249090 | C101: N-44 30ML CHUMCHUM WATI | D101: 1.8 | E101: =D101*1.18 -> 2.124 | F101: Pcs | G101: 4000 | H101: 0.18 | J101: APO
...

Sheet SOS Bag & Sheet
A1: Neeyog Packaging | J1: Summary Sheet'!A1 | Q1: Mamtora | R1: MM
A2: OFF:20, Gr Floor,Sidhpura Ind.Estate,S.V.Road,Gaiwadi Rd,Near Agilus Diagnostic Center,Goregaon(W),Mum- 062 | M2: NL | N2: New Launch | Q2: Bhiwandi | R2: BW
A3: Phone : 022-28760709 Mobile 9867607003 Email:neeyog@gmail.com | M3: FM | O3: 1-2 DAY | Q3: Shop | R3: SH
A4: www.neeyog.com/www.neeyog.net/www.indiamart.com/neeyogpackaging/www.facebook.com/neeyogpack | M4: LS | N4: Limited Stock | O4: 3-4 DAYS | Q4: Vapi | R4: VP
M5: APO | N5: As per Order | O5: 15-20 DAYS | Q5: Bansi | R5: BN
A6: Paknserve Grocery Bags & Pouch / Ecowrapp Cut Sheet Price List | G6: Date: | H6: ='Summary Sheet'!C7 -> Date 16.06.2026
C8: V bottom MF Kraft bag 60GSm 24Bf (WxGxH) | D8: Rate/Kg | E8: Rate/Incl | F8: Pc/Kg | G8: Rate/PC | H8: Packing | I8: Gst% | J8: Primary Godown | K8: Movement | L8: Tally name
A9: 1 | B9: 48194000 | C9: 501 Kraft Bag 4x9x3 | D9: 75 | E9: =D9*I9+D9 -> 88.5 | F9: 170 | G9: =E9/F9 -> 0.52058824 | H9: 30 Kg | I9: 0.18 | J9: VP | K9: FM
A10: 2 | B10: 48194000 | C10: 502 Kraft Bag 5x11x3 | D10: 75 | E10: =D10*I10+D10 -> 88.5 | F10: 100 | G10: =E10/F10 -> 0.885 | H10: 30 Kg | I10: 0.18 | J10: VP | K10: FM
A11: 3 | B11: 48194000 | C11: 503 Kraft bag 6x11x3.5 | D11: 75 | E11: =D11*I11+D11 -> 88.5 | F11: 90 | G11: =E11/F11 -> 0.98333333 | H11: 30 Kg | I11: 0.18 | J11: VP | K11: FM
A12: 4 | B12: 48194000 | C12: 504 Kraft bag 6x13x3.5 | D12: 75 | E12: =D12*I12+D12 -> 88.5 | F12: 80 | G12: =E12/F12 -> 1.10625 | H12: 30 Kg | I12: 0.18 | J12: VP | K12: FM
A13: 5 | B13: 48194000 | C13: 505 Kraft Bag 8x15x4 | D13: 75 | E13: =D13*I13+D13 -> 88.5 | F13: 55 | G13: =E13/F13 -> 1.6090909 | H13: 30 Kg | I13: 0.18 | J13: VP | K13: FM
A14: 6 | B14: 48194000 | C14: 506Kraft bag 8x18x4 | D14: 75 | E14: =D14*I14+D14 -> 88.5 | F14: 50 | G14: =E14/F14 -> 1.77 | H14: 30 Kg | I14: 0.18 | J14: BANSI | K14: LS
C15: Brown SOS MF Kraft 80Gsm 24Bf (WxGxH) | D15: Rate/Kg | E15: Rate/Incl | F15: Pc/Kg | G15: Rate/PC | H15: Packing | I15: Gst%
A16: 1 | B16: 48194000 | C16: 6x4x12 Brown 80Gsm MF Kraft | D16: 75 | E16: =D16*I16+D16 -> 88.5 | F16: 61.507937 | G16: =E16/F16 -> 1.4388387 | H16: 30 Kg | I16: 0.18 | J16: VP | K16: FM | L16: 6.5x4x12 SOS SQ Bot Plain Brown MG Kraft (80g) * Kg
A17: 2 | B17: 48194000 | C17: 7.5x5x10 Brown 80Gsm MF Kraft | D17: 75 | E17: =D17*I17+D17 -> 88.5 | F17: 53 | G17: =E17/F17 -> 1.6698113 | H17: 30 Kg | I17: 0.18 | J17: VP | K17: FM
A18: 2 | B18: 48194000 | C18: 7x5x12 Brown 80Gsm MF Kraft | D18: 75 | E18: =D18*I18+D18 -> 88.5 | F18: 54 | G18: =E18/F18 -> 1.6388889 | H18: 30 Kg | I18: 0.18 | J18: VP | K18: FM
A19: 3 | B19: 48194000 | C19: 8.5x5x12 Brown 80Gsm MF Kraft | D19: 75 | E19: =D19*I19+D19 -> 88.5 | F19: 43 | G19: =E19/F19 -> 2.0581395 | H19: 30 Kg | I19: 0.18 | J19: VP | K19: FM
A20: 4 | B20: 48194000 | C20: 9x5x13 Brown 80Gsm MF Kraft | D20: 75 | E20: =D20*I20+D20 -> 88.5 | F20: 39 | G20: =E20/F20 -> 2.2692308 | H20: 30 Kg | I20: 0.18 | J20: VP | K20: FM
A21: 5 | B21: 48194000 | C21: 10x5x14 Brown 80Gsm MF Kraft | D21: 75 | E21: =D21*I21+D21 -> 88.5 | F21: 34 | G21: =E21/F21 -> 2.6029412 | H21: 30 Kg | I21: 0.18 | J21: VP | K21: FM | L21: 10x5x14 SOS SQ Bot Plain Brown MG Kraft (80g) * Kg
A22: 6 | B22: 48194000 | C22: 12x5x16 Brwon 80Gsm Mg Kraft | D22: 75 | E22: =D22*I22+D22 -> 88.5 | F22: 27 | G22: =E22/F22 -> 3.2777778 | H22: 30 Kg | I22: 0.18 | J22: VP | K22: FM | L22: 10x6x14 SOS SQ Bot Plain Brown MG Kraft (80g) * Kg
A23: 7 | B23: 48194000 | C23: 13x7x15 Brown 80Gsm MF Kraft | D23: 75 | E23: =D23*I23+D23 -> 88.5 | F23: 23 | G23: =E23/F23 -> 3.8478261 | H23: 30 Kg | I23: 0.18 | J23: VP | K23: FM | L23: 13x7x15 SOS SQ Bot Plain Brown MG Kraft (80g) * Kg
C24: Brown SOS MG Kraft 70Gsm 24Bf (WxGXH) | D24: Rate/Kg | E24: Rate/Incl | F24: Pc/Kg | G24: Rate/PC | H24: Packing | I24: Gst%
A25: 1 | B25: 48194000 | C25: 6x4x12 Brown 70Gsm Saffron Kraft | D25: 95 | E25: =D25*I25+D25 -> 112.1 | F25: 67 | G25: =E25/F25 -> 1.6731343 | H25: 25 Kg | I25: 0.18 | K25: APO
A26: 2 | B26: 48194000 | C26: 7x5x12 Brown 70Gsm Saffron kraft | D26: 95 | E26: =D26*I26+D26 -> 112.1 | F26: 55 | G26: =E26/F26 -> 2.0381818 | H26: 25 Kg | I26: 0.18 | K26: APO
A27: 3 | B27: 48194000 | C27: 7.5x5x10 Brown 70Gsm Saffron Kraft | D27: 95 | E27: =D27*I27+D27 -> 112.1 | F27: 61 | G27: =E27/F27 -> 1.8377049 | H27: 25 Kg | I27: 0.18 | J27: VP | K27: FM
A28: 4 | B28: 48194000 | C28: 9x5x13 Brown 70Gsm Saffron Kraft | D28: 95 | E28: =D28*I28+D28 -> 112.1 | F28: 44 | G28: =E28/F28 -> 2.5477273 | H28: 25 Kg | I28: 0.18 | J28: VP | K28: FM
C29: White SOS Mg Bleached Kraft 70Gsm 35Bf | D29: Rate/Kg | E29: Rate/Incl | F29: Pc/Kg | G29: Rate/PC | H29: Packing | I29: Gst%
A30: 1 | B30: 48194000 | C30: 6x4x12 White 70Gsm Bleached kraft | D30: 110 | E30: =D30*I30+D30 -> 129.8 | F30: 67 | G30: =E30/F30 -> 1.9373134 | H30: 2000 | I30: 0.18 | K30: APO
A31: 2 | B31: 48194000 | C31: 7.5x5x10 White 70Gsm Bleached Kraft | D31: 110 | E31: =D31*I31+D31 -> 129.8 | F31: 61 | G31: =E31/F31 -> 2.1278689 | H31: 2000 | I31: 0.18 | K31: APO
A32: 3 | B32: 48194000 | C32: 8.5x5x12 White 70Gsm Bleached Kraft | D32: 100 | E32: =D32*I32+D32 -> 118 | F32: 49 | G32: =E32/F32 -> 2.4081633 | H32: 1000 | I32: 0.18 | K32: APO
A33: 4 | B33: 48194000 | C33: 9x5x13 White 70Gsm Bleached Kraft | D33: 100 | E33: =D33*I33+D33 -> 118 | F33: 44 | G33: =E33/F33 -> 2.6818182 | H33: 1000 | I33: 0.18 | K33: APO
A34: In Bleached Kraft paper the Gsm may Vary ± 10% and Subject to availabilty of Paper
C36: EcoWrapp Paper Bag Oil proof 9Kit(OGR) | D36: Rate/Kg | E36: Rate/Incl | F36: Pc/Kg | G36: Rate/PC | H36: Packing | I36: Gst%
A37: 1 | B37: 48194000 | C37: Ecowrapp Pouch 5x8 48Gsm | D37: 160 | E37: =D37*I37+D37 -> 188.8 | F37: 330 | G37: =E37/F37 -> 0.57212121 | H37: 12 Kg | I37: 0.18 | J37: VP | K37: FM
A38: 2 | B38: 48194000 | C38: Ecowrapp Pouch 6x9 48Gsm | D38: 160 | E38: =D38*I38+D38 -> 188.8 | F38: 240 | G38: =E38/F38 -> 0.78666667 | H38: 12 Kg | I38: 0.18 | J38: VP | K38: FM
A39: 3 | B39: 48194000 | C39: Ecowrapp Pouch 8x10 48Gsm | D39: 160 | E39: =D39*I39+D39 -> 188.8 | F39: 165 | G39: =E39/F39 -> 1.1442424 | H39: 12 Kg | I39: 0.18 | J39: VP | K39: FM
A40: 4 | B40: 48194000 | C40: Ecowrapp Pouch 9x13 48Gsm | D40: 160 | E40: =D40*I40+D40 -> 188.8 | F40: 110 | G40: =E40/F40 -> 1.7163636 | H40: 12 Kg | I40: 0.18 | J40: VP | K40: LS
A41: 5 | B41: 48194000 | C41: Ecowrapp Pouch 10x11 48Gsm | D41: 160 | E41: =D41*I41+D41 -> 188.8 | F41: 100 | G41: =E41/F41 -> 1.888 | H41: 12 Kg | I41: 0.18 | J41: BN | K41: LS
A42: 6 | B42: 48194000 | C42: Ecowrapp Frankie Pouch 48Gsm (4x1.5x10 V Bot ) | D42: 0.75 | E42: =D42*I42+D42 -> 0.885 | F42: Pcs | G42: - | H42: 3000 | I42: 0.18 | J42: BN | K42: LS
C43: Packnserve Specialized Pouch | D43: Rate/pcs | E43: Rate/Incl | F43: Pc/Kg | G43: Rate/PC | H43: Packing
A44: 1 | B44: 48194000 | C44: Packnserve Parchment Bags With Flap 2Cup 60Gsm | D44: 2.6 | E44: =D44*I44+D44 -> 3.068 | H44: 1000 | I44: 0.18 | J44: VP | K44: LS
A45: 2 | B45: 48194000 | C45: Packnserve Parchment Bags with Flap 4Cup 60Gsm | D45: 3.6 | E45: =D45*I45+D45 -> 4.248 | H45: 1000 | I45: 0.18 | J45: VP | K45: LS
A46: 3 | B46: 48194000 | C46: Packnserve Insulated Bags 6x4x12 Brown 110Gsm | D46: 3.1 | E46: =D46*I46+D46 -> 3.658 | H46: 800 | I46: 0.18 | K46: APO | L46: 6x4x12 SOS SQ Bot Plain Brown MG Kraft (80g) * Kg
A47: 4 | B47: 48194000 | C47: Packnserve Insulated Bags 6x4x12 White 110Gsm | D47: 4 | E47: =D47*I47+D47 -> 4.72 | H47: 800 | I47: 0.18 | K47: APO
A48: Minmum Moq for Specialzed Bags 1Color- 10000 : 4colour 25000
C49: Ecowrap Cut Sheet Plain /Printed | D49: Rate/Pac | E49: Rate/KG Incl | F49: Pc/Pac | G49: Rate/PC | H49: Box | I49: Gst Extra
A50: 1 | B50: 48062000 | C50: 8 x 8 Ecowrap Cut Sheet (250sheet) | D50: 100 | E50: =D50+D50*I50 -> 118 | F50: 250 | G50: =D50/F50 -> 0.4 | H50: 20pac | I50: 0.18 | J50: VP | K50: FM
A51: 2 | B51: 48062000 | C51: 10 x 10 Ecowrap Cut Sheet (250sheet) | D51: 150 | E51: =D51+D51*I51 -> 177 | F51: 250 | G51: =D51/F51 -> 0.6 | H51: 20pac | I51: 0.18 | J51: VP | K51: FM
A52: 3 | B52: 48062000 | C52: 12 x 12 / 10 x 15 Ecowrap Cut Sheet (250sheet) | D52: 225 | E52: =D52+D52*I52 -> 265.5 | F52: 250 | G52: =D52/F52 -> 0.9 | H52: 20pac | I52: 0.18 | J52: VP | K52: FM
A53: 4 | B53: 48062000 | C53: 20 x 30 Ecowrap Cut Sheet (Per pcs) | D53: 3.5 | E53: =D53+D53*I53 -> 4.13 | H53: 500 sheet | I53: 0.18 | K53: APO
A54: 5 | B54: 48062000 | C54: Ecowrap 30mtr | D54: 125 | E54: =D54+D54*I54 -> 147.5 | H54: 30Pc | I54: 0.18 | J54: MM | K54: FM
A55: 6 | B55: 48062000 | C55: Butter Paper Rim (6.5Kg) (20*30 Per Sheet Size) | D55: 1350 | E55: =D55+D55*I55 -> 1593 | F55: 1568 | G55: Pcs | H55: 1Rim | I55: 0.18 | J55: MM | K55: FM
C56: EcoWrap OGR Paper Roll | D56: Rate/Roll | E56: Rate/Roll Incl | F56: Per | G56: Box Packing | H56: Moq | I56: Gst
B57: 48062000 | C57: 12" Ecowrap OGR Paper Plain White 1Kg Roll *Kg | D57: 130 | E57: =D57+D57*I57 -> 153.4 | G57: 20Roll | I57: 0.18 | J57: VP | K57: FM
B58: 48062000 | C58: 12" Ecowrap OGR Paper White 1Kg Roll [Green] | D58: 175 | E58: =D58+D58*I58 -> 206.5 | G58: 20Roll | I58: 0.18 | J58: VP | K58: FM
B59: 48062000 | C59: 12" Ecowrap OGR Paper White 1Kg Roll [Red] | D59: 175 | E59: =D59+D59*I59 -> 206.5 | G59: 20Roll | I59: 0.18 | J59: VP | K59: FM
A60: Wrapp Fresh Economy Series paper and the Gsm may Vary ± 10% - 15% and Subject to availabilty of Paper
A61: Terms & Condition
A62: 1. The above prices F.O.R Mumbai. Freight charges will be extra for outstation deliveries
A63: 2. The GST tax will be applicable as extra on above.
A64: 3. The above prices are subject to change.
A65: 4 Development Charges for Printing in Flexo Shall be 1.60 per sq cm + GST18% per colour
A66: (Vbottom Jobs-2500/- per Colour Approx / SOS Jobs 4000-5000 per Colour )
A67: 5. Printing Order Shall take 10 -15 Days After Final Approval of Sample For Running Size
A68: 6. Any Size Apart from this Mentioned Sizes the Moq may Increase as per Availability And timeline shall be 15-25 Days
D73: Flexo Printing
D74: 1Colour | E74: 2Colour | F74: 3/4Colour | G74: Patch Printing
C75: Vbottom | D75: 10 | E75: 15
C76: Min Order Qutantity | D76: 100kgs | E76: 300Kgs | F76: 300Kgs | G76: 300Kgs
C77: Square Bottom | D77: 20 | E77: 25 | F77: 30 | G77: 35
C78: MOQ | D78: 300Kgs | E78: 500Kgs | F78: 600Kgs | G78: 600
A80: PAGE 12

Sheet Carry Bag With Images 
A1: Neeyog Packaging | K1: Summary Sheet' | R1: Mamtora | S1: MM
A2: OFF:G20, Gr Floor,Sidhpura Ind.Estate,S.V.Road,Gaiwadi Rd,Near Agilus Diagnostic Center,Goregaon(W),Mum- 062 | N2: NL | O2: New Launch | R2: Bhiwandi | S2: BW
A3: Phone : 022-28760709 Mobile 9867607003 Email:neeyog@gmail.com | N3: FM | P3: 1-2 DAY | R3: Shop | S3: SH
A4: www.neeyog.com/www.neeyog.net/www.indiamart.com/neeyogpackaging/www.facebook.com/neeyogpack | N4: LS | O4: Limited Stock | P4: 3-4 DAYS | R4: Vapi | S4: VP
N5: APO | O5: As per Order | P5: 15-20 DAYS | R5: Bansi | S5: BN
A6: Paknserve Paper Bags Price List (Regular) | J6: ='Summary Sheet'!C7 -> Date 16.06.2026
A8: Sr. No. | B8: HSN Code | C8: Description | D8: Excl. Gst Rate | E8: Incl. Gst Rate | F8: Packing | G8: Unit | H8: Case/Pack | I8: Gst Extra | K8: Primary Godown | L8: Movement
C9: Paper Carry Bag (L x W x H) | D9: Plain
A10: 1 | B10: 48194000 | C10: 7.5x5x10 Kraft Carry bag 80Gsm | D10: 3.5 | E10: =D10+D10*I10 -> 4.13 | F10: 50Pc | G10: Pcs | H10: 1000 | I10: 0.18 | XFD10: =SUM(A10:XFC10) -> 48195009
A11: 2 | B11: 48194000 | C11: 9x6x8.5 Kraft Carry Bag 80Gsm | D11: 3.55 | E11: =D11+D11*I11 -> 4.189 | F11: 50Pc | G11: Pcs | H11: 500 | I11: 0.18 | XFD11: =SUM(A11:XFC11) -> 48194510
A12: 3 | B12: 48194000 | C12: 11x6x11 Kraft Carry Bag 80Gsm | D12: 4.3 | E12: =D12+D12*I12 -> 5.074 | F12: 50Pc | G12: Pcs | H12: 500 | I12: 0.18 | XFD12: =SUM(A12:XFC12) -> 48194513
A13: 4 | B13: 48194000 | C13: 11x7x10 Kraft Carry Bag 80Gsm | D13: 4.65 | E13: =D13+D13*I13 -> 5.487 | F13: 50Pc | G13: Pcs | H13: 500 | I13: 0.18 | XFD13: =SUM(A13:XFC13) -> 48194514
A14: Cake/Pizza Bags | D14: Excl. Gst Rate | E14: Incl. Gst Rate | F14: Packing | G14: Unit | H14: Case/Pack | I14: Gst Extra
A15: 1 | B15: 48194000 | C15: Paper Bag 9 x 9 x 9x 120Gsm | D15: 5.85 | E15: =D15+D15*I15 -> 6.903 | F15: 50Pc | G15: Pcs | H15: 300 | I15: 0.18
A16: 2 | B16: 48194000 | C16: Paper Bag 11 x 11.5 x 9 x 120Gsm | D16: 6.5 | E16: =D16+D16*I16 -> 7.67 | F16: 50Pc | G16: Pcs | H16: 300 | I16: 0.18
A17: =A16+1 -> 3 | B17: 48194000 | C17: Paper Bag 13 x 10 x 13 120Gsm | D17: 7.3 | E17: =D17+D17*I17 -> 8.614 | F17: 50Pc | G17: Pcs | H17: 300 | I17: 0.18
A18: =A17+1 -> 4 | B18: 48194000 | C18: 8x4x10 DP Paper Carry Bag | D18: 3.8 | E18: =D18+D18*I18 -> 4.484 | F18: 50Pc | G18: Pcs | H18: 700 | I18: 0.18
A19: =A18+1 -> 5 | B19: 48194000 | C19: 8x4x12 DP Paper Carry Bag | D19: 4 | E19: =D19+D19*I19 -> 4.72 | F19: 50Pc | G19: Pcs | H19: 700 | I19: 0.18
A20: =A19+1 -> 6 | B20: 48194000 | C20: 9x5x12 DP Paper Carry Bag | D20: 4.4 | E20: =D20+D20*I20 -> 5.192 | F20: 50Pc | G20: Pcs | H20: 700 | I20: 0.18
A21: =A20+1 -> 7 | B21: 48194000 | C21: 10x4x14 DP Paper Carry Bag | D21: 4.6 | E21: =D21+D21*I21 -> 5.428 | F21: 50Pc | G21: Pcs | H21: 600 | I21: 0.18
A22: =A21+1 -> 8 | B22: 48194000 | C22: 12x5x16 DP Paper Carry Bag | D22: 4.8 | E22: =D22+D22*I22 -> 5.664 | F22: 50Pc | G22: Pcs | H22: 600 | I22: 0.18
A23: ✨ New Arrival 2025 | Exclusive Diwali, Sweets & Gift Bags Collection 🎁
A24: Sr. No. | B24: HSN Code | C24: Description | D24: Excl. Gst Rate | E24: Incl. Gst Rate | F24: Packing | G24: Unit | H24: Case/Pack | I24: Gst Extra | J24: Reference Photos
A25: Paper Carry Bag (L x W x H)
A26: 1 | B26: 48194000 | C26: 6x4x8 Gift Carry Bag 1 [Design 6] 110gsm *500Pcs | D26: 4.75 | E26: =D26+D26*I26 -> 5.605 | F26: 10 | G26: Pcs | H26: 500 | I26: 0.18
A27: =A26+1 -> 2 | B27: 48194000 | C27: 6x4x8 Gift Carry Bag 1 [Design 4] 110gsm *500Pcs | D27: 4.75 | E27: =D27+D27*I27 -> 5.605 | F27: 10 | G27: Pcs | H27: 500 | I27: 0.18 | K27: ?
A28: =A27+1 -> 3 | B28: 48194000 | C28: 7.5x5x9 Gift Carry Bag 2 [Design 5] 110gsm *500Pcs | D28: 5.2 | E28: =D28+D28*I28 -> 6.136 | F28: 10 | G28: Pcs | H28: 500 | I28: 0.18
A29: =A28+1 -> 4 | B29: 48194000 | C29: 9x7x9 Gift Carry Bag 3 [Design 3] 110gsm *500Pcs | D29: 6 | E29: =D29+D29*I29 -> 7.08 | F29: 10 | G29: Pcs | H29: 500 | I29: 0.18
A30: =A29+1 -> 5 | B30: 48194000 | C30: 10x4x14 Gift Carry Bag 4 [Design 1] 110gsm *500Pcs | D30: 8 | E30: =D30+D30*I30 -> 9.44 | F30: 10 | G30: Pcs | H30: 500 | I30: 0.18
A31: =A30+1 -> 6 | B31: 48194000 | C31: 10x4x14 Gift Carry Bag 4 [Design 2] 110gsm *500Pcs | D31: 8 | E31: =D31+D31*I31 -> 9.44 | F31: 10 | G31: Pcs | H31: 500 | I31: 0.18
A32: =A31+1 -> 7 | B32: 48194000 | C32: 13x7x10 Gift Carry Bag 5 [Design 7] 110gsm *500Pcs | D32: 7 | E32: =D32+D32*I32 -> 8.26 | F32: 10 | G32: Pcs | H32: 500 | I32: 0.18
A33: Paper Bag with Foiling Print
A34: 1 | B34: 48194000 | C34: 5x3x7 Paper Bag with Foiling Print | D34: 14 | E34: =D34+D34*I34 -> 16.52 | F34: 10 | G34: Pcs | H34: 800 | I34: 0.18
A35: =A34+1 -> 2 | B35: 48194000 | C35: 6x3x8 Paper Bag with Foiling Print | D35: 14 | E35: =D35+D35*I35 -> 16.52 | F35: 10 | G35: Pcs | H35: 800 | I35: 0.18
A36: =A35+1 -> 3 | B36: 48194000 | C36: 8x3.5x8 Paper Bag with Foiling Print | D36: 15 | E36: =D36+D36*I36 -> 17.7 | F36: 10 | G36: Pcs | H36: 500 | I36: 0.18
A37: =A36+1 -> 4 | B37: 48194000 | C37: 8x3.5x10 Paper Bag with Foiling Print | D37: 17 | E37: =D37+D37*I37 -> 20.06 | F37: 10 | G37: Pcs | H37: 500 | I37: 0.18
A38: =A37+1 -> 5 | B38: 48194000 | C38: 10x4x12 Paper Bag with Foiling Print | D38: 20 | E38: =D38+D38*I38 -> 23.6 | F38: 10 | G38: Pcs | H38: 500 | I38: 0.18
A39: =A38+1 -> 6 | B39: 48194000 | C39: 10x4x15 Paper Bag with Foiling Print | D39: 24 | E39: =D39+D39*I39 -> 28.32 | F39: 10 | G39: Pcs | H39: 500 | I39: 0.18
A40: =A39+1 -> 7 | B40: 48194000 | C40: 12x4x16 Paper Bag with Foiling Print | D40: 26 | E40: =D40+D40*I40 -> 30.68 | F40: 10 | G40: Pcs | H40: 500 | I40: 0.18
A41: =A40+1 -> 8 | B41: 48194000 | C41: 18x5x13 Paper Bag with Foiling Print | D41: 30 | E41: =D41+D41*I41 -> 35.4 | F41: 10 | G41: Pcs | H41: 500 | I41: 0.18
A42: Sr. No. | B42: HSN Code | C42: Canava Bag | D42: Excl. Gst Rate | E42: Incl. Gst Rate | F42: Packing | G42: Unit | H42: Case/Pack | I42: Gst Extra
A43: 1 | B43: 48194000 | C43: Canava Bag 10.50x4x12 | D43: 13 | E43: =D43+D43*I43 -> 15.34 | G43: Pcs | H43: 150 | I43: 0.18
C48: 7.5x5.75x8.5 Gift Paper Bags * 500Pcs | H48: 7.5X5X8 DK Gift Paper Bags * 500Pcs
C49: 7.5X5X10 DK Gift Paper Bag 100 gsm *pc
C50: 9x9x7 SQ Bot NK Paper Carry Bag * 400pcs

Sheet Carry Bags
A1: Neeyog Packaging | L1: Summary Sheet | O1: NL | P1: New Launch | S1: Mamtora | T1: MM
A2: OFF:20, Gr Floor,Sidhpura Ind.Estate,S.V.Road,Gaiwadi Rd,NearAgilus Diagnostic Center,Goregaon(W),Mum- 062 | O2: FM | Q2: 1-2 DAY | S2: Bhiwandi | T2: BW
A3: Phone : 022-28760709 Mobile 9867607003 Email:neeyog@gmail.com | O3: LS | P3: Limited Stock | Q3: 3-4 DAYS | S3: Shop | T3: SH
A4: www.neeyog.com/www.neeyog.net/www.indiamart.com/neeyogpackaging/www.facebook.com/neeyogpack | O4: APO | P4: As per Order | Q4: 15-20 DAYS | S4: Vapi | T4: VP
S5: Bansi | T5: BN
A6: Packnserve Paper Bags & Pouch Price List | J6: ='Summary Sheet'!C7 -> Date 16.06.2026
A8: Sr. No. | B8: HSN Code | C8: Description | D8: Rate/Pc | E8: Print | I8: Unit | J8: Case/Pack | K8: Gst | L8: Primary Godown | M8: Movement | N8: Tally Name
C9: Paper Carry Bag (L x W x H) | D9: Plain | E9: 1col | F9: 2Col | G9: 4Col | H9: Patch
A10: 1 | B10: 48194000 | C10: 7.5x5x10 Kraft Carry bag 80Gsm | D10: 3.5 | E10: =D10+1 -> 4.5 | F10: =D10+1.25 -> 4.75 | G10: =D10+2 -> 5.5 | H10: =D10+1.25 -> 4.75 | I10: Pcs | J10: 1000 | K10: 0.18 | L10: VAPI | M10: FM | S10: 6x4x12 SQ Bot NK Paper Carry Bag *pcs
A11: 2 | B11: 48194000 | C11: 9x6x8.5 Kraft Carry Bag 80Gsm | D11: 3.55 | E11: =D11+1 -> 4.55 | F11: =D11+1.25 -> 4.8 | G11: =D11+2 -> 5.55 | H11: =D11+1.25 -> 4.8 | I11: Pcs | J11: 500 | K11: 0.18 | L11: VAPI | M11: FM | S11: 7.5X5X10 SQ Bot BR Paper Carry Bag 80gsm * 500pc
A12: 3 | B12: 48194000 | C12: 11x6x11 Kraft Carry Bag 80Gsm | D12: 4.3 | E12: =D12+1 -> 5.3 | F12: =D12+1.25 -> 5.55 | G12: =D12+2 -> 6.3 | H12: =D12+1.25 -> 5.55 | I12: Pcs | J12: 500 | K12: 0.18 | L12: VAPI | M12: FM | N12: 11x11x9 SQ Bot BK Paper Carry Bag *Pcs
A13: 4 | B13: 48194000 | C13: 11x7x10 Kraft Carry Bag 80Gsm | D13: 4.65 | E13: =D13+1 -> 5.65 | F13: =D13+1.25 -> 5.9 | G13: =D13+2 -> 6.65 | H13: =D13+1.25 -> 5.9 | I13: Pcs | J13: 500 | K13: 0.18 | L13: VAPI | M13: FM | N13: 11x7x10 SQ Bot BR Paper Carry Bag 80gsm * 500pcs | S13: 9X5X13 SQ Bot BR Paper Carry Bag 80gsm *500pc
A14: 5 | B14: 48194000 | C14: Dcut 11x6x11 Kraft Carry Bag 80Gsm | D14: 5.8 | E14: =D14+1 -> 6.8 | F14: =D14+1.25 -> 7.05 | G14: =D14+2 -> 7.8 | H14: =D14+1.25 -> 7.05 | I14: Pcs | J14: 500 | K14: 0.18 | M14: As per Order | S14: 10x5x14 SQ Bot BR Paper Carry Bag 80gsm *500pc
C15: Cake/Pizza Bags | I15: Unit | K15: Gst | N15: 9x9x9 SQ Bot NK Paper Carry Bag * Pcs
A16: 1 | B16: 48194000 | C16: Paper Bag 9 x 9 x 9x 120Gsm | D16: ='Carry Bag With Images '!D15 -> 5.85 | E16: =D16+1 -> 6.85 | F16: =D16+1.25 -> 7.1 | G16: =D16+2 -> 7.85 | H16: =D16+1.25 -> 7.1 | I16: Pcs | J16: 500 | K16: 0.18 | L16: VAPI | M16: FM
A17: 2 | B17: 48194000 | C17: Paper Bag 11 x 11.5 x 9 x 120Gsm | D17: ='Carry Bag With Images '!D16 -> 6.5 | E17: =D17+1 -> 7.5 | F17: =D17+1.25 -> 7.75 | G17: =D17+2 -> 8.5 | H17: =D17+1.25 -> 7.75 | I17: Pcs | J17: 500 | K17: 0.18 | L17: VAPI | M17: FM
A18: =A17+1 -> 3 | B18: 48194000 | C18: Paper Bag 13 x 10 x 13 120Gsm | D18: ='Carry Bag With Images '!D17 -> 7.3 | E18: =D18+1 -> 8.3 | F18: =D18+1.25 -> 8.55 | G18: =D18+2 -> 9.3 | H18: =D18+1.25 -> 8.55 | I18: Pcs | J18: 500 | K18: 0.18 | L18: VAPI | M18: SM
A19: =A18+1 -> 4 | B19: 48194000 | C19: 8x4x10 DP Paper Carry Bag | D19: 3.8 | E19: =D19+1 -> 4.8 | F19: =D19+1.25 -> 5.05 | G19: =D19+2 -> 5.8 | H19: =D19+1.25 -> 5.05 | I19: Pcs | J19: 700 | K19: 0.18
A20: =A19+1 -> 5 | B20: 48194000 | C20: 8x4x12 DP Paper Carry Bag | D20: 4 | E20: =D20+1 -> 5 | F20: =D20+1.25 -> 5.25 | G20: =D20+2 -> 6 | H20: =D20+1.25 -> 5.25 | I20: Pcs | J20: 700 | K20: 0.18
A21: =A20+1 -> 6 | B21: 48194000 | C21: 9x5x12 DP Paper Carry Bag | D21: 4.4 | E21: =D21+1 -> 5.4 | F21: =D21+1.25 -> 5.65 | G21: =D21+2 -> 6.4 | H21: =D21+1.25 -> 5.65 | I21: Pcs | J21: 600 | K21: 0.18
A22: =A21+1 -> 7 | B22: 48194000 | C22: 10x4x14 DP Paper Carry Bag | D22: 4.6 | E22: =D22+1 -> 5.6 | F22: =D22+1.25 -> 5.85 | G22: =D22+2 -> 6.6 | H22: =D22+1.25 -> 5.85 | I22: Pcs | J22: 600 | K22: 0.18
A23: =A22+1 -> 8 | B23: 48194000 | C23: 12x5x16 DP Paper Carry Bag | D23: 4.8 | E23: =D23+1 -> 5.8 | F23: =D23+1.25 -> 6.05 | G23: =D23+2 -> 6.8 | H23: =D23+1.25 -> 6.05 | I23: Pcs | J23: 600 | K23: 0.18 | N23: 13x13x10 SQ Bot NK Paper Carry Bag Plain* 200Pcs
A25: Terms & Condition
A26: 1. The above prices F.O.R Mumbai. Freight charges will be extra for outstation deliveries
A27: 2. The GST tax will be applicable as extra on above.
A28: 3. The above prices are subject to change.
A29: 4. 50% Order Booking & 50% Before Delivery.
A30: 5. Lead time required 4 to 5 days after receipt of the Payment.
A31: 6. Printing Moq Shall Be 5000 pcs for 1colour and thereafer 5000 Additional per colour
A34: PAGE 12
C35: 13x8x8 SQ Bot NK Paper Carry Bag Plain* Pcs | G35: 11x11x9 SQ Bot BK Paper Carry Bag *Pcs
C36: 10x8x3 Gift Carry Bag SV *500Pcs | G36: 11X7X11.5 SQ Bot BR Paper Carry Bag 80gsm *pc
C37: 12x10x4 Gift Carry Bag SV *500Pcs | G37: 8X4X10 SQ Bot BR Paper Carry Bag 80gsm *500pc
C38: 13x7x10 Gift Carry Bag 5 [Design 7] 110gsm *500Pcs | G38: 9x6x8.5 SQ Bot NK Paper Carry Bag 80gsm * 500pc
C39: 13x7x9.25 BK 1Kg Sweet Paper Bag (80G) SQ Bott *500Pcs | G39: 9x9x7 SQ Bot NK Paper Carry Bag * 400pcs
C40: 15x4x10 Gift Carry Bag SV *500Pcs
C41: 6.5X3.5X9 DK Gift Paper Bag 170gsm *pc
C42: 6.5x3x8.5 (RED) Gift Paper Bag 100gsm * 500pc
C43: 7.5X3.5X8 Gift Paper Bag (170G) * Pcs
C44: 7.5x5x9 Gift Carry Bag 2 [Design 5] 110gsm *500Pcs
C45: 7X3X8.5 DK Gift Paper Bag 170gsm *pc
C46: 8x4x8 BK 1/4kg Sweet Paper Bag (80G) * Pcs
C47: 8x6x3 Gift Carry Bag SV *500Pcs
C48: 8x8x3.5 Gift Carry Bag SV *500Pcs
C49: 9X3X7 Gift Paper Bag [Black] * 500Pcs
C50: 9x6x10.50 PNS Festive Print Paper Pink/RedBag * pcs
C51: 9X6X8.5 Gift Paper Bag (100G) * 500 Pcs
... C54: 9x7x9 WH Gift Paper Bag 100gsm * 500pc

Sheet Insulated bag 
A1: Neeyog Packaging
A2: OFF:G20, Gr Floor,Sidhpura Ind.Estate,S.V.Road,Gaiwadi Rd,Near Agilus Diagnostic Center,Goregaon(W),Mum- 062
A3: Phone : 022-28760709 Mobile 9867607003 Email:neeyog@gmail.com
A4: www.neeyog.com/www.neeyog.net/www.indiamart.com/neeyogpackaging/www.facebook.com/neeyogpack
A6: Insulated laminated Bags Price List | J6: ='Summary Sheet'!C7 -> Date 16.06.2026
A8: Sr. No. | B8: HSN Code | C8: Description | D8: Excl. Gst Rate | E8: Incl. Gst Rate | F8: Packing | G8: Unit | H8: Case/Pack | I8: Gst Extra
C9: Insulated & Laminated Bag (L x W x H)
A10: 1 | B10: 39232100 | C10: 5.5x5x8 Pink SI NW Laminated Bags | D10: 11 | E10: =D10+D10*I10 -> 12.98 | G10: Pcs | H10: 500 | I10: 0.18
A11: 2 | B11: 39232100 | C11: 8x6x8 SI NW Laminated Bags (Light Blue/Brown/Green/Pink/Yellow) | D11: 13 | E11: =D11+D11*I11 -> 15.34 | G11: Pcs | H11: 400 | I11: 0.18
A12: 3 | B12: 39232100 | C12: 9x6x8 Light Yellow SI NW Laminated Bags | D12: 11 | E12: =D12+D12*I12 -> 12.98 | G12: Pcs | H12: 300 | I12: 0.18
A13: 4 | B13: 39232100 | C13: 8x6x10 Generic Print SI NW Laminated Bags (Brown/Green) | D13: 14 | E13: =D13+D13*I13 -> 16.52 | G13: Pcs | H13: 250 | I13: 0.18
A14: 5 | B14: 39232100 | C14: 8x6x10 SI NW Laminated Bags ( Light Blue/Green/Pink/Yellow) | D14: 14 | E14: =D14+D14*I14 -> 16.52 | G14: Pcs | H14: 350 | I14: 0.18
A15: 6 | B15: 39232100 | C15: 10x8x11 SI NW Laminated Bags (Light Green /Pink) | D15: 17 | E15: =D15+D15*I15 -> 20.06 | G15: Pcs | H15: 250 | I15: 0.18
A16: 7 | B16: 39232100 | C16: 10x7x13 SI NW Laminated Bags (Black/Red/White/Yellow ) | D16: 16 | E16: =D16+D16*I16 -> 18.88 | G16: Pcs | H16: 250 | I16: 0.18

Sheet Areca
A1: Neeyog Packaging | H1: summary sheet | J1: NL | K1: New Launch | N1: Mamtora | O1: MM
A2: OFF:20, Gr Floor,Sidhpura Ind.Estate,S.V.Road,Gaiwadi Rd,NearAgilus Diagnostic Center,Goregaon(W),Mum- 062 | J2: FM | L2: 1-2 DAY | N2: Bhiwandi | O2: BW
A3: Phone : 022-28760709 Mobile 9867607003 Email:neeyog@gmail.com | J3: LS | K3: Limited Stock | L3: 3-4 DAYS | N3: Shop | O3: SH
A4: www.neeyog.com/www.indiamart.com/neeyogpackaging/www.facebook.com/neeyogpack | J4: APO | K4: As per Order | L4: 15-20 DAYS | N4: Vapi | O4: VP
N5: Bansi | O5: BN
A6: Wholesale Arecaleaf Products Price List | F6: ='Summary Sheet'!C7 -> Date 16.06.2026
A7: SR No | B7: Description | C7: Rate Excl Gst | D7: Rate Incl Gst | E7: Per Pcs | F7: Std Pack | G7: GST Rate | H7: Primary Godown | I7: Movement | J7: Tally Name
B8: Arecaleaf Economical Products (HSN Code 46021990) | K8: Arvi Ent
A9: 1 | B9: 4" SQ Round Areca Domestic Bowl | C9: 3 | D9: =C9+C9*G9 -> 3.15 | E9: Per Pcs | F9: 1000 | G9: 0.05 | H9: Bansi | I9: SM | K9: 4" AE Rd Arecaleaf Bowl * Pcs
A10: =A9+1 -> 2 | B10: 4.5 " Round Areca Domestic Bowl | C10: 3 | D10: =C10+C10*G10 -> 3.15 | E10: Per Pcs | F10: 1000 | G10: 0.05 | I10: Not in Tally | K10: 4.5" AE Rd Arecaleaf Bowl * 2500pcs
A11: =A10+1 -> 3 | B11: 5 " Round Areca Domestic Bowl | C11: 4 | D11: =C11+C11*G11 -> 4.2 | E11: Per Pcs | F11: 1000 | G11: 0.05 | I11: Not in Tally
A12: =A11+1 -> 4 | B12: 6 " SQ Round Areca Domestic Plate | C12: 4 | D12: =C12+C12*G12 -> 4.2 | E12: Per Pcs | F12: 1000 | G12: 0.05 | I12: FM | K12: 6" AE SQ Arecaleaf Plate * Pcs
A13: =A12+1 -> 5 | B13: 7" SQ Areca Domestic Plate | C13: 5 | D13: =C13+C13*G13 -> 5.25 | E13: Per Pcs | F13: 1000 | G13: 0.05 | I13: NM | K13: 7" AE SQ Arecaleaf Plate * pcs
A14: =A13+1 -> 6 | B14: 8 " Round & SQ Areca Domestic Plate | C14: 6 | D14: =C14+C14*G14 -> 6.3 | E14: Per Pcs | F14: 1000 | G14: 0.05 | I14: NM
A15: =A14+1 -> 7 | B15: 9" SQ & Round Areca Domestic Plate | C15: 7 | D15: =C15+C15*G15 -> 7.35 | E15: Per Pcs | F15: 1000 | G15: 0.05 | I15: NM
A16: =A15+1 -> 8 | B16: 10 " Round Areca Domestic Plate | C16: 8 | D16: =C16+C16*G16 -> 8.4 | E16: Per Pcs | F16: 1000 | G16: 0.05 | I16: NM
A17: =A16+1 -> 9 | B17: 10" SQ Areca Domestic Plate | C17: 8 | D17: =C17+C17*G17 -> 8.4 | E17: Per Pcs | F17: 1000 | G17: 0.05 | I17: SM | K17: 10" AE SQ Arecaleaf Plate * 500pcs
A18: =A17+1 -> 10 | B18: 10 " 3CP Areca Domestic Plate | C18: 7 | D18: =C18+C18*G18 -> 7.35 | E18: Per Pcs | F18: 1000 | G18: 0.05 | I18: NM
A19: =A18+1 -> 11 | B19: 12 " Round Areca Domestic Plate | C19: 10 | D19: =C19+C19*G19 -> 10.5 | E19: Per Pcs | F19: 1000 | G19: 0.05 | I19: FM | K19: 12" AE Rd Arecaleaf Plate * pcs
A20: =A19+1 -> 12 | B20: 12 " 4CP Round Areca Domestic Plate | C20: 10 | D20: =C20+C20*G20 -> 10.5 | E20: Per Pcs | F20: 1000 | G20: 0.05 | I20: NM | K20: 12" 4CP Rd Arecaleaf Plate * 300pcs
A21: PINEWOOD PRODUCTS (HSN Code 44199090)
A22: 1 | B22: 3" Pinewood Boat | C22: 2 | D22: =C22+C22*G22 -> 2.1 | E22: Per Pcs | F22: - | G22: 0.05 | H22: Bhiwandi | I22: NM | K22: 3" Pinewood Cone *20000Pcs
A23: =A22+1 -> 2 | B23: 4.0" Pinewood Boat | C23: 2.55 | D23: =C23+C23*G23 -> 2.6775 | E23: Per Pcs | F23: 4000 | G23: 0.05 | I23: Not in Tally | K23: 4" Pinewood Boat * 6000pcs
A24: =A23+1 -> 3 | B24: 5.0" Pinewood Boat | C24: 3.4 | D24: =C24+C24*G24 -> 3.57 | E24: Per Pcs | F24: 5000 | G24: 0.05 | I24: Not in Tally | K24: 5" Pinewood Boat * 4000pcs
A25: =A24+1 -> 4 | B25: 3" Pinewood Cone(85mm) | C25: 1.9 | D25: =C25+C25*G25 -> 1.995 | E25: Per Pcs | F25: 5000 | G25: 0.05 | I25: SM | K25: 5" Pinewood Cone * 6000Pcs
A26: =A25+1 -> 5 | B26: 5" Pinewood Cone | C26: 2.75 | D26: =C26+C26*G26 -> 2.8875 | E26: Per Pcs | F26: 8000 | G26: 0.05 | I26: NM | K26: 6" Pinewood Boat * 2000PCS
A27: =A26+1 -> 6 | B27: 6" Pinewood Cone | C27: 3.4 | D27: =C27+C27*G27 -> 3.57 | E27: Per Pcs | F27: 5000 | G27: 0.05 | I27: SM | K27: 6" Pinewood Cone * 5000pcs
A28: PAGE 15

Sheet Bio Cutlery
A1: Neeyog Packaging | I1: summary sheet | Q1: Mamtora | R1: MM
A2: OFF:20, Gr Floor,Sidhpura Ind.Estate,S.V.Road,Gaiwadi Rd,Near Agilus Diagnostic Center,Goregaon(W),Mum- 062 | M2: NL | N2: New Launch | Q2: Bhiwandi | R2: BW
A3: Phone : 022-28760709 Mobile 9867607003 Email:neeyog@gmail.com | M3: FM | O3: 1-2 DAY | Q3: Shop | R3: SH
A4: www.neeyog.com/www.indiamart.com/neeyogpackaging/www.facebook.com/neeyogpack | M4: LS | N4: Limited Stock | O4: 3-4 DAYS | Q4: Vapi | R4: VP
M5: APO | N5: As per Order | O5: 15-20 DAYS | Q5: Bansi | R5: BN
A6: Wholesale Biodegradable Cutlery, Stirrer, Stick & Straw
A7: Price List | G7: ='Summary Sheet'!C7 -> Date 16.06.2026
A8: SR No | B8: HSN CODE | C8: Description | D8: Rate Excl GST | E8: Rate Incl GST | F8: Unit | G8: Std Pack | H8: GST | I8: Primary Godown | J8: Movement | K8: Tally name
C9: Paper Straw
A10: STMA6X8 | B10: 48070010 | C10: Paper Straw 6 MM x197mm x 300gsm | D10: 0.3 | E10: =D10+D10*H10 -> 0.354 | F10: Pcs | G10: 10000 | H10: 0.18 | I10: MM | J10: FM
A11: STMA8X8 | B11: 48070010 | C11: Paper Straw 8 MM x 197mm x 300gsm | D11: 0.4 | E11: =D11+D11*H11 -> 0.472 | F11: Pcs | G11: 10000 | H11: 0.18 | I11: MM | J11: FM
A12: STAI12X8 | B12: 48070010 | C12: Paper Straw 10 MM x 197mm x 300gsm | D12: 0.6 | E12: =D12+D12*H12 -> 0.708 | F12: Pcs | G12: 6000 | H12: 0.18 | I12: MM | J12: FM
A13: STAI10X10 | B13: 48070010 | C13: Paper Straw 10 MM x 250mm x 300gsm | D13: 0.85 | E13: =D13+D13*H13 -> 1.003 | F13: Pcs | G13: 4500 | H13: 0.18 | J13: not in tally
A14: STAI12X8 | B14: 48070010 | C14: Paper Straw 12 MM x 197mm x 300gsm | D14: 1.1 | E14: =D14+D14*H14 -> 1.298 | F14: Pcs | G14: 5000 | H14: 0.18 | I14: MM | J14: FM
A15: 8 Inch | B15: 48070010 | C15: Paper Straw 6mm Prepack | D15: 0.45 | E15: =D15+D15*H15 -> 0.531 | F15: Pcs | G15: 5000 | H15: 0.18 | J15: APO
A16: 8 Inch | B16: 48229090 | C16: Paper Straw 6 MM Printed Black/Spiral | D16: 0.42 | E16: =D16+D16*H16 -> 0.4956 | F16: Pcs | G16: 5000 | H16: 0.18 | J16: APO
A17: 8 Inch | B17: 48229090 | C17: Paper Straw 8 MM Printed Black/Spiral | D17: 0.52 | E17: =D17+D17*H17 -> 0.6136 | F17: Pcs | G17: 5000 | H17: 0.18 | J17: APO
C18: Compostable PLA Straw UnWrapped
A19: 1 | B19: 48229090 | C19: Compostable Straw PLA 6 X 210MM | D19: 0.27 | E19: =D19+D19*H19 -> 0.3186 | F19: Per Pcs | G19: 8000 | H19: 0.18 | I19: VP | J19: FM
A20: 2 | B20: 48229090 | C20: Compostable Straw PLA 8 X 210MM | D20: 0.5 | E20: =D20+D20*H20 -> 0.59 | F20: Per Pcs | G20: 5000 | H20: 0.18 | I20: VP | J20: FM
A21: 3 | B21: 48229090 | C21: Compostable Straw PLA 8 X 230MM | D21: 0.56 | E21: =D21+D21*H21 -> 0.6608 | F21: Per Pcs | G21: 4000 | H21: 0.18 | I21: VP | J21: FM
A22: 4 | B22: 48229090 | C22: Compostable Straw PLA 10 X 210MM | D22: 0.64 | E22: =D22+D22*H22 -> 0.7552 | F22: Per Pcs | G22: 3000 | H22: 0.18 | J22: APO
A23: 5 | B23: 48229090 | C23: Compostable Straw PLA10 X 230MM | D23: 0.78 | E23: =D23+D23*H23 -> 0.9204 | F23: Per Pcs | G23: 2700 | H23: 0.18 | J23: APO
A24: 6 | B24: 48229090 | C24: Compostable Straw PLA12X 230MM | D24: 0.88 | E24: =D24+D24*H24 -> 1.0384 | F24: Per Pcs | G24: 2100 | H24: 0.18 | J24: APO
C25: Compostable PLA Straw Wrapped
A26: 1 | B26: 39206999 | C26: Compostable Straw PLA 6 X 210MM | D26: 0.38 | E26: =D26+D26*H26 -> 0.4484 | F26: Per Pcs | G26: 6000 | H26: 0.18 | J26: APO
A27: 2 | B27: 39206999 | C27: Compostable Straw PLA 8 X 210MM | D27: 0.62 | E27: =D27+D27*H27 -> 0.7316 | F27: Per Pcs | G27: 3600 | H27: 0.18 | J27: APO
A28: 3 | B28: 39206999 | C28: Compostable Straw PLA 8 X 230MM | D28: 0.7 | E28: =D28+D28*H28 -> 0.826 | F28: Per Pcs | G28: 3000 | H28: 0.18 | J28: APO
A29: 4 | B29: 39206999 | C29: Compostable Straw PLA 10 X 210MM | D29: 0.82 | E29: =D29+D29*H29 -> 0.9676 | F29: Per Pcs | G29: 2400 | H29: 0.18 | J29: APO
A30: 5 | B30: 39206999 | C30: Compostable Straw PLA10 X 230MM | D30: 1 | E30: =D30+D30*H30 -> 1.18 | F30: Per Pcs | G30: 2000 | H30: 0.18 | J30: APO
A31: 6 | B31: 39206999 | C31: Compostable Straw PLA12X 230MM | D31: 1.1 | E31: =D31+D31*H31 -> 1.298 | F31: Per Pcs | G31: 1200 | H31: 0.18 | J31: APO
C32: Wooden Products | D32: BASIC | E32: INCL. GST | F32: Per Pcs | G32: PACKING | H32: GST
A33: 160mm | B33: 44219090 | C33: 160MM Wooden Spoon/Fork | D33: 0.6 | E33: =D33+D33*H33 -> 0.63 | F33: Per Pcs | G33: 10000 | H33: 0.05 | I33: MM | J33: FM
A34: 160mm | B34: 44219090 | C34: Wooden Knife 16cms | D34: 0.6 | E34: =D34+D34*H34 -> 0.63 | F34: Per Pcs | G34: 10000 | H34: 0.05 | I34: MM | J34: FM
A35: 160mm | B35: 44219090 | C35: Wooden Spork 16cms | D35: 0.62 | E35: =D35+D35*H35 -> 0.651 | F35: Per Pcs | G35: 10000 | H35: 0.05 | I35: BN | J35: FM
A36: 140mm | B36: 44219090 | C36: Wooden Spoon/Fork/14Cms | D36: 0.45 | E36: =D36+D36*H36 -> 0.4725 | F36: Per Pcs | G36: 10000 | H36: 0.05 | I36: BN | J36: FM
A37: 110mm | B37: 44219090 | C37: Wooden Spoon 12cms / 95mm Fawada | D37: 0.45 | E37: =D37+D37*H37 -> 0.4725 | F37: Per Pcs | G37: 10000 | H37: 0.05 | I37: BN | J37: FM
A38: 95mm | B38: 44219090 | C38: 95MM Favda Wooden Spoon * 10000pcs | D38: 0.45 | E38: =D38+D38*H38 -> 0.4725 | F38: Per Pcs | G38: 10000 | H38: 0.05 | I38: BN | J38: FM
A39: 75mm | B39: 44219090 | C39: 75MM Wooden Tasting Spoon * 20000pc, Icecream | D39: 0.2 | E39: =D39+D39*H39 -> 0.21 | F39: Per Pcs | G39: 20000 | H39: 0.05 | I39: SH | J39: FM
A40: 90mm | B40: 44219090 | C40: Wooden Fruit Fork-80 | D40: 15 | E40: =D40+D40*H40 -> 15.75 | F40: Pac | G40: 300pac | H40: 0.05 | I40: BN | J40: FM
A41: 64mm | B41: 44219090 | C41: Toothpick - Blue Sea | D41: 90 | E41: =D41+D41*H41 -> 94.5 | F41: Box | G41: 60 Box | H41: 0.05 | I41: BN | J41: FM
A42: 65mm | B42: 44219090 | C42: Fancy Toothpick | D42: 16 | E42: =D42+D42*H42 -> 16.8 | F42: Pac | G42: 100 Pac | H42: 0.05 | I42: BN | J42: FM
A43: 200mm | B43: 44219090 | C43: Wooden Chopstick 8" | D43: 2 | E43: =D43+D43*H43 -> 2.1 | F43: Pcs | G43: 5000 | H43: 0.05 | I43: BN | J43: FM
A44: 225mm | B44: 44219090 | C44: Pre Pack Chopstick 9" | D44: 2.5 | E44: =D44+D44*H44 -> 2.625 | F44: Pcs | G44: 5000 | H44: 0.05 | I44: BN | J44: FM
A45: 110mm | B45: 44219090 | C45: Ice Cream Stick | D45: 0.25 | E45: =D45+D45*H45 -> 0.2625 | F45: Pcs | G45: 10000Pcs | H45: 0.05 | I45: BN | J45: FM
A46: 100mm | B46: 44219090 | C46: 4" Stick -100Pcs | D46: 8.501 | E46: =D46+D46*H46 -> 8.92605 | F46: Pac | G46: 300Pac | H46: 0.05 | I46: BN | J46: FM
A47: 150mm | B47: 44219090 | C47: 6" Stick - 100Pcs | D47: 10.4995 | E47: =D47+D47*H47 -> 11.024475 | F47: Pac | G47: 250Pac | H47: 0.05 | I47: BN | J47: FM
A48: 200mm | B48: 44219090 | C48: 8" Stick -100Pcs | D48: 13.5015 | E48: =D48+D48*H48 -> 14.176575 | F48: Pac | G48: 150Pac | H48: 0.05 | I48: BN | J48: FM
A49: 255mm | B49: 44219090 | C49: 10" Stick - 100Pcs | D49: 17.997 | E49: =D49+D49*H49 -> 18.89685 | F49: Pac | G49: 100Pac | H49: 0.05 | I49: BN | J49: FM
A50: 300mm | B50: 44219090 | C50: 12" Stick - 100Pcs | D50: 20.999 | E50: =D50+D50*H50 -> 22.04895 | F50: Pac | G50: 100Pac | H50: 0.05 | I50: BW | J50: FM
A51: 100mm | B51: 44219090 | C51: Tepu-Kushi 4" (Knot stick) - 100Pcs | D51: 80 | E51: =D51+D51*H51 -> 84 | F51: 100 | G51: 100Pac | H51: 0.05 | I51: BW | J51: FM
A52: 150mm | B52: 44219090 | C52: Tepu-Kushi 6" (Knot stick) - 100Pcs | D52: 95 | E52: =D52+D52*H52 -> 99.75 | F52: 100 | G52: 100Pac | H52: 0.05 | I52: BW | J52: FM
A53: 90mm | B53: 44219090 | C53: 4" Wooden Peddle/Gun Stick 120mm * 100Pc/Pac | D53: 45 | E53: =D53+D53*H53 -> 47.25 | F53: 100 | G53: 100Pac | H53: 0.05 | I53: BW | J53: FM
A54: 120mm | B54: 44219090 | C54: Gun Stick/Paddle Stick 5" | D54: 55 | E54: =D54+D54*H54 -> 57.75 | F54: 100 | G54: 100Pac | H54: 0.05 | I54: BW | J54: FM
A55: 110mm | B55: 44219090 | C55: Wooden stirrer 4.5" | D55: 11 | E55: =D55+D55*H55 -> 11.55 | F55: 500 | G55: 50000 | H55: 0.05 | I55: BW | J55: FM
A56: 140mm | B56: 44219090 | C56: Wooden stirrer 5.5" | D56: 12.5 | E56: =D56+D56*H56 -> 13.125 | F56: 500 | G56: 50000 | H56: 0.05 | I56: BW | J56: FM
B57: 44219090 | C57: Wooden stirrer 8 Drink Stirrer" | D57: 0.7 | E57: =D57+D57*H57 -> 0.735 | F57: 50 | G57: 10000 | H57: 0.05 | I57: BW | J57: FM
C58: Biodegradable Cutlery
A59: 150mm | B59: 39249090 | C59: Bio-Spoon/Fork/Sporks(200Pcs)Black/White | D59: 1 | E59: =D59+D59*H59 -> 1.18 | F59: Per Pcs | G59: 8000 | H59: 0.18 | I59: MM | J59: FM | K59: AP Bio Spork [Cream] * 2500pcs
A60: 140mm | B60: 39249090 | C60: AP Bio Spoon Cream * 5000pcs | D60: 0.7 | E60: =D60+D60*H60 -> 0.826 | F60: Per Pcs | G60: 5000 | H60: 0.18 | I60: VP | J60: FM
B61: 39241090 | C61: PS Plastic Spoon (SN) | D61: 0.8 | E61: =D61+D61*H61 -> 0.944 | F61: Per Pcs | G61: 2000 | H61: 0.18 | I61: BN | J61: FM
B62: 39241090 | C62: Soup Spoon [Clear] * 14000pcs | D62: 0.85 | E62: =D62+D62*H62 -> 1.003 | F62: Per Pcs | G62: 14000 | H62: 0.18 | I62: BN | J62: FM
B63: 39241090 | C63: PS Plastic spoon [PA] [Jagmag] * 20000Pcs | D63: 0.55 | E63: =D63+D63*H63 -> 0.649 | F63: Per Pcs | G63: 20000 | H63: 0.18 | I63: BN | J63: FM
B64: 39206999 | C64: Compostable Cutlery SPORK | D64: 1.5 | E64: =D64+D64*H64 -> 1.77 | F64: Per Pcs | G64: 5000 | H64: 0.18 | I64: VP | J64: FM
B65: 39249090 | C65: Biodegradable Spoon /Spork (White/Black) | D65: 1.1 | E65: =D65+D65*H65 -> 1.298 | F65: Per Pcs | G65: 8000 | H65: 0.18 | I65: BN | J65: FM | O65: Biodegradable Spoon Brown *5000 pc
A66: 160mm | B66: 48236900 | C66: 160MM PAPER SPOON White (PPT)* 5000pcs | D66: 1 | E66: =D66+D66*H66 -> 1.18 | F66: Per Pcs | G66: 5000 | H66: 0.18 | I66: BN | J66: FM
A67: 160mm | B67: 48236900 | C67: 160MM PAPER SPOON White (PPT)* 5000pcs | D67: 1 | E67: =D67+D67*H67 -> 1.18 | F67: Per Pcs | G67: 5000 | H67: 0.18 | I67: BN | J67: FM
C68: Corn Starch Cutlery
A69: 1 | C69: 6" Spoon | D69: 1.3 | E69: =D69+D69*H69 -> 1.534 | F69: Per Pcs | G69: 10000 | H69: 0.18 | J69: APO
A70: 2 | C70: 5.5" Spoon | D70: 1.1 | E70: =D70+D70*H70 -> 1.298 | F70: Per Pcs | G70: 10000 | H70: 0.18 | J70: APO
C71: Cutlery Set
A72: 1 | B72: 44219090 | C72: Set no 1 (16Cm Spoon +Tissue) | D72: 1.9 | E72: =D72+D72*H72 -> 2.242 | F72: Per Pcs | G72: 3000 | H72: 0.18 | J72: APO
A73: =A72+1 -> 2 | B73: 44219090 | C73: Set no 2 (16Cm Spoon+Fork+Tissue) | D73: 2.7 | E73: =D73+D73*H73 -> 3.186 | F73: Per Pcs | G73: 2000 | H73: 0.18 | I73: BN | J73: FM
A74: =A73+1 -> 3 | B74: 44219090 | C74: Set no 3 (14Cm Spoon+Tissue) | D74: 1.85 | E74: =D74+D74*H74 -> 2.183 | F74: Per Pcs | G74: 3000 | H74: 0.18 | J74: APO
A75: =A74+1 -> 4 | B75: 44219090 | C75: Set no 2 (16Cm Spoon+Fork+Knife) | D75: 3.1 | E75: =D75+D75*H75 -> 3.658 | F75: Per Pcs | H75: 0.18 | J75: not in tally
A76: =A75+1 -> 5 | B76: 44219090 | C76: Set no.4 (14Cm Spoon+Fork+Tissue) | D76: 2.5 | E76: =D76+D76*H76 -> 2.95 | F76: Per Pcs | G76: 2000 | H76: 0.18 | J76: APO
A79: PAGE 14
C81: 100mm Wooden Round Shape Spoon * 10000Pcs
C82: 110MM Wooden Spoon (Gold) * 10000Pcs
C84: BW 95MM PAPER ICE CREAM SPOON * 5000pcs
C85: FP Folding spoon [Clear] * 3000Pcs
C86: FP Folding spoon [Clear] * 4000Pcs
C87: PP PLASTIC SPOON [AP] * 5000Pcs
C88: Drink Stirrer PL *pcs
C89: PS Baby Parlour spoon [DP] [Black] * 10000Pcs
C90: PS Baby Parlour spoon [DP] [Black] * 5000Pcs
C91: PS Parlour spoon [DP] [Clear] * 10000Pcs
C92: PS PLASTIC SPOON [DP] [Black] * 2000Pcs
C93: PS PLASTIC SPOON [DP] [Clear] * 2000Pcs
... C102: PS PLASTIC SPOON [DP] [White] * 2500Pcs

Sheet Tissue Paper
A1: Neeyog Packaging | K1: summary sheet | S1: Mamtora | T1: MM
A2: OFF:20, Gr Floor,Sidhpura Ind.Estate,S.V.Road,Gaiwadi Rd,Near Agilus Diagnostic Center,Goregaon(W),Mum- 062 | O2: NL | P2: New Launch | S2: Bhiwandi | T2: BW
A3: Phone : 022-28760709 Mobile 9867607003 Email:neeyog@gmail.com | O3: FM | Q3: 1-2 DAY | S3: Shop | T3: SH
A4: www.neeyog.com/www.indiamart.com/neeyogpackaging/www.facebook.com/neeyogpack | O4: LS | P4: Limited Stock | Q4: 3-4 DAYS | S4: Vapi | T4: VP
O5: APO | P5: As per Order | Q5: 15-20 DAYS | S5: Bansi | T5: BN
A6: Wholesale Tissue Products Price List | G6: ='Summary Sheet'!C7 -> Date 16.06.2026
A7: SR No | B7: HSN Code | C7: Description | D7: Rate Excl GST/Pack | E7: Rate Incl GST | F7: Pac/Pcs | G7: Std Pack | H7: MOQ For Printing | I7: Unit | J7: GST
C8: Tissue, Toilet , Kitchen , JRT & HRT Rolls | K8: Primary Godown | L8: Movement | M8: Tally name
A9: 1 | B9: 48183000 | C9: 9" X 9" 1 Ply Chapati Tissue - 600Pcs (100*6) | D9: 120 | E9: =D9*J9+D9 -> 141.6 | F9: 600 | G9: 21 | I9: Pac | J9: 0.18
A10: =A9+1 -> 2 | B10: 48183000 | C10: 9" X 9" x15Gsm Soft Tissue Plain | D10: 17 | E10: =D10*J10+D10 -> 20.06 | F10: 100 | G10: 60 | I10: Pac | J10: 0.18 | K10: MM | L10: FM
A11: =A10+1 -> 3 | B11: 48183000 | C11: 9" X 9" x15Gsm Soft Tissue (1Col) | D11: 18 | E11: =D11*J11+D11 -> 21.24 | F11: 100 | G11: 500 | I11: Pac | J11: 0.18 | K11: MM | L11: FM
A12: =A11+1 -> 4 | B12: 48183000 | C12: 11" X 11" 1 Ply Hotel Tissue - 80 Pulls (10*1) | D12: 130 | E12: =D12*J12+D12 -> 153.4 | F12: 600 | G12: 12 | I12: Pac | J12: 0.18 | L12: NOT IN TALLY
A13: =A12+1 -> 5 | B13: 48183000 | C13: 11" X 12" x15Gsm Soft Tissue Plain | D13: 21 | E13: =D13*J13+D13 -> 24.78 | F13: 100 | G13: 35 | I13: Pac | J13: 0.18 | K13: MM | L13: FM
A14: =A13+1 -> 6 | B14: 48183000 | C14: 11" X 12" x17Gsm Soft Tissue (1Col) | D14: 23 | E14: =D14*J14+D14 -> 27.14 | F14: 100 | G14: 350 | I14: Pac | J14: 0.18 | K14: MM | L14: FM
A15: =A14+1 -> 7 | B15: 48183000 | C15: 11*12 Unbleached Brown Tissue Paper-37 Gsm | D15: 42 | E15: =D15*J15+D15 -> 49.56 | F15: 100 | G15: 25 | I15: Pac | J15: 0.18 | K15: BW | L15: FM
A16: =A15+1 -> 8 | B16: 48183000 | C16: 9" X 9" 2 Ply Soft Tissue 23cm x 23cm | D16: 31 | E16: =D16*J16+D16 -> 36.58 | F16: 100 | G16: 50 | I16: Pac | J16: 0.18 | K16: MM | L16: FM
A17: =A16+1 -> 9 | B17: 48183000 | C17: 9" X 9"2 Ply Soft Tissue (1col) | D17: 34 | E17: =D17*J17+D17 -> 40.12 | F17: 100 | G17: 500 | I17: Pac | J17: 0.18 | K17: MM | L17: FM
A18: =A17+1 -> 10 | B18: 48183000 | C18: 12" X 12" 2 Ply tissue Paper - 100Pcs | D18: 49 | E18: =D18*J18+D18 -> 57.82 | F18: 100 | G18: 42 | I18: Pac | J18: 0.18 | K18: MM | L18: FM
A19: =A18+1 -> 11 | B19: 48183000 | C19: 12" X 12" 2 Ply Tissue Paper 1col | D19: 51 | E19: =D19*J19+D19 -> 60.18 | F19: 100 | G19: 250 | I19: Pac | J19: 0.18 | K19: BW | L19: FM
A20: =A19+1 -> 12 | B20: 48183000 | C20: 12x12 TB Brown Tissue Paper Printed - 35gsm | D20: 0.46 | E20: =D20*J20+D20 -> 0.5428 | F20: Pcs | G20: 30Pac | H20: 25000 | I20: Pcs | J20: 0.18 | K20: BW | L20: FM
A21: =A20+1 -> 13 | B21: 48183000 | C21: 13" X 13" 2 Ply tissue Paper | D21: 56 | E21: =D21*J21+D21 -> 66.08 | F21: 100 | G21: 42 | I21: Pac | J21: 0.18 | K21: BW | L21: FM
A22: =A21+1 -> 14 | B22: 48183000 | C22: 13" X 13" 2 Ply Tissue (1Col) | D22: 58 | E22: =D22*J22+D22 -> 68.44 | F22: 100 | G22: 250 | I22: Pac | J22: 0.18 | K22: BW | L22: FM
A23: =A22+1 -> 15 | B23: 48183000 | C23: 13x13 Nested 2 Ply | D23: 1.35 | E23: =D23*J23+D23 -> 1.593 | F23: Pcs | G23: 2000 | I23: Pcs | J23: 0.18
A24: =A23+1 -> 16 | B24: 48183000 | C24: 16" X 16" 2 Ply Tissue Paper Plain 44Gsm Max | D24: 55 | E24: =D24*J24+D24 -> 64.9 | F24: 50 | G24: 42 | H24: 20000 | I24: Pac | J24: 0.18 | K24: MM | L24: FM
A25: =A24+1 -> 17 | B25: 48183000 | C25: 16" X 16" 2 Ply Tissue Paper Printed 44Gsm Max | D25: 65 | E25: =D25*J25+D25 -> 76.7 | F25: 50 | G25: 42 | I25: Pac | J25: 0.18 | K25: MM | L25: FM
A26: =A25+1 -> 18 | B26: 48183000 | C26: 16" X 16" 1 Ply Tissue 40Gsm(1col) T/B White -Tad | D26: 1 | E26: =D26*J26+D26 -> 1.18 | F26: Pcs | G26: 2000 | H26: 20000 | I26: Pcs | J26: 0.18 | K26: BW | L26: FM
A27: =A26+1 -> 19 | B27: 48183000 | C27: 16" X 16" 3 Ply Tissue | D27: 1.65 | E27: =D27*J27+D27 -> 1.947 | F27: Pcs | G27: 5000 | I27: Pcs | J27: 0.18 | K27: MM | L27: LS
A28: =A27+1 -> 20 | B28: 48183000 | C28: 13" X 13" Nested tissue Paper | D28: 1.35 | E28: =D28*J28+D28 -> 1.593 | F28: Pcs | G28: 2000 | I28: Pcs | J28: 0.18 | L28: APO
A29: =A28+1 -> 21 | B29: 48183000 | C29: 16" X 16" Nested tissue Paper Cleen | D29: 1.6 | E29: =D29*J29+D29 -> 1.888 | F29: Pcs | G29: 2400 | I29: Pcs | J29: 0.18 | K29: BW | L29: FM
A30: =A29+1 -> 22 | B30: 48183000 | C30: 16x16 Nested 3Ply Tissue Paper - 60gsm | D30: 2.4 | E30: =D30*J30+D30 -> 2.832 | F30: Pcs | G30: 1400 | H30: 20000 | I30: Pcs | J30: 0.18
A31: =A30+1 -> 23 | B31: 48183000 | C31: 16x16 4Ply Napkin - 70gsm | D31: 2.4 | E31: =D31*J31+D31 -> 2.832 | F31: Pcs | G31: 1400 | H31: 20000 | I31: Pcs | J31: 0.18
A32: =A31+1 -> 24 | B32: 48183000 | C32: 12x16 Airlad Tissue - 50gsm | D32: 1.7 | E32: =D32*J32+D32 -> 2.006 | F32: 1750 | G32: 20000 | I32: Pcs | J32: 0.18
A33: =A32+1 -> 25 | B33: 48183000 | C33: 16" X 16" Airlaid Tissue white 60Gsm Heavy | D33: 3.25 | E33: =D33*J33+D33 -> 3.835 | F33: Pcs | G33: 800 | I33: Pcs | J33: 0.18 | K33: MM | L33: LS
A34: =A33+1 -> 26 | B34: 48183000 | C34: 16" X 16" Airlaid Tissue white 50Gsm MTP | D34: 2.85 | E34: =D34*J34+D34 -> 3.363 | F34: Pcs | G34: 800 | I34: Pcs | J34: 0.18 | K34: BW | L34: FM
A35: =A34+1 -> 27 | B35: 48183000 | C35: 16" X 16" Airlaid Tissue white 45Gsm JPP | D35: 2.6 | E35: =D35*J35+D35 -> 3.068 | F35: Pcs | G35: 800 | I35: Pcs | J35: 0.18 | K35: MM | L35: FM
A36: =A35+1 -> 28 | B36: 48183000 | C36: 16" X 16" Airlaid Tissue 50Gsm Colour MTP | D36: 2.85 | E36: =D36*J36+D36 -> 3.363 | F36: Pcs | G36: 800 | I36: Pcs | J36: 0.18
A37: =A36+1 -> 29 | B37: 48183000 | C37: 16" X 16" Airlaid Tissue 45Gsm Colour JPP | D37: 2.6 | E37: =D37*J37+D37 -> 3.068 | F37: Pcs | G37: 800 | I37: Pcs | J37: 0.18
A38: =A37+1 -> 30 | B38: 48182000 | C38: Kitchen Roll 2Pcs Per Pac | D38: 85 | E38: =D38*J38+D38 -> 100.3 | F38: Pac | G38: - | J38: 0.18 | K38: MM | L38: FM
A39: =A38+1 -> 31 | B39: 48182000 | C39: Facial Tissue Refill -100Pcs | D39: 22 | E39: =D39*J39+D39 -> 25.96 | F39: 100 | G39: 150 | I39: Pac | J39: 0.18 | L39: not in tally
A40: =A39+1 -> 32 | B40: 48182000 | C40: Car Tissue Max 200Pull | D40: 70 | E40: =D40*J40+D40 -> 82.6 | F40: Box | G40: 50 | I40: Box | J40: 0.18 | K40: MM | L40: FM
A41: =A40+1 -> 33 | B41: 48183000 | C41: Popup Tissue (4x8)-PP 80pull | D41: 12 | E41: =D41*J41+D41 -> 14.16 | F41: 100 | G41: 300 | I41: Pac | J41: 0.18
A42: =A41+1 -> 34 | B42: 48183000 | C42: Table Top MM (125 Pulls) Tissue Paper * 80pac | D42: 21 | E42: =D42*J42+D42 -> 24.78 | F42: 150 | G42: 80 | I42: Pac | J42: 0.18
A43: =A42+1 -> 35 | B43: 48183000 | C43: Party Pop up Box | D43: 21 | E43: =D43*J43+D43 -> 24.78 | G43: 1000 | I43: Box | J43: 0.18
A44: =A43+1 -> 36 | B44: 48183000 | C44: Facial Tissue Box -100Pull | D44: 35 | E44: =D44*J44+D44 -> 41.3 | I44: Box | J44: 0.18
A45: =A44+1 -> 37 | B45: 48183000 | C45: Facial Tissue Box -200Pull | D45: 70 | E45: =D45*J45+D45 -> 82.6 | I45: Box | J45: 0.18
A46: 38 | B46: 48183000 | C46: 90/10 MM Toilet Paper Roll * 100Pcs | D46: 17 | E46: =D46*J46+D46 -> 20.06 | F46: Roll | G46: 100 | I46: Box | J46: 0.18
A47: 39 | B47: 48181000 | C47: Toilet Roll-140/10 : Sheet Size:10cmX11cm | D47: 22 | E47: =D47*J47+D47 -> 25.96 | F47: Roll | G47: 60 | I47: Roll | J47: 0.18 | K47: MM | L47: FM
A48: 40 | B48: 48182000 | C48: C Fold/ M Fold Towel 30cmx20cmx 34Gsm | D48: 32 | E48: =D48*J48+D48 -> 37.76 | F48: 120 | G48: 40 | I48: Pac | J48: 0.18 | K48: BW | L48: FM
A49: 41 | B49: 48182000 | C49: HRT Roll -2 Kg (Kitchen Roll) | D49: 290 | E49: =D49*J49+D49 -> 342.2 | F49: 2KG | G49: 8 | I49: Roll | J49: 0.18 | K49: MM | L49: FM
A50: =A49+1 -> 42 | B50: 48182000 | C50: HRT Roll -2 Kg (Kitchen Roll) 2Ply | D50: 300 | E50: =D50*J50+D50 -> 354 | F50: 2KG | G50: 8 | I50: Roll | J50: 0.18 | K50: MM | L50: FM
A51: =A50+1 -> 43 | B51: 48182000 | C51: Sented Tissue | D51: 1.25 | E51: =D51*J51+D51 -> 1.475 | F51: Pcs | G51: 3000 | I51: Pcs | J51: 0.18 | K51: BN | L51: FM
A52: =A51+1 -> 44 | B52: 48182000 | C52: Sented Tissue Refreshing Towel (8x10) | D52: 1.1 | E52: =D52*J52+D52 -> 1.298 | F52: Pcs | G52: 2000 | H52: 50000 | I52: Pcs | J52: 0.18
A53: =A52+1 -> 45 | B53: 48182000 | C53: Sented Tissue Wet Towlet (8x10) | D53: 1.1 | E53: =D53*J53+D53 -> 1.298 | F53: Pcs | G53: 2000 | H53: 50000 | I53: Pcs | J53: 0.18
A54: =A53+1 -> 46 | B54: 48182000 | C54: Button Tablet Tissue (70Gsm) | D54: 1.1 | E54: =D54*J54+D54 -> 1.298 | F54: Pcs | G54: 5000 | I54: Pcs | J54: 0.18 | K54: BN | L54: FM
A55: =A54+1 -> 47 | B55: 48182000 | C55: Nesta Face Wipes (Citrus, Aloe Vera ,cucumber,Rose & mint) | D55: 1.75 | E55: =D55*J55+D55 -> 2.065 | F55: Pcs | G55: 6000 | H55: 50000 | I55: Pcs | J55: 0.18 | K55: VP | L55: FM
A58: PAGE 16
B60: Sr.No | C60: Item | D60: Rate Excl GST/Pack | E60: Rate Incl GST | F60: Unit | G60: Std. Pack | I60: Printing MOQ
B61: 1 | C61: 16x16 T/B Tissue Paper - 40gsm | D61: 1 | E61: 1.18 | F61: Pcs | G61: 2000 | I61: 20000
B62: 2 | C62: 16x16 Nested 3Ply Tissue Paper - 60gsm | D62: 2.4 | E62: 2.832 | F62: Pcs | G62: 1400 | I62: 20000
B63: 3 | C63: 16x16 4Ply Napkin - 70gsm | D63: 2.4 | E63: 2.832 | F63: Pcs | G63: 1400 | I63: 20000
B64: 4 | C64: 16x16 Airlaid White Tissue paper - 60gsm | D64: 2.7 | E64: 3.186 | F64: Pcs | G64: 1400 | I64: -
B65: 5 | C65: 16x16 Airlaid Printed Tissue paper - 60gsm | D65: 2.85 | E65: 3.363 | F65: Pcs | G65: 800 | I65: -
B66: 7 | C66: 16x16 2ply Printed Tissue Paper - 34gsm | D66: 1 | E66: 1.18 | F66: Pcs | G66: 4000 | I66: 20000
B68: 9 | C68: 13x13 Nested 2 Ply | D68: 1.35 | E68: 1.593 | F68: Pcs | G68: 2000 | I68: 20000
B69: 10 | C69: 12x12 TB Brown Tissue Paper Printed - 35gsm | D69: 0.45 | E69: 0.531 | F69: 100Pcs | G69: 30Pac | I69: 25000
C72: Tissue Papers | D72: Rate Excl GST/Pack | E72: Rate Incl GST | F72: Unit | G72: Std. Pack/ Box | H72: Printing MOQ
A74: 1 | B74: 48183000 | C74: 9x9 1Ply RP Chapati Tissue Paper * 20pac
A75: 2 | B75: 48183000 | C75: 9x9 1Ply Zoft Tissue Paper (15G) (Pac) * 50pac | D75: 15 | E75: =D75*J75+D75 -> 17.7 | F75: 100/Pac | G75: 60Pac | H75: - | I75: Pac | J75: 0.18 | K75: MM | L75: FM
A76: 3 | B76: 48183000 | C76: 9X9 2Ply Zoft Tissue Paper * 50pac 23cm x 23cm | D76: 30 | E76: =D76*J76+D76 -> 35.4 | F76: 100/Pac | G76: 50Pac | H76: 500Pac | I76: Pac | J76: 0.18 | K76: MM | L76: FM
A77: 4 | B77: 48183000 | C77: 11X12 1Ply MM Tissue Paper (15G) (Pac) * 35pac | D77: 20 | E77: =D77*J77+D77 -> 23.6 | F77: 100/Pac | G77: 35Pac | H77: 500Pac | I77: Pac | J77: 0.18 | K77: MM | L77: FM
A78: 5 | B78: 48183000 | C78: 12X12 2Ply Zoft Tissue Paper * 4000pc | D78: 52 | E78: =D78*J78+D78 -> 61.36 | F78: 100/Pac | G78: 40Pac | H78: 350Pac | I78: Pac | J78: 0.18 | K78: MM | L78: FM
A79: 6 | B79: 48183000 | C79: 12X12 2Ply Tissue Paper G&G * 3000pc | D79: 55 | E79: =D79*J79+D79 -> 64.9 | F79: 100/Pac | G79: 30Pac | H79: 250Pac | I79: Pac | J79: 0.18
A80: 7 | B80: 48183000 | C80: 13X13 2Ply Tissue Paper G&G[PlainWhite] * 3000Pcs | D80: 65 | E80: =D80*J80+D80 -> 76.7 | F80: 100/Pac | G80: 30Pac | H80: 250Pac | I80: Pac | J80: 0.18 | K80: BW | L80: FM
A81: 8 | B81: 48183000 | C81: 13" X 13" 2 Ply Tissue Printed G&G (Elephant/Diamond) | D81: 70 | E81: =D81*J81+D81 -> 82.6 | F81: 100/Pac | G81: 30Pac | H81: 250Pac | I81: Pac | J81: 0.18 | K81: BW | L81: FM
A82: 9 | B82: 48183000 | C82: 16x16 2Ply Airline Max Tissue Printed * 4200Pcs | D82: 59 | E82: =D82*J82+D82 -> 69.62 | F82: 50/Pac | G82: 84pac | H82: - | I82: Pac | J82: 0.18
A83: 10 | B83: 48183000 | C83: 16X16 2Ply VH BlueTissue Paper (Heavy) *1600PCS | D83: 63.55 | E83: =D83*J83+D83 -> 74.989 | F83: 50/Pac | I83: Pac | J83: 0.18 | K83: BW | L83: FM
A84: 11 | B84: 48183000 | C84: 16X16 2Ply VH Brown Tissue Paper *2500PCS | D84: 42.37 | E84: =D84*J84+D84 -> 49.9966 | F84: 50/Pac | I84: Pac | J84: 0.18 | K84: BW | L84: FM
C85: TB Tissues
A86: =A85+1 -> 1 | B86: 48183000 | C86: 9x9 1Ply GG T/B Tissue Paper Print [3 Line Border] *pcs | D86: 40 | E86: =D86*J86+D86 -> 47.2 | F86: 100 | G86: 50 | H86: 25000 | I86: Pcs | J86: 0.18 | K86: BW | L86: FM
A87: 2 | B87: 48183000 | C87: 12" X 12" TB Brown Tissue Paper Printed - 35gsm | D87: 45 | E87: =D87*J87+D87 -> 53.1 | F87: 100 | G87: 25 | H87: 25000 | I87: Pcs | J87: 0.18 | K87: BW | L87: FM
A88: 3 | B88: 48183000 | C88: 16x16 TB Tissue White G&G [3 line Brown] * 2000Pcs | D88: 105 | E88: =D88*J88+D88 -> 123.9 | F88: 100 | G88: 20 | H88: 20000 | I88: Pcs | J88: 0.18
A89: 4 | B89: 48183000 | C89: 16" X 16" TB Tissue Brown G&G (3line Border)*2000pc | D89: 105 | E89: =D89*J89+D89 -> 123.9 | F89: 100 | G89: 20 | H89: 20000 | I89: Pcs | J89: 0.18 | K89: BW | L89: FM
C90: Nested Tissues
A91: 1 | B91: 48183000 | C91: 9x9 x2ply Imported Colour Tissue G&G | D91: 45 | E91: =D91*J91+D91 -> 53.1 | F91: 100 | G91: 50Pac | H91: - | I91: Pcs | J91: 0.18
A92: 2 | B92: 48183000 | C92: 13" X 13" Nested tissue Paper ColouredG&G | D92: 1.3 | E92: =D92*J92+D92 -> 1.534 | F92: Pcs | G92: 2000 | H92: 20000 | I92: Pcs | J92: 0.18 | L92: APO
A93: 3 | B93: 48183000 | C93: 16X16 2Ply Nested G&G Tissue Paper [Brown] *1800 Pcs | E93: =D93*J93+D93 -> 0 | F93: Pcs | G93: 1800 | H93: 20000 | I93: Pcs | J93: 0.18 | L93: APO
A94: 5 | B94: 48183000 | C94: 16" X 16" Nested 3Ply Tissue Paper Coloured - 60gsm | D94: 2.6 | E94: =D94*J94+D94 -> 3.068 | F94: Pcs | G94: 1400 | H94: 20000 | I94: Pcs | J94: 0.18
C95: Airlaid Tissues
A96: 1 | B96: 48183000 | C96: 9x9 2Ply Airlaid G&G Tissue Paper [Plain Black] * 5000Pcs | D96: 0.5 | E96: =D96*J96+D96 -> 0.59 | F96: Pcs | G96: 5000 | I96: Pcs | J96: 0.18
A97: 2 | B97: 48183000 | C97: 8x8 Airlaid Tissue Paper AC[Printed Black/Blue] * 8000Pcs | D97: 0.75 | E97: =D97*J97+D97 -> 0.885 | F97: Pcs | G97: 8000 | I97: Pcs | J97: 0.18 | K97: BW | L97: NL
A98: 3 | B98: 48183000 | C98: 12" X 16" Airlad Tissue White/Blue G&G - 50gsm | D98: 1.7 | E98: =D98*J98+D98 -> 2.006 | F98: Pcs | G98: 1750 | H98: 20000 | I98: Pcs | J98: 0.18
A99: 4 | B99: 48183000 | C99: 16x16 White Airlaid Tissue Paper AC * 2000Pcs | D99: 2.6 | E99: =D99*J99+D99 -> 3.068 | F99: Pcs | G99: 2000 | H99: 20000 | I99: Pcs | J99: 0.18
A100: 5 | B100: 48183000 | C100: 16" X 16" White Airlaid Tissue 50Gsm G&G | D100: 2.6 | E100: =D100*J100+D100 -> 3.068 | F100: Pcs | G100: 800 | H100: 20000 | I100: Pcs | J100: 0.18 | K100: BW | L100: FM
A101: 6 | B101: 48183000 | C101: 16" X 16" Printed Airlaid Tissue 50Gsm AC | D101: 2.9 | E101: =D101*J101+D101 -> 3.422 | F101: Pcs | G101: 800 | H101: - | I101: Pcs | J101: 0.18 | K101: MM | L101: FM
A102: 7 | B102: 48183000 | C102: 16" X 16" Colour Airlaid Tissue 50Gsm AC | D102: 3.4 | E102: =D102*J102+D102 -> 4.012 | F102: Pcs | G102: 800 | H102: - | I102: Pcs | J102: 0.18
C104: Speciality Tissues & Facial Tisues
C105: 8x8 MM Face Tissue ( 100 Pulls) Tissue Paper * 100pac | H105: 100 | I105: Pac | J105: 0.18
A106: 1 | B106: 48182000 | C106: Facial Tissue Refill -100Pcs | D106: 22 | E106: =D106*J106+D106 -> 25.96 | F106: 100 | G106: 150 | I106: Pac | J106: 0.18 | L106: not in tally
A107: =A106+1 -> 2 | B107: 48183000 | C107: Facial Tissue Box -100Pull | D107: 35 | E107: =D107*J107+D107 -> 41.3 | I107: Box | J107: 0.18
A108: =A107+1 -> 3 | B108: 48183000 | C108: Car Facial Tissue Paper RP (200N) * 72box | D108: 70 | E108: =D108*1.18 -> 82.6 | I108: Box | J108: 0.18
...

Sheet Pizza Boxes 
A1: Neeyog Packaging | N1: Summary Sheet | T1: Mamtora | U1: MM
A2: OFF:20, Gr Floor,Sidhpura Ind.Estate,S.V.Road,Gaiwadi Rd,Near Agilus Diagnostic Center,Goregaon(W),Mum- 062 | P2: NL | Q2: New Launch | T2: Bhiwandi | U2: BW
A3: Phone : 022-28760709 Mobile 9867607003 Email:neeyog@gmail.com | P3: FM | R3: 1-2 DAY | T3: Shop | U3: SH
A4: www.neeyog.com/www.indiamart.com/neeyogpackaging/www.facebook.com/neeyogpack | P4: LS | Q4: Limited Stock | R4: 3-4 DAYS | T4: Vapi | U4: VP
P5: APO | Q5: As per Order | R5: 15-20 DAYS | T5: Bansi | U5: BN
A6: Pizza Boxes Price & cake Boxes List | K6: ='Summary Sheet'!C7 -> Date 16.06.2026
A7: HSN CODE - 48191010
A9: PIZZA BOX SIZE | B9: 6" std | C9: 7" std | D9: 8" std | E9: 9" std | F9: 10" std | G9: 11" std | H9: 12" std | I9: 13" std | J9: 14" std | K9: 16" std | L9: 20" std | M9: GARLIC BREAD
A10: Box Pack in Pcs | B10: 100 | C10: 100 | D10: 100 | E10: 100 | F10: 50 | G10: 50 | H10: 50 | I10: 50 | J10: 50 | K10: 50 | L10: 50 | M10: 100
A12: GG PRINTED + WHITE | B12: 5.85 | C12: 6.65 | D12: 8.3 | E12: 9.2 | F12: 11.55 | H12: 15.7 | I12: 19.35
A14: GG PRINTED + BROWN | B14: 5.15 | C14: 5.85 | D14: 7.3 | E14: 8.1 | F14: 9.7 | H14: 13.75 | I14: 16.85 | K14: 25.3 | L14: 38.1 | M14: 5.2
A16: CUSTOMIZED DUPLEX | B16: 6.8 | C16: 7.6 | D16: 9.25 | E16: 10.15 | F16: 13 | G16: 16.55 | H16: 18.75 | I16: 22.2 | J16: 24.2 | K16: 31.5 | L16: 46 | M16: 6.7
A18: CUSTOMIZED BROWN | B18: 6 | C18: 6.9 | D18: 8.35 | E18: 9.15 | F18: 11.75 | G18: 15.4 | H18: 16.9 | I18: 20.35 | J18: 23.25 | K18: 29.35 | M18: 6
A20: PIZZA LINER | C20: 0.75 | D20: 1.15 | E20: 1.5 | F20: 1.75 | H20: 4.75

Sheet Thalia & Cake
A1: Neeyog Packaging | K1: summary sheet | S1: Mamtora | T1: MM
A2: OFF:20, Gr Fr,Sidhpura Ind.Est,S.V.Road,Gaiwadi, Near Agilus Diagnostic Center,Goregaon(W),Mum- 062 | O2: NL | P2: New Launch | S2: Bhiwandi | T2: BW
A3: Phone : 022-28760709 Mobile 9867607003 Email:neeyog@gmail.com | O3: FM | Q3: 1-2 DAY | S3: Shop | T3: SH
A4: www.neeyog.com / www.neeyog.net | O4: LS | P4: Limited Stock | Q4: 3-4 DAYS | S4: Vapi | T4: VP
O5: APO | P5: As per Order | Q5: 15-20 DAYS | S5: Bansi | T5: BN
A6: PAKNSERVE Cake Boxes Price List | B6: THALIA & CAKE, BURGER, SANDWICH & PIZZA BOXES | I6: 22.09.2025
A7: CODE | B7: SR. NO. | C7: GSM | D7: DESCRIPTION | E7: APPLICATION | F7: RATE | G7: RATE WITH GST | H7: PER | I7: STD PACK | J7: GST
D8: ITC BROWINE / CUP CAKE BOXES (HSN Code - 48192020) | K8: Primary Godown | L8: Movement | M8: Tally name
A9: ITCPS332WI | B9: 1 | C9: 280 | D9: ITC 3X3X2 Window | E9: 1 BROWINE | F9: 3 | G9: =F9*J9+F9 -> 3.15 | H9: Pcs | I9: 100 | J9: 0.05
A10: ITCPS632WI | B10: =B9+1 -> 2 | C10: 320 | D10: ITC 6X3X2 WINDOW 2BROWNIE 320G | E10: 2 BROWINE | F10: 5.5 | G10: =(F10*J10)+F10 -> 5.775 | H10: Pcs | I10: 100 | J10: 0.05 | K10: SH | L10: FM
A11: ITCPS662WI | B11: =B10+1 -> 3 | C11: 320 | D11: ITC 6X6X2 Window | E11: 4 BROWINE | F11: 6.75 | G11: =(F11*J11)+F11 -> 7.0875 | H11: Pcs | I11: 100 | J11: 0.05 | K11: SH | L11: LS
A12: ITCPSS962WI | B12: =B11+1 -> 4 | C12: 350 | D12: ITC 9X6X2 Window | E12: 6 BROWINE | F12: 8 | G12: =(F12*J12)+F12 -> 8.4 | H12: Pcs | I12: 100 | J12: 0.05 | L12: APO
A13: ITCPSS334WI | B13: =B12+1 -> 5 | C13: 280 | D13: ITC 3X3X4 Window +Insert 1Cupcake 280G * 1000Pcs | E13: 1CUPCAKE | F13: 5.5 | G13: =(F13*J13)+F13 -> 5.775 | H13: Pcs | I13: 100 | J13: 0.05 | K13: SH | L13: FM
A14: ITCPS634WI | B14: =B13+1 -> 6 | C14: 300 | D14: ITC 6x3x4 Window +Insert | E14: 2CUPCAKE | F14: 7.25 | G14: =(F14*J14)+F14 -> 7.6125 | H14: Pcs | I14: 100 | J14: 0.05 | K14: SH | L14: LS
A15: ITCPSS664WI | B15: =B14+1 -> 7 | C15: 350 | D15: ITC 6X6X4 WINDOW +INSERT 4CUPCAKE 350G | E15: 4CUPCAKE | F15: 9.5 | G15: =(F15*J15)+F15 -> 9.975 | H15: Pcs | I15: 100 | J15: 0.05 | K15: SH | L15: LS
A16: ITCPSS964WI | B16: =B15+1 -> 8 | C16: 350 | D16: ITC 9X6X4 WINDOW +INSERT 6CUP CAKE 350G | E16: 6CUP CAKE | F16: 12 | G16: =(F16*J16)+F16 -> 12.6 | H16: Pcs | I16: 100 | J16: 0.05 | L16: APO
D17: KRAFT BROWINE / CUP CAKE BOXES
A18: KFPS332WI | B18: 1 | C18: 280 | D18: KRAFT 4X4X3 ENJOY BOX 280G | E18: 1 BROWINE | F18: 3 | G18: =(F18*J18)+F18 -> 3.15 | H18: Pcs | I18: 100 | J18: 0.05 | K18: SH | L18: FM
A19: KFPS632WI | B19: =B18+1 -> 2 | C19: 320 | D19: Kraft 6X3X2 Window | E19: 2 BROWINE | F19: 5.5 | G19: =(F19*J19)+F19 -> 5.775 | H19: Pcs | I19: 100 | J19: 0.05 | K19: SH | L19: FM
A20: KFPS662WI | B20: =B19+1 -> 3 | C20: 320 | D20: KRAFT 6X6X2 WINDOW 320G | E20: 4 BROWINE | F20: 6.75 | G20: =(F20*J20)+F20 -> 7.0875 | H20: Pcs | I20: 100 | J20: 0.05 | K20: SH | L20: FM
A21: KFPS962WI | B21: =B20+1 -> 4 | C21: 350 | D21: Kraft 9X6X2 Window | E21: 6 BROWINE | F21: 8 | G21: =(F21*J21)+F21 -> 8.4 | H21: Pcs | I21: 100 | J21: 0.05 | K21: SH | L21: LS
A22: KFPS334WI | B22: =B21+1 -> 5 | C22: 280 | D22: Kraft 3x3x4 Window +Insert | E22: 1CUPCAKE | F22: 5.5 | G22: =(F22*J22)+F22 -> 5.775 | H22: Pcs | I22: 100 | J22: 0.05 | K22: SH | L22: FM
A23: KFPS634WI | B23: =B22+1 -> 6 | C23: 300 | D23: Kraft 6x3x4 Window +Insert | E23: 2CUPCAKE | F23: 7.25 | G23: =(F23*J23)+F23 -> 7.6125 | H23: Pcs | I23: 100 | J23: 0.05 | K23: SH | L23: FM
A24: KFPS664WI | B24: =B23+1 -> 7 | C24: 350 | D24: KRAFT 6X6X4 WINDOW +INSERT 350G | E24: 4CUPCAKE | F24: 9.5 | G24: =(F24*J24)+F24 -> 9.975 | H24: Pcs | I24: 100 | J24: 0.05 | K24: SH | L24: FM
A25: KFPS964WI | B25: =B24+1 -> 8 | C25: 350 | D25: Kraft 9X6X4 Window +Insert | E25: 6CUP CAKE | F25: 12 | G25: =(F25*J25)+F25 -> 12.6 | H25: Pcs | I25: 100 | J25: 0.05 | K25: SH | L25: FM
D26: KRAFT ENJOY BOXES
A27: KF443NJ | B27: 1 | C27: 280 | D27: Kraft 4*4*3 ENjoy Box | E27: SNACK BOX | F27: 3 | G27: =(F27*J27)+F27 -> 3.15 | H27: Pcs | I27: 100 | J27: 0.05 | K27: SH | L27: FM
A28: KF553NJ | B28: =B27+1 -> 2 | C28: 300 | D28: Kraft 5*5*3 ENjoy Box | E28: BURGER BOX | F28: 4 | G28: =(F28*J28)+F28 -> 4.2 | H28: Pcs | I28: 100 | J28: 0.05 | K28: SH | L28: FM
A29: KF753NJ | B29: =B28+1 -> 3 | C29: 300 | D29: Kraft 7*5*3 ENjoy Box | E29: SNACK BOX | F29: 5.25 | G29: =(F29*J29)+F29 -> 5.5125 | H29: Pcs | I29: 100 | J29: 0.05 | K29: SH | L29: FM
B30: =B29+1 -> 4 | D30: Kraft 9*6*3 ENjoy Box | K30: SH | L30: FM
D31: Printed Cake Boxes
A32: EGCB884 | B32: 1 | C32: 320 | D32: ELEGANT CAKE BOX 8X8X4 (PINK/BLUE) 320G | E32: 1/2 KG CAKE | F32: 8.5 | G32: =(F32*J32)+F32 -> 8.925 | H32: Pcs | I32: 100 | J32: 0.05 | K32: SH | L32: LS
D34: ITC CAKE BOXES
A35: ITC884WI | B35: 1 | C35: 300 | D35: ITC 8X8X4 Window 300G * 400Pcs | E35: 1/2CAKE | F35: 11 | G35: =(F35*J35)+F35 -> 11.55 | H35: Pcs | I35: 50 | J35: 0.05 | K35: SH | L35: FM
A36: ITC10104WI | B36: =B35+1 -> 2 | C36: 360 | D36: ITC 10X10X4 WINDOW 360G | E36: 1KG CAKE | F36: 14 | G36: =(F36*J36)+F36 -> 14.7 | H36: Pcs | I36: 50 | J36: 0.05 | K36: SH | L36: FM
A37: ITC885WI | B37: =B36+1 -> 3 | C37: 380 | D37: ITC Cake Box 8x8x5 Window | E37: 1/2CAKE | F37: 12.5 | G37: =(F37*J37)+F37 -> 13.125 | H37: Pcs | I37: 50 | J37: 0.05 | K37: SH | L37: FM
A38: ITC10105WI | B38: =B37+1 -> 4 | C38: 380 | D38: ITC Cake Box 10x10x5 Window | E38: 1KG CAKE | F38: 15.5 | G38: =(F38*J38)+F38 -> 16.275 | H38: Pcs | I38: 50 | J38: 0.05 | K38: SH | L38: LS
A40: CODE | B40: SR. NO. | C40: GSM | D40: DUPLEX BOXES | E40: APPLICATION | F40: RATE | G40: RATE WITH GST | H40: PER | I40: STD PACK | J40: GST
A41: DPSR552 | B41: 1 | C41: 320 | D41: Duplex Cake Box 5*5*2 | E41: 48191010 | F41: 1.75 | G41: =(F41*J41)+F41 -> 1.8375 | H41: Pcs | I41: 100 | J41: 0.05 | K41: SH
A42: DPSR553 | B42: =B41+1 -> 2 | C42: 320 | D42: Duplex Cake Box 5*5*3 | E42: 48191010 | F42: 2.5 | G42: =(F42*J42)+F42 -> 2.625 | H42: Pcs | I42: 100 | J42: 0.05 | K42: SH
A43: DPSR443 | B43: =B42+1 -> 3 | C43: 320 | D43: Duplex Cake Box 4*4*3 | E43: 48191010 | F43: 1.75 | G43: =(F43*J43)+F43 -> 1.8375 | H43: Pcs | I43: 100 | J43: 0.05 | K43: SH
A44: DPSR7525 | B44: =B43+1 -> 4 | C44: 320 | D44: Duplex Cake Box 7*5*2.5 | E44: 48191010 | F44: 2.7 | G44: =(F44*J44)+F44 -> 2.835 | H44: Pcs | I44: 100 | J44: 0.05 | K44: SH
A45: DPSR753 | B45: =B44+1 -> 5 | C45: 320 | D45: Duplex Cake Box 7*5*3 | E45: 48191010 | F45: 3.6 | G45: =(F45*J45)+F45 -> 3.78 | H45: Pcs | I45: 100 | J45: 0.05 | K45: SH
A46: DPSR883 | B46: =B45+1 -> 6 | C46: 320 | D46: Duplex Cake Box 8*8*4 | E46: 48191010 | F46: 5.1 | G46: =(F46*J46)+F46 -> 5.355 | H46: Pcs | I46: 100 | J46: 0.05 | K46: SH
A47: DPSR963 | B47: =B46+1 -> 7 | C47: 320 | D47: Duplex Cake Box 9*6*3 | E47: 48191010 | F47: 4.8 | G47: =(F47*J47)+F47 -> 5.04 | H47: Pcs | I47: 100 | J47: 0.05 | K47: SH
A48: DPSR884 | B48: =B47+1 -> 8 | C48: 350 | D48: Duplex Cake Box 8x8x4 | E48: 48191010 | F48: 5.76 | G48: =(F48*J48)+F48 -> 6.048 | H48: Pcs | I48: 50 | J48: 0.05 | K48: SH
A49: DPSR10104 | B49: =B48+1 -> 9 | C49: 350 | D49: Duplex Cake Box 10x10x4 | E49: 48191010 | F49: 7 | G49: =(F49*J49)+F49 -> 7.35 | H49: Pcs | I49: 50 | J49: 0.05 | K49: SH
A50: DPSR12124 | B50: =B49+1 -> 10 | C50: 400 | D50: Duplex Cake Box 12x12x4 | E50: 48191010 | F50: 13 | G50: =(F50*J50)+F50 -> 13.65 | H50: Pcs | I50: 50 | J50: 0.05 | K50: SH
A51: DPSR14144 | B51: =B50+1 -> 11 | C51: 400 | D51: Duplex Cake Box 14x14x4 | E51: 48191010 | F51: 15.5 | G51: =(F51*J51)+F51 -> 16.275 | H51: Pcs | I51: 50 | J51: 0.05 | K51: SH
A52: DPSR16164 | B52: =B51+1 -> 12 | C52: 450 | D52: Duplex Cake Box 16x16x4 | E52: 48191010 | F52: 24 | G52: =(F52*J52)+F52 -> 25.2 | H52: Pcs | I52: 50 | J52: 0.05 | K52: SH
A53: DPSR7715 | B53: =B52+1 -> 13 | C53: 320 | D53: Duplex Pizza Box7*7*1.5 | E53: 48191010 | F53: 2.9 | G53: =(F53*J53)+F53 -> 3.045 | H53: Pcs | I53: 100 | J53: 0.05 | K53: SH
... A56: DPSR121215 | B56: =B55+1 -> 16 | C56: 350 | D56: Duplex Pizza Box12*12*1.5 | E56: 48191010 | F56: 10.8 | G56: =(F56*J56)+F56 -> 11.34 | H56: Pcs | I56: 100 | J56: 0.05 | K56: SH
A57: CODE | B57: SR. NO. | C57: GSM | D57: ITC CAKE BOXES | E57: APPLICATION | F57: RATE | G57: RATE WITH GST | H57: PER | I57: STD PACK | J57: GST
A58: ITCSR443 | B58: 1 | C58: 320 | D58: ITC Cake Box 4x4x3 | E58: 48191010 | F58: 2 | G58: =(F58*J58)+F58 -> 2.1 | H58: Pcs | I58: 100 | J58: 0.05 | K58: SH
A59: ITCSR552 | B59: =B58+1 -> 2 | C59: 320 | D59: ITC 5X5X2 CAKE BOX 320G * 1000Pcs | E59: 48191010 | F59: 2 | G59: =(F59*J59)+F59 -> 2.1 | H59: Pcs | I59: 100 | J59: 0.05 | K59: SH
A60: ITCSR553 | B60: =B59+1 -> 3 | C60: 320 | D60: ITC CAKE BOX 5X5X3 320G | E60: 48191010 | F60: 4 | G60: =(F60*J60)+F60 -> 4.2 | H60: Pcs | I60: 100 | J60: 0.05 | K60: SH
A61: ITCSR7525 | B61: =B60+1 -> 4 | C61: 320 | D61: ITC Cake Box7x5x2.5 | E61: 48191010 | F61: 4 | G61: =(F61*J61)+F61 -> 4.2 | H61: Pcs | I61: 100 | J61: 0.05 | K61: SH
A62: ITCSR753 | B62: =B61+1 -> 5 | C62: 320 | D62: ITC Cake Box 7x5x3 | E62: 48191010 | F62: 4.8 | G62: =(F62*J62)+F62 -> 5.04 | H62: Pcs | I62: 100 | J62: 0.05 | K62: SH
A63: ITCSR963 | B63: =B62+1 -> 6 | C63: 350 | D63: ITC CAKE BOX 9X6X3 350G | E63: 48191010 | F63: 6 | G63: =(F63*J63)+F63 -> 6.3 | H63: Pcs | I63: 100 | J63: 0.05 | K63: SH
A64: ITCSR884 | B64: =B63+1 -> 7 | C64: 350 | D64: ITC CAKE BOX 8X8X4 350G | E64: 48191010 | F64: 9 | G64: =(F64*J64)+F64 -> 9.45 | H64: Pcs | I64: 50 | J64: 0.05 | K64: SH
A65: ITCSR10104 | B65: =B64+1 -> 8 | C65: 350 | D65: ITC Cake Boxx 10x10x4 | E65: 48191010 | F65: 10.8 | G65: =(F65*J65)+F65 -> 11.34 | H65: Pcs | I65: 50 | J65: 0.05 | K65: SH
A66: ITC885 | B66: =B65+1 -> 9 | C66: 380 | D66: ITC CAKE BOX 8X8X5 WINDOW 380G | E66: 48191010 | F66: 11 | G66: =(F66*J66)+F66 -> 11.55 | H66: Pcs | I66: 50 | J66: 0.05 | K66: SH
A67: ITC10105 | B67: =B66+1 -> 10 | C67: 380 | D67: ITC CAKE BOX 10X10X5 WINDOW 380G | E67: 48191010 | F67: 14 | G67: =(F67*J67)+F67 -> 14.7 | H67: Pcs | I67: 50 | J67: 0.05 | K67: SH
A68: ITCSR12124 | B68: =B67+1 -> 11 | C68: 400 | D68: ITC Cake Box 12x12x4 | E68: 48191010 | F68: 16.8 | G68: =(F68*J68)+F68 -> 17.64 | H68: Pcs | I68: 50 | J68: 0.05 | K68: SH
A69: ITCSR14144 | B69: =B68+1 -> 12 | C69: 400 | D69: ITC Cake Box 14x14x4 | E69: 48191010 | F69: 20.5 | G69: =(F69*J69)+F69 -> 21.525 | H69: Pcs | I69: 50 | J69: 0.05 | K69: SH
A70: ITCSR101015 | B70: =B69+1 -> 13 | C70: 350 | D70: ITC Pizza Box10*10*1.5 | E70: 48191010 | F70: 7.8 | G70: =(F70*J70)+F70 -> 8.19 | H70: Pcs | I70: 100 | J70: 0.05 | K70: SH
A71: ITCSR121215 | B71: =B70+1 -> 14 | C71: 350 | D71: ITC Pizza Box12*12*1.5 | E71: 48191010 | F71: 10.8 | G71: =(F71*J71)+F71 -> 11.34 | H71: Pcs | I71: 100 | J71: 0.05 | K71: SH
A72: CODE | B72: SR. NO. | C72: GSM | D72: KRAFT CAKE BOXES | E72: APPLICATION | F72: RATE | G72: RATE WITH GST | H72: PER | I72: STD PACK | J72: GST
B73: 1 | D73: Kraft Cake Box6x6x4 | J73: 0.05
A74: KRSR7525 | B74: =B73+1 -> 2 | C74: 320 | D74: Kraft Cake Box7x5x2.5 | E74: 48191010 | F74: 4 | G74: =(F74*J74)+F74 -> 4.2 | H74: Pcs | I74: 100 | J74: 0.05 | K74: SH
A75: KRSR753 | B75: =B74+1 -> 3 | C75: 320 | D75: KRAFT CAKE BOX 7X5X3 320G | E75: 48191010 | F75: 4.8 | G75: =(F75*J75)+F75 -> 5.04 | H75: Pcs | I75: 100 | J75: 0.05 | K75: SH
A76: KRSR963 | B76: =B75+1 -> 4 | C76: 350 | D76: Kraft Cake Box 9x6x3 | E76: 48191010 | F76: 6 | G76: =(F76*J76)+F76 -> 6.3 | H76: Pcs | I76: 100 | J76: 0.05 | K76: SH
A77: KRSR884 | B77: =B76+1 -> 5 | C77: 350 | D77: KRAFT CAKE BOX 8X8X4 350G | E77: 48191010 | F77: 9 | G77: =(F77*J77)+F77 -> 9.45 | H77: Pcs | I77: 50 | J77: 0.05 | K77: SH
A78: KRSR10104 | B78: =B77+1 -> 6 | C78: 350 | D78: Kraft Cake Box 10x10x4 | E78: 48191010 | F78: 10.8 | G78: =(F78*J78)+F78 -> 11.34 | H78: Pcs | I78: 50 | J78: 0.05 | K78: SH
A79: CODE | B79: SR. NO. | C79: GSM | D79: JAR BAG | E79: APPLICATION | F79: RATE | G79: RATE WITH GST | H79: PER | I79: STD PACK | J79: GST
A80: PNS1JARBG | B80: 1 | C80: 350 | D80: 1 JAR BAG (5.75 X 8 X 3.5 inch) | E80: 48191010 | F80: 12 | G80: =(F80*J80)+F80 -> 12.6 | H80: Pcs | I80: 100 | J80: 0.05 | K80: SH | L80: FM
A81: PNS2JARBG | B81: =B80+1 -> 2 | C81: 350 | D81: 2 JAR BAG (7.5 X 8 X 3.5 inch) | E81: 48191010 | F81: 15.5 | G81: =(F81*J81)+F81 -> 16.275 | H81: Pcs | I81: 100 | J81: 0.05 | K81: SH | L81: FM
A82: PNS3JARBG | B82: =B81+1 -> 3 | C82: 350 | D82: 3 JAR BAG (10.5 X 8 X 3.5 inch) | E82: 48191010 | F82: 20.5 | G82: =(F82*J82)+F82 -> 21.525 | H82: Pcs | I82: 100 | J82: 0.05 | K82: SH | L82: LS
A83: CODE | B83: SR. NO. | C83: GSM | D83: OTHER SPECIAL BOX | E83: APPLICATION | F83: RATE | G83: RATE WITH GST | H83: PER | I83: STD PACK | J83: GST
A84: PNSPLUMCK | B84: 1 | C84: 320 | D84: Plum Cake (4 X 7.5 X 2.5) | E84: 48191010 | F84: 9.3 | G84: =(F84*J84)+F84 -> 9.765 | H84: Pcs | I84: 100 | J84: 0.05 | L84: APO
A85: PNSLOAFCK | B85: =B84+1 -> 2 | C85: 320 | D85: Loaf Cake Box (5 X 11.5 X 3) | E85: 48191010 | F85: 12.55 | G85: =(F85*J85)+F85 -> 13.1775 | H85: Pcs | I85: 100 | J85: 0.05 | L85: APO
A86: PNSWAFBX | B86: =B85+1 -> 3 | D86: WAFFLE BOX | E86: 48191010 | F86: 5 | G86: =(F86*J86)+F86 -> 5.25 | H86: Pcs | I86: 100 | J86: 0.05 | K86: SH | L86: LS
A87: PNSWAFTY | B87: =B86+1 -> 4 | D87: WAFFLE TRAY 9.5X2.25X1.5 | E87: 48191010 | F87: 3.5 | G87: =(F87*J87)+F87 -> 3.675 | H87: Pcs | I87: 100 | J87: 0.05 | K87: SH | L87: LS
A88: CODE | B88: SR. NO. | C88: GSM | D88: SWEET BOX | E88: APPLICATION | F88: RATE | G88: RATE WITH GST | H88: PER | I88: STD PACK | J88: GST
A89: PNS100SWBX | B89: 1 | C89: 320 | D89: 100grm Duplex with Inside Lamination | E89: 48191010 | F89: 9.3 | G89: =(F89*J89)+F89 -> 9.765 | H89: Pcs | I89: 100 | J89: 0.05 | K89: SH | L89: FM
A90: PNS500SWBX | B90: =B89+1 -> 2 | C90: 320 | D90: 500grm Sweet box DP+LM | E90: 48191010 | F90: 12.55 | G90: =(F90*J90)+F90 -> 13.1775 | H90: Pcs | I90: 100 | J90: 0.05 | K90: SH | L90: LS
A91: PNS1KGSWBX | B91: =B90+1 -> 3 | C91: 320 | D91: 1kg Sweet Box DP+LM | E91: 48191010 | F91: 5 | G91: =(F91*J91)+F91 -> 5.25 | H91: Pcs | I91: 100 | J91: 0.05 | L91: APO
A93: SR. NO. | B93: SR. NO. | D93: DESCRIPTIONS | E93: HSN CODE | F93: MDF Board | G93: RATE WITH GST | H93: PER | I93: STD PACK | J93: GST
A95: 1 | B95: 1 | D95: 7X7 | E95: 48191010 | F95: 3.5 | G95: =(F95*J95)+F95 -> 4.13 | H95: Pcs | I95: 100 | J95: 0.18 | L95: APO
A96: 2 | B96: =B95+1 -> 2 | D96: 8X8 | E96: 48191010 | F96: 4.5 | G96: =(F96*J96)+F96 -> 5.31 | H96: Pcs | I96: 100 | J96: 0.18 | K96: SH | L96: FM
A97: 3 | B97: =B96+1 -> 3 | D97: 9X9 | E97: 48191010 | F97: 6 | G97: =(F97*J97)+F97 -> 7.08 | H97: Pcs | I97: 100 | J97: 0.18 | L97: APO
A98: 4 | B98: =B97+1 -> 4 | D98: 10X10 | E98: 48191010 | F98: 7 | G98: =(F98*J98)+F98 -> 8.26 | H98: Pcs | I98: 100 | J98: 0.18 | K98: SH | L98: FM
A99: 5 | B99: =B98+1 -> 5 | D99: 12X12 | E99: 48191010 | F99: 10.5 | G99: =(F99*J99)+F99 -> 12.39 | H99: Pcs | I99: 100 | J99: 0.18 | K99: SH | L99: FM
A100: 6 | B100: =B99+1 -> 6 | D100: 14X14 | E100: 48191010 | F100: 16 | G100: =(F100*J100)+F100 -> 18.88 | H100: Pcs | I100: 100 | J100: 0.18 | K100: SH | L100: LS
A101: 7 | B101: =B100+1 -> 7 | D101: 16X16 | E101: 48191010 | F101: 19 | G101: =(F101*J101)+F101 -> 22.42 | H101: Pcs | I101: 100 | J101: 0.18 | K101: SH | L101: LS

Sheet Recyclable Containers
A1: Neeyog Packaging | I1: Summary Sheet' | P1: Warehouse
A2: OFF:20, Gr Floor,Sidhpura Ind.Estate,S.V.Road,Gaiwadi Rd,Near Agilus Diagnostic Center,Goregaon(W),Mum- 062 | P2: Mamtora | Q2: MM
A3: Phone : 022-28760709 Mobile 9867607003 Email:neeyog@gmail.com | L3: New Launch | P3: Bhiwandi | Q3: BW
A4: www.neeyog.com/www.indiamart.com/neeyogpackaging/www.facebook.com/neeyogpack | L4: FM | N4: 1-2 DAY | P4: Shop | Q4: SH
A5: Wholesale Recyclable Containers Price List | F5: ='Summary Sheet'!C7 -> Date 16.06.2026 | L5: LS | M5: Limited Stock | N5: 3-4 DAYS | P5: Vapi | Q5: VP
A6: SR No | B6: Image | C6: Description | D6: Rate Excl Gst | E6: Rate Incl Gst | F6: Per Pcs | G6: Std Pack | H6: GST Rate | I6: Primary Godown | J6: Movement | L6: APO | M6: As per Order | N6: 15-20 DAYS | P6: Bansi | Q6: BN
C7: SAUCE CUP FLAT
A8: 1 | C8: 1OZ SD 25ml (Hinged) PP Food Cont Trans (AL) | D8: ='SD Temper Proof '!D10 -> 0.68 | E8: =D8+D8*H8 -> 0.8024 | F8: Pcs | G8: 5000 | H8: 0.18 | I8: VP | J8: FM
A9: 2 | C9: 2OZ SD 60ml (Hinged) PP Food Cont Trans (AL) | D9: 1.15 | E9: =D9+D9*H9 -> 1.357 | F9: Pcs | G9: 3000 | H9: 0.18 | I9: VP | J9: FM
C10: SAUCE CUP FLAT
A11: 1 | C11: 1OZ BS 25ml (Hinged) PP Food Cont Trans (AL) * 4800pcs | D11: 0.58 | E11: =D11+D11*H11 -> 0.6844 | F11: Pcs | G11: 4800 | H11: 0.18 | I11: VP | J11: FM
A12: 2 | C12: 2OZ BS 50ml (Hinged) PP Food Cont Trans (AL) * 2400pcs | D12: 1.1 | E12: =D12+D12*H12 -> 1.298 | F12: Pcs | G12: 2400 | H12: 0.18 | I12: VP | J12: FM
C13: Food Cont 2CP (Microwaveable) -NP (HSN Code 39233090)
A14: 1 | C14: 500ml 2CP HP Rect PP Twin Container Black / Lid Trans * 500pcs | D14: 6.65 | E14: =D14+D14*H14 -> 7.847 | F14: Pcs | G14: 500 | H14: 0.18 | I14: VP | J14: FM
C15: Food Cont (Microwaveable) -AP (HSN Code 39241090) | D15: Rate Excl Gst | E15: Rate Incl Gst | F15: Per Pcs | G15: Std Pack | H15: GST Rate
A16: 1 | C16: 25ml AP PP Tall Food Container AP (Attached Lid) | D16: 0.66 | E16: =D16+D16*18% -> 0.7788 | F16: Pcs | G16: 7500 | H16: 0.18 | I16: VP | J16: FM
A17: 2 | C17: 50ml AP PP Tall Food Container AP (Attached Lid) | D17: 1.5 | E17: =D17+D17*18% -> 1.77 | F17: Pcs | G17: 5000 | H17: 0.18 | I17: MM | J17: FM
A18: 3 | C18: 100ml AP PP Food Container AP (Attached Lid) | D18: 1.85 | E18: =D18+D18*18% -> 2.183 | F18: Pcs | G18: 3000 | H18: 0.18
A19: 4 | C19: 50ml Round AP Container Trans/Trans Lid *6000Pcs | D19: 0.85 | E19: =D19+D19*18% -> 1.003 | F19: Pcs | G19: 6000 | H19: 0.18 | I19: VP | J19: FM
A20: 5 | C20: 100ml Round AP PP Food Cont Black / Lid Trans (80D) | D20: 1.75 | E20: =D20+D20*18% -> 2.065 | F20: Pcs | G20: 3600 | H20: 0.18 | I20: MM | J20: FM
A21: 6 | C21: 125ml Round AP PP Food Cont Black / Lid Trans (80D) | D21: 1.9 | E21: =D21+D21*18% -> 2.242 | F21: Pcs | G21: 3500 | H21: 0.18 | I21: MM | J21: FM
A22: 7 | C22: 150ml Round AP PP Food Cont Black / Lid Trans (New) (85D) | D22: 2.45 | E22: =D22+D22*18% -> 2.891 | F22: Pcs | G22: 2500 | H22: 0.18 | I22: MM | J22: FM
A23: 9 | C23: 250ml Natraj AP PP Food Cont Black / Lid Trans (110D) | D23: 2.6 | E23: =D23+D23*18% -> 3.068 | F23: Pcs | G23: 2000 | H23: 0.18 | I23: MM | J23: FM
A24: 10 | C24: 500G Natraj AP PP Food Cont Black / Lid Trans (110D) | D24: 3.15 | E24: =D24+D24*18% -> 3.717 | F24: Pcs | G24: 1500 | H24: 0.18 | I24: MM | J24: FM
A25: 11 | C25: 500ML Natraj AP PP Food Cont Black / Lid Trans (110D) | D25: 3.4 | E25: =D25+D25*18% -> 4.012 | F25: Pcs | G25: 1500 | H25: 0.18 | I25: MM | J25: FM
A26: 12 | C26: 750ML Natraj AP PP Food Cont Trans / Lid Trans (110D) | D26: 4.95 | E26: =D26+D26*18% -> 5.841 | F26: Pcs | G26: 1000 | H26: 0.18 | I26: VP | J26: FM
A27: 13 | C27: 250ml Round Tall AP PP Food Cont Black / Lid Trans 95D * 2000pc | D27: 2.55 | E27: =D27+D27*18% -> 3.009 | F27: Pcs | G27: 2000 | H27: 0.18 | I27: MM | J27: FM
A28: 14 | C28: 225ML Round AP PP Food Cont Black / Lid Trans (120D) | D28: 3.15 | E28: =D28+D28*18% -> 3.717 | F28: Pcs | G28: 2000 | H28: 0.18
A29: 15 | C29: 250ML Round AP PP Food Cont Black / Lid Trans (120D) | D29: 3.3 | E29: =D29+D29*18% -> 3.894 | F29: Pcs | G29: 2000 | H29: 0.18
A30: 16 | C30: 300ML Round AP PP Food Cont Black / Lid Trans (120D) | D30: 3.75 | E30: =D30+D30*18% -> 4.425 | F30: Pcs | G30: 1500 | H30: 0.18 | I30: MM | J30: FM
A31: 17 | C31: 500N AP PP Food Cont Black / Lid Trans (120D) | D31: 4.25 | E31: =D31+D31*18% -> 5.015 | F31: Pcs | G31: 1500 | H31: 0.18 | I31: MM | J31: FM
A32: 18 | C32: 500ml Round Cont XL AP (120D) | D32: 4.75 | E32: =D32+D32*18% -> 5.605 | F32: Pcs | G32: 1500 | H32: 0.18 | I32: VP | J32: FM
A33: 19 | C33: 750ml N Round AP PP Food Cont Black / Lid Trans (120D) | D33: 6.3 | E33: =D33+D33*18% -> 7.434 | F33: Pcs | G33: 1000 | H33: 0.18
A34: 20 | C34: 675ml New Round Cont AP (120D) | D34: 5.05 | E34: =D34+D34*18% -> 5.959 | F34: Pcs | G34: 1200 | H34: 0.18 | J34: APO
A35: 21 | C35: 1000ml Round Tall AP PP Food Cont Black / Lid Trans (120D) | D35: 6.5 | E35: =D35+D35*18% -> 7.67 | F35: Pcs | G35: 1200 | H35: 0.18 | I35: MM | J35: FM
A36: 22 | C36: 650ml Black Bowl (145D) | D36: 6.1 | E36: =D36+D36*18% -> 7.198 | F36: Pcs | G36: 800 | H36: 0.18 | I36: BW | J36: FM
A37: 23 | C37: 600ml Flat AP PP Food Cont Black / Lid Trans (145D) | D37: 5.9 | E37: =D37+D37*18% -> 6.962 | F37: Pcs | G37: 800 | H37: 0.18 | I37: MM | J37: FM
A38: 24 | C38: 750ML Flat AP PP Food Cont Black / Lid Trans (145D) | D38: 6.4 | E38: =D38+D38*18% -> 7.552 | F38: Pcs | G38: 800 | H38: 0.18 | I38: VP | J38: FM
A39: 25 | C39: 1000ml Flat AP PP Food RD Cont Black / Lid Trans (145D) | D39: 8.45 | E39: =D39+D39*18% -> 9.971 | F39: Pcs | G39: 800 | H39: 0.18 | I39: VP | J39: FM
A40: 26 | C40: 1200ml Flat AP PP Food Cont Trans / Lid Trans (145D) | D40: 9 | E40: =D40+D40*18% -> 10.62 | F40: Pcs | G40: 800 | H40: 0.18 | I40: VP | J40: LS
A41: 27 | C41: 1500ml Flat AP PP Food Cont Trans / Lid Trans (145D) | D41: 10.15 | E41: =D41+D41*18% -> 11.977 | F41: Pcs | G41: 800 | H41: 0.18 | I41: VP | J41: FM
A42: 28 | C42: 2000ML Flat AP PP Food Cont Black / Lid Trans (170D) | D42: 9 | E42: =D42+D42*18% -> 10.62 | F42: Pcs | G42: 400 | H42: 0.18 | I42: VP | J42: FM
A43: 29 | C43: 2500ML Flat AP PP Food Cont Black / Lid Trans (170D) | D43: 13.8 | E43: =D43+D43*18% -> 16.284 | F43: Pcs | G43: 400 | H43: 0.18 | I43: VP | J43: FM
A44: 30 | C44: 500ml Elite Rect AP PP Food Cont Black / Lid Trans | D44: 5.6 | E44: =D44+D44*18% -> 6.608 | F44: Pcs | G44: 500 | H44: 0.18 | I44: VP | J44: FM
A45: 31 | C45: 650ml Elite Rect AP PP Food Cont Black /Lid Trans | D45: 6.1 | E45: =D45+D45*18% -> 7.198 | F45: Pcs | G45: 500 | H45: 0.18 | I45: VP | J45: FM
A46: 32 | C46: 750ml Elite Rect AP PP Food Cont Black / Lid Trans | D46: 6.2 | E46: =D46+D46*18% -> 7.316 | F46: Pcs | G46: 500 | H46: 0.18 | I46: VP | J46: FM
A47: 33 | C47: 1000ml Elite Rect AP PP Food Cont Black / Lid Trans | D47: 7.25 | E47: =D47+D47*18% -> 8.555 | F47: Pcs | G47: 500 | H47: 0.18 | I47: VP | J47: FM
C48: Zen (HSN Code 39241090) | D48: Rate Excl Gst | E48: Rate Incl Gst | F48: Per Pcs | G48: Std Pack | H48: GST Rate
A49: 1 | C49: 500ml Zen Rect AP PP Food Cont Black/ Lid Trans | D49: 4.4 | E49: =D49+D49*18% -> 5.192 | F49: Pcs | G49: 500 | H49: 0.18 | J49: APO
A50: 2 | C50: 650ml Zen Rect AP PP Food Cont Black/ Lid Trans | D50: 4.95 | E50: =D50+D50*18% -> 5.841 | F50: Pcs | G50: 500 | H50: 0.18 | J50: APO
A51: 3 | C51: 750ml Zen Rect AP PP Food Cont Black/ Lid Trans | D51: 5.05 | E51: =D51+D51*18% -> 5.959 | F51: Pcs | G51: 500 | H51: 0.18 | J51: APO
A52: 4 | C52: 1000ml Zen Rect AP PP Food Cont Black/ Lid Trans | D52: 6.15 | E52: =D52+D52*18% -> 7.257 | F52: Pcs | G52: 500 | H52: 0.18 | J52: APO
C53: Sweet Box (HSN Code 39241090)
A54: 1 | C54: 250GM Rect AP Sweet Food Cont with Lid | D54: 6.25 | E54: =D54+D54*18% -> 7.375 | F54: Pcs | G54: 1000 | H54: 0.18 | J54: APO
A55: 2 | C55: 500GM Rect AP Sweet Food Cont with Lid | D55: 10.7 | E55: =D55+D55*18% -> 12.626 | F55: Pcs | G55: 600 | H55: 0.18 | J55: APO
A56: 3 | C56: 1000gm Rect AP Sweet Cont White/Lid Trans | D56: 14.75 | E56: =D56+D56*18% -> 17.405 | F56: Pcs | G56: 400 | H56: 0.18 | J56: APO
C57: Food Cont Container -DP (HSN Code 39231090)
A58: 1 | C58: 25ML VE PP Food Cont Trans / Lid Trans * 5000pc | D58: 0.85 | E58: =D58+D58*H58 -> 1.003 | F58: Pcs | G58: 5000 | H58: 0.18 | I58: VP | J58: FM
A59: 2 | C59: 40ML DP PP Food Cont Dettached | D59: 1 | E59: =D59+D59*H59 -> 1.18 | F59: Pcs | G59: 5000 | H59: 0.18 | I59: VP | J59: FM
A60: 3 | C60: 50ML DP PP Food Cont Dettached | D60: 1.29 | E60: =D60+D60*H60 -> 1.5222 | F60: Pcs | G60: 5000 | H60: 0.18 | I60: BW | J60: LS
A61: 4 | B61: 39233090 | C61: 150ml Dessert Round Container with Lid | D61: 2.2 | E61: =D61+D61*H61 -> 2.596 | F61: Pcs | G61: 2000 | H61: 0.18 | I61: BW | J61: LS
C62: Recyclable Rice Bowl (SP ) (HSN Code 39231010)
A63: 1 | C63: 200ml SP Lassi PP Bev Cont (WL) Trans * 2000pc | D63: 3.65 | E63: =D63+D63*H63 -> 4.307 | F63: Pcs | G63: 2000 | H63: 0.18 | I63: VP | J63: FM
A64: 2 | C64: A-200ML SP Amul PP Food Cont | D64: 3.65 | E64: =D64+D64*H64 -> 4.307 | F64: Pcs | G64: 2000 | H64: 0.18 | I64: MM | J64: FM
A65: 3 | C65: 300ML SP Rice Bowl (WL) | D65: 4 | E65: =D65+D65*H65 -> 4.72 | F65: Pcs | G65: 1400 | H65: 0.18 | I65: MM | J65: LS
A66: 4 | C66: 500ML SP Rice Bowl (WL)(400ML) | D66: 4.5 | E66: =D66+D66*H66 -> 5.31 | F66: Pcs | G66: 1200 | H66: 0.18 | I66: MM | J66: LS
A67: 5 | C67: 550ML SP RICE Bowl Black /Lid Trans (WL) * 800pcs | D67: 6.2 | E67: =D67+D67*H67 -> 7.316 | F67: ` | G67: 800 | H67: 0.18
A68: 6 | C68: 650ML SP Rice Bowl (WL) | D68: 6.5 | E68: =D68+D68*H68 -> 7.67 | F68: Pcs | G68: 600 | H68: 0.18 | I68: VP | J68: FM
C69: IP Pack Food Container (HSN Code 39239090)
C70: Food Cont Container - IP (HSN Code 39241090)
A71: 1 | C71: 50ml IP Food Packaging Container * 3000pcs | D71: 0.9 | E71: =D71+D71*H71 -> 1.062 | F71: Pcs | G71: 3000 | H71: 0.18
C72: Ostern PP Containers (Microwaveable) (HSN Code 39231090)
A73: 1 | C73: 500ml 2CP GI Rect PP Twin Container Black / Lid Trans | D73: 8.3 | E73: =D73+D73*H73 -> 9.794 | F73: Pcs | G73: 500 | H73: 0.18 | I73: MM | J73: FM
A74: =A73+1 -> 2 | C74: CD 1200ML 3CP GI Meal Tray Black with Trans Lid | D74: 17.2 | E74: =D74+D74*H74 -> 20.296 | F74: Pcs | G74: 300 | H74: 0.18 | I74: MM | J74: FM
A75: =A74+1 -> 3 | C75: CD 950 Rect Cont.Black(6630) | D75: 12.3 | E75: =D75+D75*H75 -> 14.514 | F75: Pcs | G75: 300 | H75: 0.18 | I75: MM | J75: FM
A76: 4 | C76: C 2000ML GI Rect Food Cont Black / Flat Lid Trans *200Pcs | D76: 23.5 | E76: =D76+D76*H76 -> 27.73 | F76: Pcs | G76: 200 | H76: 0.18
A77: 5 | C77: BK-2500ml Round bucket Container | D77: 32.2 | E77: =D77+D77*H77 -> 37.996 | F77: Pcs | G77: 80 | H77: 0.18 | I77: MM | J77: FM
A78: =A77+1 -> 6 | C78: BK-3200ml Round bucket Container | D78: 36 | E78: =D78+D78*H78 -> 42.48 | F78: Pcs | G78: 80 | H78: 0.18 | I78: MM | J78: FM
A79: 7 | C79: BK-4500ml Round bucket Container | D79: 42 | E79: =D79+D79*H79 -> 49.56 | F79: Pcs | G79: 80 | H79: 0.18 | I79: MM | J79: FM
A80: =A79+1 -> 8 | C80: MP 3CP THALI | D80: 12.75 | E80: =D80+D80*H80 -> 15.045 | F80: Pcs | G80: 200 | H80: 0.18 | J80: not in tally
A81: =A80+1 -> 9 | C81: MP 4CP THALI | D81: 15.7 | E81: =D81+D81*H81 -> 18.526 | F81: Pcs | G81: 150 | H81: 0.18 | J81: not in tally
A82: 10 | C82: MP 5CP THALI | D82: 15.2 | E82: =D82+D82*H82 -> 17.936 | F82: Pcs | G82: 200 | H82: 0.18 | J82: APO
A83: =A82+1 -> 11 | C83: MP 8CP THALI | D83: 20.9 | E83: =D83+D83*H83 -> 24.662 | F83: Pcs | G83: 150 | H83: 0.18 | I83: MM | J83: LS
A84: =A83+1 -> 12 | C84: PF 750 ( Bucket 750 ML ) | D84: 9.4 | E84: =D84+D84*H84 -> 11.092 | F84: Pcs | G84: 500 | H84: 0.18 | J84: not in tally
A85: 13 | C85: PF 1200 ( Bucket 1200 ML ) | D85: 14.45 | E85: =D85+D85*H85 -> 17.051 | F85: Pcs | G85: 250 | H85: 0.18 | J85: not in tally
C86: Sipper Juice Glasses (HSN Code 39231090)
A87: 1 | C87: J 250 ( 250 ML ) | D87: 4.5 | E87: =D87+D87*H87 -> 5.31 | F87: Pcs | G87: 1000 | H87: 0.18
A88: 2 | C88: J 350 ( 350 ML ) | D88: 5 | E88: =D88+D88*H88 -> 5.9 | F88: Pcs | G88: 500 | H88: 0.18
A89: 3 | C89: J 500 ( 500 ML ) | D89: 5.85 | E89: =D89+D89*H89 -> 6.903 | F89: Pcs | G89: 500 | H89: 0.18
C92: 25ml CM PP Food Cont (AL) * 5000pcs
C93: 200ml Round Pet Bottle AF (OB) (38D-16gm) * 170pc

Sheet Sipper Container 
A1: Neeyog Packaging
A2: OFF:- G20 Sidhpura Ind Estate, Near SRL Diagnostic Centre, SV Road, Goregaon West , Mumbai 400062
A3: Phone : 022-28760709/42667003 Mob: 7045402654 Email:neeyog@gmail.com
A4: www.neeyog.com/www.indiamart.com/neeyogpackaging/www.facebook.com/neeyogpack
A6: Paknserve Sipper Container Price List | I6: Date 25-05-2026
A8: Sr. No. | B8: HSN Code | C8: Description | D8: Excl. Gst Rate | E8: Incl. Gst rate | F8: Unit | G8: Std. Pack. | H8: GST Extra | I8: Image
A9: Paknserve Sipper Container With Black Lid (80 & 90Dia)
A10: 1 | B10: 39233090 | C10: 250ML Paknserve Sipper Cont with Black lid (80Dia) | D10: 3.1 | E10: =D10+D10*H10 -> 3.658 | F10: Pcs | G10: 1000 | H10: 0.18
A11: 2 | B11: 39233090 | C11: 300ML Paknserve Sipper Cont with Black lid (80Dia) | D11: 3.4 | E11: =D11+D11*H11 -> 4.012 | F11: Pcs | G11: 1000 | H11: 0.18
A12: 3 | B12: 39233090 | C12: 350ML Paknserve Sipper (Flat) Cont with Black lid (80Dia) | D12: 3.85 | E12: =D12+D12*H12 -> 4.543 | F12: Pcs | G12: 1000 | H12: 0.18
A13: 4 | B13: 39233090 | C13: 350ML Paknserve Sipper (Flat) Cont with Black lid (90Dia) | D13: 4 | E13: =D13+D13*H13 -> 4.72 | F13: Pcs | G13: 1000 | H13: 0.18
A14: 5 | B14: 39233090 | C14: 500ML Paknserve Sipper (Flat) Cont with Black lid (90Dia) | D14: 5 | E14: =D14+D14*H14 -> 5.9 | F14: Pcs | G14: 1000 | H14: 0.18
A15: 6 | B15: 39233090 | C15: Sipper Cont Black lid only for 250/300ml (80Dia) | D15: 1.05 | E15: =D15+D15*H15 -> 1.239 | F15: Pcs | G15: 4000 | H15: 0.18
A16: 7 | B16: 39233090 | C16: Sipper Cont Black lid only for 350/500ml (90Dia) | D16: 1.25 | E16: =D16+D16*H16 -> 1.475 | F16: Pcs | G16: 4000 | H16: 0.18
C17: Colour Lids (80/90) for Sipper Cups Shall Be @0.10 extra (White/Black & clear will be Considered as Regular)
C18: Available Colour are Red,green,Orange,Purple,Blue,Pink. Any New colour will require MOQ of 1lakh pcs
A19: Paknserve Sipper Container With Flat Lid (80Dia)
A20: 1 | B20: 39233090 | C20: 250ML Paknserve Sipper Cont with Flat lid (80Dia) | D20: 2.65 | E20: =D20+D20*H20 -> 3.127 | F20: Pcs | G20: 1000 | H20: 0.18
A21: 2 | B21: 39233090 | C21: Flat Black lid for 250ml (80Dia) | D21: 0.6 | E21: =D21+D21*H21 -> 0.708 | F21: Pcs | G21: 4000 | H21: 0.18
A22: Paknserve Reusable Cup Only (Flat Bottom)
A23: 1 | B23: 39233090 | C23: 250ML Paknserve Reusable Cup Only (80Dia) | D23: 2.05 | E23: =D23+D23*H23 -> 2.419 | F23: Pcs | G23: 1500 | H23: 0.18
A24: 2 | B24: 39233090 | C24: 300ML Paknserve Reusable Cup Only (80Dia) | D24: 2.35 | E24: =D24+D24*H24 -> 2.773 | F24: Pcs | G24: 1500 | H24: 0.18
A25: 3 | B25: 39233090 | C25: 350ml Paknserve Reusable Cup Only (80Dia) | D25: 2.8 | E25: =D25+D25*H25 -> 3.304 | F25: Pcs | G25: 1500 | H25: 0.18
A26: 4 | B26: 39233090 | C26: 350ml Paknserve Reusable Cup Only (90Dia) | D26: 2.75 | E26: =D26+D26*H26 -> 3.245 | F26: Pcs | G26: 1500 | H26: 0.18
A27: 5 | B27: 39233090 | C27: 500ml Paknserve Reusable Cup Only (90Dia) | D27: 3.7 | E27: =D27+D27*H27 -> 4.366 | F27: Pcs | G27: 1000 | H27: 0.18
A28: Sr. No. | B28: HSN Code | C28: Description | D28: Excl. Gst Rate | E28: Incl. Gst rate | F28: Unit | G28: Std. Pack. | H28: GST Extra
C29: RPPL Sipper SQ Container With Lid | I29: New Arrival
A30: 1 | B30: 39233090 | C30: 350ml RP SQR Sipper Cont Trans/Lid Black (WL) | D30: 4.75 | E30: =D30+D30*H30 -> 5.605 | F30: Pcs | G30: 1000 | H30: 0.18
A31: 2 | B31: 39233090 | C31: RP SQR Sipper Cont Trans/ Black Lid | D31: 1.3 | E31: =D31+D31*H31 -> 1.534 | F31: Pcs | G31: 1000 | H31: 0.18
C32: Paknserve 90Dia False bottom With Flip Top Lid | I32: New Arrival
A33: 1 | B33: 39233090 | C33: 350ml Paknserve Sipper Cont with Flip Top lid (90D) (False Bottom) | D33: 5.95 | E33: =D33+D33*H33 -> 7.021 | F33: Pcs | G33: 1000 | H33: 0.18
A34: 2 | B34: 39233090 | C34: 500ml Paknserve Sipper Cont with Flip Top lid (90D) (False Bottom) | D34: 6.95 | E34: =D34+D34*H34 -> 8.201 | F34: Pcs | G34: 1000 | H34: 0.18
A35: 3 | B35: 39233090 | C35: 90D Flip Top Sipper lid (Black /Red/White)for 250/300/350/500ml | D35: 3.1 | E35: =D35+D35*H35 -> 3.658 | F35: Pcs | G35: 4000 | H35: 0.18
C36: Paknserve 90Dia False bottom With Sipper Lid (Clear / Frosted) / Black Series
A37: 1 | B37: 39233090 | C37: 350ml Paknserve Frosted Trans Sipper Cont with Black lid (90D) | D37: 4.1 | E37: =D37+D37*H37 -> 4.838 | F37: Pcs | G37: 1000 | H37: 0.18
A38: 2 | B38: 39233090 | C38: 500ml Paknserve Frosted Trans Sipper Cont with Black lid (90D) | D38: 5.1 | E38: =D38+D38*H38 -> 6.018 | F38: Pcs | G38: 1000 | H38: 0.18
A39: 3 | B39: 39233090 | C39: 500ml (90D) Paknserve Party Sipper Cont with Black lid (Black/ Frosted/Glossy) | D39: 4.5 | E39: =D39+D39*H39 -> 5.31 | F39: Pcs | G39: 1000 | H39: 0.18
A40: 4 | B40: 39233090 | C40: 90D Sipper lid (Black/Clear)for 350/500ml | D40: 1.25 | E40: =D40+D40*H40 -> 1.475 | F40: Pcs | G40: 4000 | H40: 0.18
A41: 5 | B41: 39233090 | C41: 90D Sipper lid (Color)for 350/500ml | D41: 1.35 | E41: =D41+D41*H41 -> 1.593 | F41: Pcs | G41: 4000 | H41: 0.18
C42: Paknserve Freyo Tower with Reusable Glass | I42: New Arrival
A43: 1 | B43: 39233090 | C43: Freyo Tower | D43: 4.5 | E43: =D43+D43*H43 -> 5.31 | F43: Pcs | G43: 750 | H43: 0.18
A44: 2 | B44: 39233090 | C44: 250ML Paknserve Reusable Cup With Tower (80Dia) | D44: =D43+D23 -> 6.55 | E44: =D44+D44*H44 -> 7.729 | F44: Pcs | G44: 3000 | H44: 0.18
A45: 3 | B45: 39233090 | C45: 300ML Paknserve Reusable Cup With Tower (80Dia) | D45: =D43+D24 -> 6.85 | E45: =D45+D45*H45 -> 8.083 | F45: Pcs | G45: 3000 | H45: 0.18
A46: 4 | B46: 39233090 | C46: 350ml Paknserve Reusable Cup With Tower (80Dia) | D46: =D43+D25 -> 7.3 | E46: =D46+D46*H46 -> 8.614 | F46: Pcs | G46: 3000 | H46: 0.18
A47: 5 | B47: 39233090 | C47: 350ml Paknserve Reusable Cup With Tower (90Dia) False Bottom | D47: 7.35 | E47: =D47+D47*H47 -> 8.673 | F47: Pcs | G47: 1000 | H47: 0.18
A48: 6 | B48: 39233090 | C48: 500ml Paknserve Reusable Cup With Tower (90Dia) False Bottom | D48: 8.35 | E48: =D48+D48*H48 -> 9.853 | F48: Pcs | G48: 1000 | H48: 0.18
C49: SQ Lassi Cup With Lid | I49: New Arrival
A50: 1 | B50: 39233090 | C50: 200ml WC SQ Container (White) with Transparent Lid (WL) | D50: 3.65 | E50: =D50+D50*H50 -> 4.307 | F50: Pcs | G50: 2000 | H50: 0.18
A51: Terms & Condition
A52: 4. 100% Advance Payment.
A53: 2. The GST tax will be applicable as extra on above.
A54: 3. The above prices are subject to change.
A55: 1. The above prices are Ex Factory. Freight charges will be extra for outstation
A56: 5. Lead time required 4 to 5 days after receipt of the payment.
A57: 6.For Printing Order Lead time shall be 15days
A58: 6.Color Lid available in Black/Red/Green/Orange/Pink /White/Trans /Purple .

Sheet Pet Bottle & Jar 
A1: Neeyog Packaging
A2: OFF:20, Gr Floor,Sidhpura Ind.Estate,S.V.Road,Gaiwadi Rd,Near Agilus Diagnostic Center,Goregaon(W),Mum- 062
A3: Phone : 022-28760709 Mobile 9867607003 Email:neeyog@gmail.com
A4: www.neeyog.com/www.indiamart.com/neeyogpackaging/www.facebook.com/neeyogpack
A6: Wholesale Pet Bottle & Jar Containers Price List | F6: ='Summary Sheet'!C7 -> Date 16.06.2026
A7: SR No | B7: Image | C7: Description | D7: Rate Excl Gst | E7: Rate Incl Gst | F7: Per Pcs | G7: Std Pack | H7: GST Rate
C8: Ushape Pet Glasses
A9: 1 | C9: 300ML RP 92Dia U Shape Sipper (OB)* 1800 Pcs | D9: 2.3 | E9: =D9+D9*H9 -> 2.714 | F9: Pcs | G9: 1800 | H9: 0.18
A10: 2 | C10: 350ML RP 92Dia U Shape Sipper (OB)* 1800 Pcs | D10: 2.7 | E10: =D10+D10*H10 -> 3.186 | F10: Pcs | G10: 1800 | H10: 0.18
A11: 3 | C11: 420ML RP 92Dia U Shape Sipper (OB)* 1800 Pcs | D11: 3.1 | E11: =D11+D11*H11 -> 3.658 | F11: Pcs | G11: 1800 | H11: 0.18
A13: 1 | C13: 1232 92D ORA PET SIPPER LID*3600Pcs | D13: =Oracle!D261 -> 1.05 | E13: =D13+D13*18% -> 1.239 | F13: Pcs | G13: 3600 | H13: 0.18
A14: 2 | C14: 1233A 92 Dia ORA Flat Lid Straw cut * 7200Pcs | D14: =Oracle!D262 -> 0.71 | E14: =D14+D14*18% -> 0.8378 | F14: Pcs | G14: 7200 | H14: 0.18
A15: 3 | C15: 1234A 92 Dia ORA Dome Lid Straw cut * 5400Pcs | D15: =Oracle!D263 -> 0.9 | E15: =D15+D15*18% -> 1.062 | F15: Pcs | G15: 5400 | H15: 0.18
C16: PET Bottle With Lid (HSN Code 39233090) | D16: Rate Excl Gst | E16: Rate Incl Gst | F16: Per Pcs | G16: Std Pack | H16: GST Rate
A17: 1 | C17: 250ml SQ Pet Bottle AF (OB) (38D-16gm) * 135pc | D17: 5.05 | E17: =D17+D17*H17 -> 5.959 | F17: Pcs | G17: 135/10Bag | H17: 0.18 | J17: MM | K17: FM
A18: 2 | C18: 300ml RD Pet Bottle AF (OB) (38D-15gm) * 112pc | D18: 5.05 | E18: =D18+D18*H18 -> 5.959 | F18: Pcs | G18: 112/10Bag | H18: 0.18 | J18: MM | K18: FM
A19: 3 | C19: 200ml SQ Pet Bottle AF (OB) (38D-19gm) * 170pc | D19: 6 | E19: =D19+D19*H19 -> 7.08 | F19: Pcs | G19: 170/10Bag | H19: 0.18
